Workbook

Sheet Classify
B1: EXPORT CONTROL CLASSIFICATION TOOL — Document QA Front Page
B2: Formula-only, standalone. Basis: Wassenaar Arrangement Lists (WA-LIST (25) 1 Corr.), SA Controlled Items Schedule (GN 321/2012), National Conventional Arms Control Act 41 of 2002, Non-Proliferation of WMD Act 87 of 1993, Firearms Control Act 60 of 2000.
B3: Yellow = you type / select here | C3: Grey = label | D3: Red = EXPORT CONTROLLED | E3: Green = NOT controlled | F3: Amber = conditional / review
B5: STEP 1 — DESCRIBE THE DOCUMENT
B6: Document type (select from list) *
B7: Document number / title
B8: Scope / general paragraphs (paste the text — the tool scans it for controlled technical terms)
B16: STEP 2 — EXPORT CONTROL DECISION (automatic — no AI, formulas only)
B17: Default classification for this document type | C17: =IF($C$6="","",INDEX(Doc_Types!$C$2:$C$77,MATCH($C$6,Doc_Types!$A$2:$A$77,0))) | D17: V-model phase | E17: =IF($C$6="","",INDEX(Doc_Types!$B$2:$B$77,MATCH($C$6,Doc_Types!$A$2:$A$77,0)))
B18: Why this document type has that default | C18: =IF($C$6="","",INDEX(Doc_Types!$E$2:$E$77,MATCH($C$6,Doc_Types!$A$2:$A$77,0)))
B19: Typical control-list entry for this document type | C19: =IF($C$6="","",INDEX(Doc_Types!$D$2:$D$77,MATCH($C$6,Doc_Types!$A$2:$A$77,0)))
B20: Controlled technical keywords found in the scope text | C20: =SUMPRODUCT(--ISNUMBER(SEARCH(Keywords!$A$2:$A$136,$C$8)),--(Keywords!$A$2:$A$136<>"")) -> 0 | D20: =IF($C$17="Yes","(type is controlled regardless of keywords)",IF($C$17="Depends","Escalates to YES at "&$C$40&" or more hit(s)",IF($C$17="No","Escalates to YES at "&$C$41&" or more hit(s)","")))
B21: Keywords matched | C21: =IF($C$20=0,"none",LEFT(Keywords!$F$136,LEN(Keywords!$F$136)-2)) -> none
B22: Control-list entries indicated by those keywords | C22: =IF($C$20=0,"—",LEFT(Keywords!$G$136,LEN(Keywords!$G$136)-2)) -> —
B24: EXPORT CONTROLLED ? | C24: =IF($C$6="","— select a document type —",IF($C$17="Yes","YES",IF($C$17="Depends",IF($C$20>=$C$40,"YES","NO"),IF($C$20>=$C$41,"YES","NO")))) -> — select a document type — | E24: =IF($C$24="YES","Permit required before ANY transfer abroad or to a foreign person",IF($C$24="NO","No export permit needed for this document itself",""))
B25: Reason for the decision | C25: =IF($C$6="","",IF($C$17="Yes","Document type '"&$C$6&"' is by default EXPORT CONTROLLED. "&$C$18&" (Wassenaar ML22 'technology'; NCAC Act s1 'conventional arms' includes technology.)",IF($C$24="YES","Document type '"&$C$6&"' is by default '"&$C$17&"', BUT the scope text contains "&$C$20&" controlled technical term(s): "&$C$21&". Classification follows CONTENT, not title — technical data for a Munitions List item is 'technology' (Wassenaar ML22; NCAC Act s1).","Document type '"&$C$6&"' is by default '"&$C$17&"' ("&$C$18&") and the scope text contains "&$C$20&" controlled technical term(s), below the escalation threshold. No 'technology' (specific information necessary for development, production or use of a controlled item) identified.")))
B28: Legal basis | C28: =IF($C$6="","",IF($C$24="YES","Controlled item (technology) — NCAC Act 41 of 2002 s1, s13, s14; SA Controlled Items Schedule GN 321/2012; Wassenaar Munitions List "&$C$19&IF($C$20>0," and "&$C$22,"")&". Dual-use entries (3A/5A/6A/7A…) additionally fall under the Non-Proliferation Act 87/1993 (NPC permit).","Not a controlled item under the SA Controlled Items Schedule / Wassenaar Lists — no 'technology' as defined. NOTE: if this document is used to MARKET conventional arms abroad (brochure, proposal, tender) the activity itself still needs an NCACC marketing permit (NCAC Act s1, s13)."))
B30: Marking to apply to the document (follows the FINAL classification in C36) | C30: =IF($C$6="","",IF(LEFT($C$36,2)="NO",Markings_QA!$B$6,IF(LEFT($C$36,4)="DUAL",Markings_QA!$B$7,Markings_QA!$B$5)))
B33: STEP 3 — NEXT ACTION
B34: What to do now | C34: =IF($C$6="","Select a document type in Step 1.",IF($C$24="YES","Apply the EXPORT CONTROLLED marking. If the author believes the document should NOT be export controlled, go to the Mitigation tab (link on the right) and enter 1 to 3 grounds — the tool will tell you whether a downgrade is possible.","Apply the NOT EXPORT CONTROLLED marking and log the decision in the Register tab. No mitigation needed.")) -> Select a document type in Step 1. | F34: ➜ Go to Mitigation tab
B35: Mitigation verdict (from Mitigation tab) | C35: =IF($C$24<>"YES","n/a",IF(Mitigation!$C$16="NONE","none entered yet",Mitigation!$C$16)) -> n/a | E35: =IF($C$24<>"YES","",Mitigation!$C$15)
B36: FINAL CLASSIFICATION | C36: =IF($C$24<>"YES",$C$24,IF(AND(Mitigation!$C$16="ACCEPTED",Mitigation!$J$21="Confirm downgrade to NOT EXPORT CONTROLLED"),"NO — downgraded (ECO signed off)",IF(Mitigation!$C$16="ACCEPTED","YES — downgrade accepted, awaiting ECO sign-off",IF(Mitigation!$J$21="Re-classify as DUAL-USE CONTROLLED (NPC)","DUAL-USE CONTROLLED (NPC permit)","YES")))) -> — select a document type — | E36: =IF(LEFT($C$36,3)="YES","Document stays under NCACC permit control.",IF(LEFT($C$36,2)="NO","Document may be released without an export permit (marketing activity may still need one).",IF(LEFT($C$36,4)="DUAL","Route to the NPC (dtic) permit process.","")))
B38: RULE SETTINGS (Export Control Officer only — change only when company policy changes)
B39: Setting | C39: Value | D39: Meaning
B40: Escalation threshold for 'Depends' document types | C40: 1 | D40: Number of controlled keyword hits in the scope text that turns a 'Depends' type into YES. Policy default 1 (any controlled term = controlled).
B41: Escalation threshold for 'No' document types | C41: 2 | D41: Number of hits that turns a 'No' type (e.g. project plan) into YES. Policy default 2 (one stray word such as 'radar' does not control a schedule; two or more do).
B42: Tool version | C42: v1.0 — 17 Sep 2026 — list basis WA-LIST (25) 1 Corr.
B44: HOW TO USE (30 seconds)
B45: 1. Select the document type in C6 and paste the scope / general paragraphs into C8.
B46: 2. Read the decision in C24 and the reason in C25. Red = EXPORT CONTROLLED, green = NOT controlled.
B47: 3. If red and you disagree: Mitigation tab → choose 1-3 grounds, write your justification and evidence → read the verdict.
B48: 4. The Export Control Officer signs off on the Mitigation tab; the FINAL classification appears in C36.
B49: 5. Copy the marking text (C30) into the document and log the result on the Register tab.
B50: Many documents at once: use the Batch_Check tab (one row per document, same rules). Fact base: Doc_Types · Keywords · Mitigation_Grounds · Wassenaar_ML · Wassenaar_DualUse · Definitions · SA_Law · Penalties · Markings_QA.

Sheet Mitigation
B1: MITIGATION — Author's case for downgrading to NOT EXPORT CONTROLLED
B2: Only relevant when the Classify tab says YES. Choose up to three grounds; the tool applies the Wassenaar General Technology Note, the Definitions and the NCAC Act rules and tells you whether each ground is ACCEPTED, CONDITIONAL or REJECTED — and why.
B3: Document | C3: =IF(Classify!$C$6="","— none selected on Classify tab —",Classify!$C$6&IF(Classify!$C$7<>""," | "&Classify!$C$7,"")) -> — none selected on Classify tab — | F3: Matched keywords: | G3: =Classify!$C$21 -> none
B4: Initial | C4: =Classify!$C$24 -> — select a document type — | D4: Keyword hits in scope text | E4: =Classify!$C$20 -> 0
B5: hits | C5: =Classify!$C$20 -> 0 | D5: Default classification of this document type | E5: =Classify!$C$17
B6: default | C6: =Classify!$C$17
B8: STEP 3 — AUTHOR'S GROUNDS (select a ground, write the justification, give the evidence)
B9: # | C9: Mitigation ground (select) | D9: Author's justification (free text) | E9: Evidence reference (URL / publication / standard / permit no.) | F9: Outcome | G9: Why (automatic, rule-based) | H9: Fact base tab
B10: 1 | F10: =IF($C10="","",IF($D10="","INCOMPLETE",IF($J10="NONE",$K10,IF($J10="EVIDENCE",IF($E10<>"","ACCEPTED","CONDITIONAL"),IF($J10="NOHITS",IF($C$6="Yes","REJECTED",IF($C$5>0,"REJECTED","ACCEPTED")),IF($J10="NOTPRODUCT",IF($C$6="Yes","REJECTED","CONDITIONAL"),IF($J10="REVIEW","CONDITIONAL",$K10))))))) | G10: =IF($C10="","",IF($F10="INCOMPLETE","Write the author's justification in column D — an outcome is only given for a stated case.",IF($F10="ACCEPTED",INDEX(Mitigation_Grounds!$E$2:$E$17,MATCH($C10,Mitigation_Grounds!$B$2:$B$17,0)),IF($F10="CONDITIONAL",INDEX(Mitigation_Grounds!$F$2:$F$17,MATCH($C10,Mitigation_Grounds!$B$2:$B$17,0)),INDEX(Mitigation_Grounds!$G$2:$G$17,MATCH($C10,Mitigation_Grounds!$B$2:$B$17,0))&IF(AND($J10="NOHITS",$C$5>0)," Keywords found in the scope text: "&Classify!$C$21,""))))) | H10: =IF($C10="","",INDEX(Mitigation_Grounds!$I$2:$I$17,MATCH($C10,Mitigation_Grounds!$B$2:$B$17,0))) | J10: =IF($C10="","",INDEX(Mitigation_Grounds!$C$2:$C$17,MATCH($C10,Mitigation_Grounds!$B$2:$B$17,0))) | K10: =IF($C10="","",INDEX(Mitigation_Grounds!$D$2:$D$17,MATCH($C10,Mitigation_Grounds!$B$2:$B$17,0)))
B11: 2 | F11: =IF($C11="","",IF($D11="","INCOMPLETE",IF($J11="NONE",$K11,IF($J11="EVIDENCE",IF($E11<>"","ACCEPTED","CONDITIONAL"),IF($J11="NOHITS",IF($C$6="Yes","REJECTED",IF($C$5>0,"REJECTED","ACCEPTED")),IF($J11="NOTPRODUCT",IF($C$6="Yes","REJECTED","CONDITIONAL"),IF($J11="REVIEW","CONDITIONAL",$K11))))))) | G11: =IF($C11="","",IF($F11="INCOMPLETE","Write the author's justification in column D — an outcome is only given for a stated case.",IF($F11="ACCEPTED",INDEX(Mitigation_Grounds!$E$2:$E$17,MATCH($C11,Mitigation_Grounds!$B$2:$B$17,0)),IF($F11="CONDITIONAL",INDEX(Mitigation_Grounds!$F$2:$F$17,MATCH($C11,Mitigation_Grounds!$B$2:$B$17,0)),INDEX(Mitigation_Grounds!$G$2:$G$17,MATCH($C11,Mitigation_Grounds!$B$2:$B$17,0))&IF(AND($J11="NOHITS",$C$5>0)," Keywords found in the scope text: "&Classify!$C$21,""))))) | H11: =IF($C11="","",INDEX(Mitigation_Grounds!$I$2:$I$17,MATCH($C11,Mitigation_Grounds!$B$2:$B$17,0))) | J11: =IF($C11="","",INDEX(Mitigation_Grounds!$C$2:$C$17,MATCH($C11,Mitigation_Grounds!$B$2:$B$17,0))) | K11: =IF($C11="","",INDEX(Mitigation_Grounds!$D$2:$D$17,MATCH($C11,Mitigation_Grounds!$B$2:$B$17,0)))
B12: 3 | F12: =IF($C12="","",IF($D12="","INCOMPLETE",IF($J12="NONE",$K12,IF($J12="EVIDENCE",IF($E12<>"","ACCEPTED","CONDITIONAL"),IF($J12="NOHITS",IF($C$6="Yes","REJECTED",IF($C$5>0,"REJECTED","ACCEPTED")),IF($J12="NOTPRODUCT",IF($C$6="Yes","REJECTED","CONDITIONAL"),IF($J12="REVIEW","CONDITIONAL",$K12))))))) | G12: =IF($C12="","",IF($F12="INCOMPLETE","Write the author's justification in column D — an outcome is only given for a stated case.",IF($F12="ACCEPTED",INDEX(Mitigation_Grounds!$E$2:$E$17,MATCH($C12,Mitigation_Grounds!$B$2:$B$17,0)),IF($F12="CONDITIONAL",INDEX(Mitigation_Grounds!$F$2:$F$17,MATCH($C12,Mitigation_Grounds!$B$2:$B$17,0)),INDEX(Mitigation_Grounds!$G$2:$G$17,MATCH($C12,Mitigation_Grounds!$B$2:$B$17,0))&IF(AND($J12="NOHITS",$C$5>0)," Keywords found in the scope text: "&Classify!$C$21,""))))) | H12: =IF($C12="","",INDEX(Mitigation_Grounds!$I$2:$I$17,MATCH($C12,Mitigation_Grounds!$B$2:$B$17,0))) | J12: =IF($C12="","",INDEX(Mitigation_Grounds!$C$2:$C$17,MATCH($C12,Mitigation_Grounds!$B$2:$B$17,0))) | K12: =IF($C12="","",INDEX(Mitigation_Grounds!$D$2:$D$17,MATCH($C12,Mitigation_Grounds!$B$2:$B$17,0)))
B14: VERDICT (automatic)
B15: Verdict | C15: =IF($C$4<>"YES","n/a — the document is already NOT Export Controlled (or no document type has been selected on the Classify tab).",IF(COUNTIF($F$10:$F$12,"ACCEPTED")>0,"DOWNGRADE POSSIBLE — at least one ground is ACCEPTED on the facts entered. The document may be re-marked NOT EXPORT CONTROLLED only after the Export Control Officer signs off below (Step 4).",IF(COUNTIF($F$10:$F$12,"CONDITIONAL")>0,"DOWNGRADE POSSIBLE ONLY IF THE CONDITION IS MET — see column G for exactly what the Export Control Officer must verify. Until then the document REMAINS EXPORT CONTROLLED.",IF(COUNTIF($F$10:$F$12,"INCOMPLETE")>0,"INCOMPLETE — write the justification for every ground selected.",IF(COUNTA($C$10:$C$12)=0,"REMAINS EXPORT CONTROLLED — no grounds entered yet.","DOWNGRADE NOT POSSIBLE — every ground entered is REJECTED (column G explains why). The document REMAINS EXPORT CONTROLLED."))))) -> n/a — the document is already NOT Export Controlled (or no document type has been selected on the Classify tab).
B16: Code | C16: =IF($C$4<>"YES","NA",IF(COUNTIF($F$10:$F$12,"ACCEPTED")>0,"ACCEPTED",IF(COUNTIF($F$10:$F$12,"CONDITIONAL")>0,"CONDITIONAL",IF(COUNTIF($F$10:$F$12,"INCOMPLETE")>0,"INCOMPLETE",IF(COUNTA($C$10:$C$12)=0,"NONE","REJECTED"))))) -> NA | D16: Grounds 7, 8, 9, 10, 12 and 13 are always REJECTED — they describe the recipient, destination, permit status, intent, dual-use nature or age, none of which changes what the document IS.
B18: STEP 4 — EXPORT CONTROL OFFICER SIGN-OFF (the ECO's decision is final; the author cannot self-downgrade)
C19: Export Control Officer name | F19: =IF($C$16="ACCEPTED",IF($D$21="Confirm downgrade to NOT EXPORT CONTROLLED","Sign-off complete — apply the NOT EXPORT CONTROLLED marking.","Awaiting ECO sign-off — document remains EXPORT CONTROLLED."),IF($C$16="CONDITIONAL","ECO must verify the condition in column G before choosing a decision.",IF($C$16="NA","","No accepted ground — the only lawful decisions are Maintain, Sanitise or Re-classify as Dual-Use.")))
C20: Date of decision
C21: ECO decision (select) | J21: =$D$21 -> 0
C22: ECO comments / conditions verified
B24: LIABILITY NOTE — Under the NCAC Act s24 the offence of transferring a controlled item without a permit carries up to 25 years' imprisonment, and under the Criminal Procedure Act s332 the company's directors and managers are personally liable unless they prove they could not have prevented it. This sheet, completed and signed, is the evidence that all reasonable steps were taken. A downgrade is never the author's decision alone.

Sheet Batch_Check
A1: BATCH CHECK — classify a table of documents by document type against the Wassenaar Lists
A2: One row per document. Select the document type (column D); optionally paste the scope / description (column E) so the keyword scan can escalate or confirm. Columns F-K are automatic and use the same rules and thresholds as the Classify tab. To argue a YES down, copy that row's type and text into the Classify tab and use the Mitigation tab.
B4: Documents listed | C4: ="Rules: type default Yes → YES; Depends → YES at "&Classify!$C$40&"+ keyword hit(s) (REVIEW if no text given); No → YES at "&Classify!$C$41&"+ hits. Thresholds live on the Classify tab." -> Rules: type default Yes → YES; Depends → YES at 1+ keyword hit(s) (REVIEW if no text given); No → YES at 2+ hits. Thresholds live on the Classify tab. | D4: EXPORT CONTROLLED | E4: NOT EXPORT CONTROLLED | H4: REVIEW (needs scope text)
B5: =COUNTA($D$8:$D$207) -> 3 | D5: =COUNTIF($H$8:$H$207,"YES") -> 1 | E5: =COUNTIF($H$8:$H$207,"NO") -> 1 | H5: =COUNTIF($H$8:$H$207,"REVIEW*") -> 1
A7: # | B7: Document number | C7: Title | D7: Document type (select) | E7: Scope / description (optional — paste text) | F7: Type default | G7: Keyword hits | H7: EXPORT CONTROLLED ? | I7: Wassenaar / SA entry | J7: Reason | K7: Marking to apply
A8: 1 | B8: EW-SRS-0042 | C8: Radar Warning Receiver LRU — System Requirements Specification | D8: System Requirements Specification (SRS) | E8: Defines the RWR LRU: 2-18 GHz, sensitivity -65 dBm, pulse descriptor word output. | F8: =IF($D8="","",INDEX(Doc_Types!$C$2:$C$77,MATCH($D8,DocTypeList,0))) -> Yes | G8: =IF($D8="","",IF($E8="",0,SUMPRODUCT(--ISNUMBER(SEARCH(Keywords!$A$2:$A$136,$E8)),--(Keywords!$A$2:$A$136<>"")))) -> 5 | H8: =IF($D8="","",IF($F8="Yes","YES",IF(AND($F8="Depends",$E8=""),"REVIEW — add scope text",IF($F8="Depends",IF($G8>=Classify!$C$40,"YES","NO"),IF($G8>=Classify!$C$41,"YES","NO"))))) -> YES | I8: =IF($D8="","",INDEX(Doc_Types!$D$2:$D$77,MATCH($D8,DocTypeList,0))) -> ML22 (technology for ML11/ML10/ML5 items) | J8: =IF($D8="","",IF($F8="Yes",INDEX(Doc_Types!$E$2:$E$77,MATCH($D8,DocTypeList,0)),IF(LEFT($H8,6)="REVIEW","Type is 'Depends' — classification is decided by content; paste the scope text to resolve.",IF($H8="YES","Type default is '"&$F8&"' but the text contains "&$G8&" controlled technical term(s) — classification follows content (Wassenaar ML22 technology).",INDEX(Doc_Types!$E$2:$E$77,MATCH($D8,DocTypeList,0))&" Text scan: "&$G8&" controlled term(s), below threshold.")))) -> Quantified requirements for a military system are 'technology' required for its development. | K8: =IF($H8="YES","EXPORT CONTROLLED",IF($H8="NO","NOT EXPORT CONTROLLED",IF($D8="","","— pending review —"))) -> EXPORT CONTROLLED
A9: 2 | B9: EW-PMP-0001 | C9: Programme Management Plan | D9: Project Management Plan / Schedule / WBS | E9: Milestones, budget, resourcing and review schedule. | F9: =IF($D9="","",INDEX(Doc_Types!$C$2:$C$77,MATCH($D9,DocTypeList,0))) -> No | G9: =IF($D9="","",IF($E9="",0,SUMPRODUCT(--ISNUMBER(SEARCH(Keywords!$A$2:$A$136,$E9)),--(Keywords!$A$2:$A$136<>"")))) -> 0 | H9: =IF($D9="","",IF($F9="Yes","YES",IF(AND($F9="Depends",$E9=""),"REVIEW — add scope text",IF($F9="Depends",IF($G9>=Classify!$C$40,"YES","NO"),IF($G9>=Classify!$C$41,"YES","NO"))))) -> NO | I9: =IF($D9="","",INDEX(Doc_Types!$D$2:$D$77,MATCH($D9,DocTypeList,0))) -> n/a | J9: =IF($D9="","",IF($F9="Yes",INDEX(Doc_Types!$E$2:$E$77,MATCH($D9,DocTypeList,0)),IF(LEFT($H9,6)="REVIEW","Type is 'Depends' — classification is decided by content; paste the scope text to resolve.",IF($H9="YES","Type default is '"&$F9&"' but the text contains "&$G9&" controlled technical term(s) — classification follows content (Wassenaar ML22 technology).",INDEX(Doc_Types!$E$2:$E$77,MATCH($D9,DocTypeList,0))&" Text scan: "&$G9&" controlled term(s), below threshold.")))) -> Programme management information is not 'technology' (no development, production or use information). Text scan: 0 controlled term(s), below threshold. | K9: =IF($H9="YES","EXPORT CONTROLLED",IF($H9="NO","NOT EXPORT CONTROLLED",IF($D9="","","— pending review —"))) -> NOT EXPORT CONTROLLED
A10: 3 | B10: EW-CON-0007 | C10: Concept of Operations — Self-Protection Suite | D10: Concept of Operations (ConOps) | F10: =IF($D10="","",INDEX(Doc_Types!$C$2:$C$77,MATCH($D10,DocTypeList,0))) -> Depends | G10: =IF($D10="","",IF($E10="",0,SUMPRODUCT(--ISNUMBER(SEARCH(Keywords!$A$2:$A$136,$E10)),--(Keywords!$A$2:$A$136<>"")))) -> 0 | H10: =IF($D10="","",IF($F10="Yes","YES",IF(AND($F10="Depends",$E10=""),"REVIEW — add scope text",IF($F10="Depends",IF($G10>=Classify!$C$40,"YES","NO"),IF($G10>=Classify!$C$41,"YES","NO"))))) -> REVIEW — add scope text | I10: =IF($D10="","",INDEX(Doc_Types!$D$2:$D$77,MATCH($D10,DocTypeList,0))) -> ML22 / ML11 | J10: =IF($D10="","",IF($F10="Yes",INDEX(Doc_Types!$E$2:$E$77,MATCH($D10,DocTypeList,0)),IF(LEFT($H10,6)="REVIEW","Type is 'Depends' — classification is decided by content; paste the scope text to resolve.",IF($H10="YES","Type default is '"&$F10&"' but the text contains "&$G10&" controlled technical term(s) — classification follows content (Wassenaar ML22 technology).",INDEX(Doc_Types!$E$2:$E$77,MATCH($D10,DocTypeList,0))&" Text scan: "&$G10&" controlled term(s), below threshold.")))) -> Type is 'Depends' — classification is decided by content; paste the scope text to resolve. | K10: =IF($H10="YES","EXPORT CONTROLLED",IF($H10="NO","NOT EXPORT CONTROLLED",IF($D10="","","— pending review —"))) -> — pending review —
A11: 4 | F11: =IF($D11="","",INDEX(Doc_Types!$C$2:$C$77,MATCH($D11,DocTypeList,0))) | G11: =IF($D11="","",IF($E11="",0,SUMPRODUCT(--ISNUMBER(SEARCH(Keywords!$A$2:$A$136,$E11)),--(Keywords!$A$2:$A$136<>"")))) | H11: =IF($D11="","",IF($F11="Yes","YES",IF(AND($F11="Depends",$E11=""),"REVIEW — add scope text",IF($F11="Depends",IF($G11>=Classify!$C$40,"YES","NO"),IF($G11>=Classify!$C$41,"YES","NO"))))) | I11: =IF($D11="","",INDEX(Doc_Types!$D$2:$D$77,MATCH($D11,DocTypeList,0))) | J11: =IF($D11="","",IF($F11="Yes",INDEX(Doc_Types!$E$2:$E$77,MATCH($D11,DocTypeList,0)),IF(LEFT($H11,6)="REVIEW","Type is 'Depends' — classification is decided by content; paste the scope text to resolve.",IF($H11="YES","Type default is '"&$F11&"' but the text contains "&$G11&" controlled technical term(s) — classification follows content (Wassenaar ML22 technology).",INDEX(Doc_Types!$E$2:$E$77,MATCH($D11,DocTypeList,0))&" Text scan: "&$G11&" controlled term(s), below threshold.")))) | K11: =IF($H11="YES","EXPORT CONTROLLED",IF($H11="NO","NOT EXPORT CONTROLLED",IF($D11="","","— pending review —")))
A12: 5 | F12: =IF($D12="","",INDEX(Doc_Types!$C$2:$C$77,MATCH($D12,DocTypeList,0))) | G12: =IF($D12="","",IF($E12="",0,SUMPRODUCT(--ISNUMBER(SEARCH(Keywords!$A$2:$A$136,$E12)),--(Keywords!$A$2:$A$136<>"")))) | H12: =IF($D12="","",IF($F12="Yes","YES",IF(AND($F12="Depends",$E12=""),"REVIEW — add scope text",IF($F12="Depends",IF($G12>=Classify!$C$40,"YES","NO"),IF($G12>=Classify!$C$41,"YES","NO"))))) | I12: =IF($D12="","",INDEX(Doc_Types!$D$2:$D$77,MATCH($D12,DocTypeList,0))) | J12: =IF($D12="","",IF($F12="Yes",INDEX(Doc_Types!$E$2:$E$77,MATCH($D12,DocTypeList,0)),IF(LEFT($H12,6)="REVIEW","Type is 'Depends' — classification is decided by content; paste the scope text to resolve.",IF($H12="YES","Type default is '"&$F12&"' but the text contains "&$G12&" controlled technical term(s) — classification follows content (Wassenaar ML22 technology).",INDEX(Doc_Types!$E$2:$E$77,MATCH($D12,DocTypeList,0))&" Text scan: "&$G12&" controlled term(s), below threshold.")))) | K12: =IF($H12="YES","EXPORT CONTROLLED",IF($H12="NO","NOT EXPORT CONTROLLED",IF($D12="","","— pending review —")))
A13: 6 | F13: =IF($D13="","",INDEX(Doc_Types!$C$2:$C$77,MATCH($D13,DocTypeList,0))) | G13: =IF($D13="","",IF($E13="",0,SUMPRODUCT(--ISNUMBER(SEARCH(Keywords!$A$2:$A$136,$E13)),--(Keywords!$A$2:$A$136<>"")))) | H13: =IF($D13="","",IF($F13="Yes","YES",IF(AND($F13="Depends",$E13=""),"REVIEW — add scope text",IF($F13="Depends",IF($G13>=Classify!$C$40,"YES","NO"),IF($G13>=Classify!$C$41,"YES","NO"))))) | I13: =IF($D13="","",INDEX(Doc_Types!$D$2:$D$77,MATCH($D13,DocTypeList,0))) | J13: =IF($D13="","",IF($F13="Yes",INDEX(Doc_Types!$E$2:$E$77,MATCH($D13,DocTypeList,0)),IF(LEFT($H13,6)="REVIEW","Type is 'Depends' — classification is decided by content; paste the scope text to resolve.",IF($H13="YES","Type default is '"&$F13&"' but the text contains "&$G13&" controlled technical term(s) — classification follows content (Wassenaar ML22 technology).",INDEX(Doc_Types!$E$2:$E$77,MATCH($D13,DocTypeList,0))&" Text scan: "&$G13&" controlled term(s), below threshold.")))) | K13: =IF($H13="YES","EXPORT CONTROLLED",IF($H13="NO","NOT EXPORT CONTROLLED",IF($D13="","","— pending review —")))
A14: 7 | F14: =IF($D14="","",INDEX(Doc_Types!$C$2:$C$77,MATCH($D14,DocTypeList,0))) | G14: =IF($D14="","",IF($E14="",0,SUMPRODUCT(--ISNUMBER(SEARCH(Keywords!$A$2:$A$136,$E14)),--(Keywords!$A$2:$A$136<>"")))) | H14: =IF($D14="","",IF($F14="Yes","YES",IF(AND($F14="Depends",$E14=""),"REVIEW — add scope text",IF($F14="Depends",IF($G14>=Classify!$C$40,"YES","NO"),IF($G14>=Classify!$C$41,"YES","NO"))))) | I14: =IF($D14="","",INDEX(Doc_Types!$D$2:$D$77,MATCH($D14,DocTypeList,0))) | J14: =IF($D14="","",IF($F14="Yes",INDEX(Doc_Types!$E$2:$E$77,MATCH($D14,DocTypeList,0)),IF(LEFT($H14,6)="REVIEW","Type is 'Depends' — classification is decided by content; paste the scope text to resolve.",IF($H14="YES","Type default is '"&$F14&"' but the text contains "&$G14&" controlled technical term(s) — classification follows content (Wassenaar ML22 technology).",INDEX(Doc_Types!$E$2:$E$77,MATCH($D14,DocTypeList,0))&" Text scan: "&$G14&" controlled term(s), below threshold.")))) | K14: =IF($H14="YES","EXPORT CONTROLLED",IF($H14="NO","NOT EXPORT CONTROLLED",IF($D14="","","— pending review —")))
A15: 8 | F15: =IF($D15="","",INDEX(Doc_Types!$C$2:$C$77,MATCH($D15,DocTypeList,0))) | G15: =IF($D15="","",IF($E15="",0,SUMPRODUCT(--ISNUMBER(SEARCH(Keywords!$A$2:$A$136,$E15)),--(Keywords!$A$2:$A$136<>"")))) | H15: =IF($D15="","",IF($F15="Yes","YES",IF(AND($F15="Depends",$E15=""),"REVIEW — add scope text",IF($F15="Depends",IF($G15>=Classify!$C$40,"YES","NO"),IF($G15>=Classify!$C$41,"YES","NO"))))) | I15: =IF($D15="","",INDEX(Doc_Types!$D$2:$D$77,MATCH($D15,DocTypeList,0))) | J15: =IF($D15="","",IF($F15="Yes",INDEX(Doc_Types!$E$2:$E$77,MATCH($D15,DocTypeList,0)),IF(LEFT($H15,6)="REVIEW","Type is 'Depends' — classification is decided by content; paste the scope text to resolve.",IF($H15="YES","Type default is '"&$F15&"' but the text contains "&$G15&" controlled technical term(s) — classification follows content (Wassenaar ML22 technology).",INDEX(Doc_Types!$E$2:$E$77,MATCH($D15,DocTypeList,0))&" Text scan: "&$G15&" controlled term(s), below threshold.")))) | K15: =IF($H15="YES","EXPORT CONTROLLED",IF($H15="NO","NOT EXPORT CONTROLLED",IF($D15="","","— pending review —")))
A16: 9 | F16: =IF($D16="","",INDEX(Doc_Types!$C$2:$C$77,MATCH($D16,DocTypeList,0))) | G16: =IF($D16="","",IF($E16="",0,SUMPRODUCT(--ISNUMBER(SEARCH(Keywords!$A$2:$A$136,$E16)),--(Keywords!$A$2:$A$136<>"")))) | H16: =IF($D16="","",IF($F16="Yes","YES",IF(AND($F16="Depends",$E16=""),"REVIEW — add scope text",IF($F16="Depends",IF($G16>=Classify!$C$40,"YES","NO"),IF($G16>=Classify!$C$41,"YES","NO"))))) | I16: =IF($D16="","",INDEX(Doc_Types!$D$2:$D$77,MATCH($D16,DocTypeList,0))) | J16: =IF($D16="","",IF($F16="Yes",INDEX(Doc_Types!$E$2:$E$77,MATCH($D16,DocTypeList,0)),IF(LEFT($H16,6)="REVIEW","Type is 'Depends' — classification is decided by content; paste the scope text to resolve.",IF($H16="YES","Type default is '"&$F16&"' but the text contains "&$G16&" controlled technical term(s) — classification follows content (Wassenaar ML22 technology).",INDEX(Doc_Types!$E$2:$E$77,MATCH($D16,DocTypeList,0))&" Text scan: "&$G16&" controlled term(s), below threshold.")))) | K16: =IF($H16="YES","EXPORT CONTROLLED",IF($H16="NO","NOT EXPORT CONTROLLED",IF($D16="","","— pending review —")))
A17: 10 | F17: =IF($D17="","",INDEX(Doc_Types!$C$2:$C$77,MATCH($D17,DocTypeList,0))) | G17: =IF($D17="","",IF($E17="",0,SUMPRODUCT(--ISNUMBER(SEARCH(Keywords!$A$2:$A$136,$E17)),--(Keywords!$A$2:$A$136<>"")))) | H17: =IF($D17="","",IF($F17="Yes","YES",IF(AND($F17="Depends",$E17=""),"REVIEW — add scope text",IF($F17="Depends",IF($G17>=Classify!$C$40,"YES","NO"),IF($G17>=Classify!$C$41,"YES","NO"))))) | I17: =IF($D17="","",INDEX(Doc_Types!$D$2:$D$77,MATCH($D17,DocTypeList,0))) | J17: =IF($D17="","",IF($F17="Yes",INDEX(Doc_Types!$E$2:$E$77,MATCH($D17,DocTypeList,0)),IF(LEFT($H17,6)="REVIEW","Type is 'Depends' — classification is decided by content; paste the scope text to resolve.",IF($H17="YES","Type default is '"&$F17&"' but the text contains "&$G17&" controlled technical term(s) — classification follows content (Wassenaar ML22 technology).",INDEX(Doc_Types!$E$2:$E$77,MATCH($D17,DocTypeList,0))&" Text scan: "&$G17&" controlled term(s), below threshold.")))) | K17: =IF($H17="YES","EXPORT CONTROLLED",IF($H17="NO","NOT EXPORT CONTROLLED",IF($D17="","","— pending review —")))
A18: 11 | F18: =IF($D18="","",INDEX(Doc_Types!$C$2:$C$77,MATCH($D18,DocTypeList,0))) | G18: =IF($D18="","",IF($E18="",0,SUMPRODUCT(--ISNUMBER(SEARCH(Keywords!$A$2:$A$136,$E18)),--(Keywords!$A$2:$A$136<>"")))) | H18: =IF($D18="","",IF($F18="Yes","YES",IF(AND($F18="Depends",$E18=""),"REVIEW — add scope text",IF($F18="Depends",IF($G18>=Classify!$C$40,"YES","NO"),IF($G18>=Classify!$C$41,"YES","NO"))))) | I18: =IF($D18="","",INDEX(Doc_Types!$D$2:$D$77,MATCH($D18,DocTypeList,0))) | J18: =IF($D18="","",IF($F18="Yes",INDEX(Doc_Types!$E$2:$E$77,MATCH($D18,DocTypeList,0)),IF(LEFT($H18,6)="REVIEW","Type is 'Depends' — classification is decided by content; paste the scope text to resolve.",IF($H18="YES","Type default is '"&$F18&"' but the text contains "&$G18&" controlled technical term(s) — classification follows content (Wassenaar ML22 technology).",INDEX(Doc_Types!$E$2:$E$77,MATCH($D18,DocTypeList,0))&" Text scan: "&$G18&" controlled term(s), below threshold.")))) | K18: =IF($H18="YES","EXPORT CONTROLLED",IF($H18="NO","NOT EXPORT CONTROLLED",IF($D18="","","— pending review —")))
A19: 12 | F19: =IF($D19="","",INDEX(Doc_Types!$C$2:$C$77,MATCH($D19,DocTypeList,0))) | G19: =IF($D19="","",IF($E19="",0,SUMPRODUCT(--ISNUMBER(SEARCH(Keywords!$A$2:$A$136,$E19)),--(Keywords!$A$2:$A$136<>"")))) | H19: =IF($D19="","",IF($F19="Yes","YES",IF(AND($F19="Depends",$E19=""),"REVIEW — add scope text",IF($F19="Depends",IF($G19>=Classify!$C$40,"YES","NO"),IF($G19>=Classify!$C$41,"YES","NO"))))) | I19: =IF($D19="","",INDEX(Doc_Types!$D$2:$D$77,MATCH($D19,DocTypeList,0))) | J19: =IF($D19="","",IF($F19="Yes",INDEX(Doc_Types!$E$2:$E$77,MATCH($D19,DocTypeList,0)),IF(LEFT($H19,6)="REVIEW","Type is 'Depends' — classification is decided by content; paste the scope text to resolve.",IF($H19="YES","Type default is '"&$F19&"' but the text contains "&$G19&" controlled technical term(s) — classification follows content (Wassenaar ML22 technology).",INDEX(Doc_Types!$E$2:$E$77,MATCH($D19,DocTypeList,0))&" Text scan: "&$G19&" controlled term(s), below threshold.")))) | K19: =IF($H19="YES","EXPORT CONTROLLED",IF($H19="NO","NOT EXPORT CONTROLLED",IF($D19="","","— pending review —")))
A20: 13 | F20: =IF($D20="","",INDEX(Doc_Types!$C$2:$C$77,MATCH($D20,DocTypeList,0))) | G20: =IF($D20="","",IF($E20="",0,SUMPRODUCT(--ISNUMBER(SEARCH(Keywords!$A$2:$A$136,$E20)),--(Keywords!$A$2:$A$136<>"")))) | H20: =IF($D20="","",IF($F20="Yes","YES",IF(AND($F20="Depends",$E20=""),"REVIEW — add scope text",IF($F20="Depends",IF($G20>=Classify!$C$40,"YES","NO"),IF($G20>=Classify!$C$41,"YES","NO"))))) | I20: =IF($D20="","",INDEX(Doc_Types!$D$2:$D$77,MATCH($D20,DocTypeList,0))) | J20: =IF($D20="","",IF($F20="Yes",INDEX(Doc_Types!$E$2:$E$77,MATCH($D20,DocTypeList,0)),IF(LEFT($H20,6)="REVIEW","Type is 'Depends' — classification is decided by content; paste the scope text to resolve.",IF($H20="YES","Type default is '"&$F20&"' but the text contains "&$G20&" controlled technical term(s) — classification follows content (Wassenaar ML22 technology).",INDEX(Doc_Types!$E$2:$E$77,MATCH($D20,DocTypeList,0))&" Text scan: "&$G20&" controlled term(s), below threshold.")))) | K20: =IF($H20="YES","EXPORT CONTROLLED",IF($H20="NO","NOT EXPORT CONTROLLED",IF($D20="","","— pending review —")))
A21: 14 | F21: =IF($D21="","",INDEX(Doc_Types!$C$2:$C$77,MATCH($D21,DocTypeList,0))) | G21: =IF($D21="","",IF($E21="",0,SUMPRODUCT(--ISNUMBER(SEARCH(Keywords!$A$2:$A$136,$E21)),--(Keywords!$A$2:$A$136<>"")))) | H21: =IF($D21="","",IF($F21="Yes","YES",IF(AND($F21="Depends",$E21=""),"REVIEW — add scope text",IF($F21="Depends",IF($G21>=Classify!$C$40,"YES","NO"),IF($G21>=Classify!$C$41,"YES","NO"))))) | I21: =IF($D21="","",INDEX(Doc_Types!$D$2:$D$77,MATCH($D21,DocTypeList,0))) | J21: =IF($D21="","",IF($F21="Yes",INDEX(Doc_Types!$E$2:$E$77,MATCH($D21,DocTypeList,0)),IF(LEFT($H21,6)="REVIEW","Type is 'Depends' — classification is decided by content; paste the scope text to resolve.",IF($H21="YES","Type default is '"&$F21&"' but the text contains "&$G21&" controlled technical term(s) — classification follows content (Wassenaar ML22 technology).",INDEX(Doc_Types!$E$2:$E$77,MATCH($D21,DocTypeList,0))&" Text scan: "&$G21&" controlled term(s), below threshold.")))) | K21: =IF($H21="YES","EXPORT CONTROLLED",IF($H21="NO","NOT EXPORT CONTROLLED",IF($D21="","","— pending review —")))
A22: 15 | F22: =IF($D22="","",INDEX(Doc_Types!$C$2:$C$77,MATCH($D22,DocTypeList,0))) | G22: =IF($D22="","",IF($E22="",0,SUMPRODUCT(--ISNUMBER(SEARCH(Keywords!$A$2:$A$136,$E22)),--(Keywords!$A$2:$A$136<>"")))) | H22: =IF($D22="","",IF($F22="Yes","YES",IF(AND($F22="Depends",$E22=""),"REVIEW — add scope text",IF($F22="Depends",IF($G22>=Classify!$C$40,"YES","NO"),IF($G22>=Classify!$C$41,"YES","NO"))))) | I22: =IF($D22="","",INDEX(Doc_Types!$D$2:$D$77,MATCH($D22,DocTypeList,0))) | J22: =IF($D22="","",IF($F22="Yes",INDEX(Doc_Types!$E$2:$E$77,MATCH($D22,DocTypeList,0)),IF(LEFT($H22,6)="REVIEW","Type is 'Depends' — classification is decided by content; paste the scope text to resolve.",IF($H22="YES","Type default is '"&$F22&"' but the text contains "&$G22&" controlled technical term(s) — classification follows content (Wassenaar ML22 technology).",INDEX(Doc_Types!$E$2:$E$77,MATCH($D22,DocTypeList,0))&" Text scan: "&$G22&" controlled term(s), below threshold.")))) | K22: =IF($H22="YES","EXPORT CONTROLLED",IF($H22="NO","NOT EXPORT CONTROLLED",IF($D22="","","— pending review —")))
... A207: 200 | F207: =IF($D207="","",INDEX(Doc_Types!$C$2:$C$77,MATCH($D207,DocTypeList,0))) | G207: =IF($D207="","",IF($E207="",0,SUMPRODUCT(--ISNUMBER(SEARCH(Keywords!$A$2:$A$136,$E207)),--(Keywords!$A$2:$A$136<>"")))) | H207: =IF($D207="","",IF($F207="Yes","YES",IF(AND($F207="Depends",$E207=""),"REVIEW — add scope text",IF($F207="Depends",IF($G207>=Classify!$C$40,"YES","NO"),IF($G207>=Classify!$C$41,"YES","NO"))))) | I207: =IF($D207="","",INDEX(Doc_Types!$D$2:$D$77,MATCH($D207,DocTypeList,0))) | J207: =IF($D207="","",IF($F207="Yes",INDEX(Doc_Types!$E$2:$E$77,MATCH($D207,DocTypeList,0)),IF(LEFT($H207,6)="REVIEW","Type is 'Depends' — classification is decided by content; paste the scope text to resolve.",IF($H207="YES","Type default is '"&$F207&"' but the text contains "&$G207&" controlled technical term(s) — classification follows content (Wassenaar ML22 technology).",INDEX(Doc_Types!$E$2:$E$77,MATCH($D207,DocTypeList,0))&" Text scan: "&$G207&" controlled term(s), below threshold.")))) | K207: =IF($H207="YES","EXPORT CONTROLLED",IF($H207="NO","NOT EXPORT CONTROLLED",IF($D207="","","— pending review —")))
B209: Rows 8-10 are examples — overwrite them with real documents. Yellow = input; all other columns are formulas.

Sheet Doc_Types
A1: Document type | B1: V-model phase | C1: Default classification | D1: Typical control-list entry | E1: Reason for the default
A2: Concept of Operations (ConOps) | B2: Concept & Requirements | C2: Depends | D2: ML22 / ML11 | E2: Usually describes mission and operational use; becomes controlled when it states threat types, frequency bands, ranges or effectiveness.
A3: Operational Scenario / Threat Analysis | B3: Concept & Requirements | C3: Yes | D3: ML11 / ML17 (libraries) / ML22 | E3: Threat emitter parameters and EW mission data are among the most sensitive military technology; controlled regardless of format.
A4: Stakeholder / User Requirements Document | B4: Concept & Requirements | C4: Depends | D4: ML22 | E4: Controlled when it contains quantified military performance requirements; generic needs statements are not technology.
A5: System Requirements Specification (SRS) | B5: Concept & Requirements | C5: Yes | D5: ML22 (technology for ML11/ML10/ML5 items) | E5: Quantified requirements for a military system are 'technology' required for its development.
A6: Subsystem / LRU Requirements Specification | B6: Concept & Requirements | C6: Yes | D6: ML22 | E6: LRU-level performance, interface and environmental requirements are development technology.
A7: Interface Requirements Specification (IRS) | B7: Concept & Requirements | C7: Yes | D7: ML22 | E7: Defines signals, protocols, timing and data formats of a military system.
A8: Requirements Traceability Matrix (RTM) | B8: Concept & Requirements | C8: Depends | D8: ML22 | E8: Controlled if it reproduces requirement text; an ID-only matrix is not technology.
A9: System Architecture Description | B9: Architecture & Design | C9: Yes | D9: ML22 | E9: Functional and physical decomposition of a military system is development technology.
A10: System / Segment Design Description (SSDD) | B10: Architecture & Design | C10: Yes | D10: ML22 | E10: Detailed design of a controlled system.
A11: Interface Control Document (ICD) | B11: Architecture & Design | C11: Yes | D11: ML22 | E11: Signal, message, electrical and protocol definitions; only a purely mechanical form-fit ICD may be argued down (Mitigation ground 14).
A12: Hardware Design Description (HDD) | B12: Architecture & Design | C12: Yes | D12: ML22 | E12: Circuit-level and module-level design of controlled hardware.
... A77: Company Policies / HR / Finance Documents | B77: Management & Commercial | C77: No | D77: n/a | E77: No technology.
A79: Legend: Yes = controlled by nature of the document type; No = not controlled unless the scope text shows 2+ controlled terms; Depends = decided by the scope text (1+ controlled term = YES). Add or edit rows here to tune the tool — the Classify dropdown reads this column A range.
B80: Concept & Requirements
B81: Architecture & Design
B82: Implementation
B83: Integration & Verification
B84: Validation & Acceptance
B85: Operations & Support
B86: Production & Manufacturing
B87: Management & Commercial

Sheet Keywords
A1: Controlled technical keyword (case-insensitive, substring match) | B1: Control-list entry indicated | C1: Group | D1: Hit in current scope text (auto) | E1: Entry if hit (auto) | F1: Running list of hits (auto) | G1: Running list of entries (auto)
A2: jammer | B2: ML11 | C2: EW | D2: =IF(ISNUMBER(SEARCH($A2,Classify!$C$8)),$A2&"; ","") | E2: =IF($D2<>"",$B2&"; ","") | F2: =$D2 | G2: =$E2
A3: jamming | B3: ML11 | C3: EW | D3: =IF(ISNUMBER(SEARCH($A3,Classify!$C$8)),$A3&"; ","") | E3: =IF($D3<>"",$B3&"; ","") | F3: =$F2&$D3 | G3: =$G2&$E3
A4: ECM | B4: ML11 | C4: EW | D4: =IF(ISNUMBER(SEARCH($A4,Classify!$C$8)),$A4&"; ","") | E4: =IF($D4<>"",$B4&"; ","") | F4: =$F3&$D4 | G4: =$G3&$E4
A5: ECCM | B5: ML11 | C5: EW | D5: =IF(ISNUMBER(SEARCH($A5,Classify!$C$8)),$A5&"; ","") | E5: =IF($D5<>"",$B5&"; ","") | F5: =$F4&$D5 | G5: =$G4&$E5
A6: ESM | B6: ML11 | C6: EW | D6: =IF(ISNUMBER(SEARCH($A6,Classify!$C$8)),$A6&"; ","") | E6: =IF($D6<>"",$B6&"; ","") | F6: =$F5&$D6 | G6: =$G5&$E6
A7: ELINT | B7: ML11 | C7: EW | D7: =IF(ISNUMBER(SEARCH($A7,Classify!$C$8)),$A7&"; ","") | E7: =IF($D7<>"",$B7&"; ","") | F7: =$F6&$D7 | G7: =$G6&$E7
A8: COMINT | B8: ML11 | C8: EW | D8: =IF(ISNUMBER(SEARCH($A8,Classify!$C$8)),$A8&"; ","") | E8: =IF($D8<>"",$B8&"; ","") | F8: =$F7&$D8 | G8: =$G7&$E8
A9: SIGINT | B9: ML11 | C9: EW | D9: =IF(ISNUMBER(SEARCH($A9,Classify!$C$8)),$A9&"; ","") | E9: =IF($D9<>"",$B9&"; ","") | F9: =$F8&$D9 | G9: =$G8&$E9
A10: electronic warfare | B10: ML11 | C10: EW | D10: =IF(ISNUMBER(SEARCH($A10,Classify!$C$8)),$A10&"; ","") | E10: =IF($D10<>"",$B10&"; ","") | F10: =$F9&$D10 | G10: =$G9&$E10
A11: electronic attack | B11: ML11 | C11: EW | D11: =IF(ISNUMBER(SEARCH($A11,Classify!$C$8)),$A11&"; ","") | E11: =IF($D11<>"",$B11&"; ","") | F11: =$F10&$D11 | G11: =$G10&$E11
A12: electronic support | B12: ML11 | C12: EW | D12: =IF(ISNUMBER(SEARCH($A12,Classify!$C$8)),$A12&"; ","") | E12: =IF($D12<>"",$B12&"; ","") | F12: =$F11&$D12 | G12: =$G11&$E12
A13: radar warning | B13: ML11 | C13: EW | D13: =IF(ISNUMBER(SEARCH($A13,Classify!$C$8)),$A13&"; ","") | E13: =IF($D13<>"",$B13&"; ","") | F13: =$F12&$D13 | G13: =$G12&$E13
A14: RWR | B14: ML11 | C14: EW | D14: =IF(ISNUMBER(SEARCH($A14,Classify!$C$8)),$A14&"; ","") | E14: =IF($D14<>"",$B14&"; ","") | F14: =$F13&$D14 | G14: =$G13&$E14
... A136: CONFIDENTIAL | B136: national security | C136: Context | D136: =IF(ISNUMBER(SEARCH($A136,Classify!$C$8)),$A136&"; ","") | E136: =IF($D136<>"",$B136&"; ","") | F136: =$F135&$D136 | G136: =$G135&$E136
A138: Blue = editable list. Add a keyword in column A (and copy the formulas in D, E, F and G down — the Classify tab reads the LAST row of F and G). Short tokens (ADC, INS, SAR, ERP, gun) can produce false hits — the author notes any false hit in the Register; the Export Control Officer may then override.
C139: EW
C140: Signature
C141: RF/Radar
C142: Software
C143: Security
C144: Nav/Avionics
C145: Weapons/EO
C146: Context

Sheet Mitigation_Grounds
A1: ID | B1: Mitigation ground | C1: Rule code | D1: Base outcome | E1: Reason given when ACCEPTED | F1: Reason given when CONDITIONAL | G1: Reason given when REJECTED | H1: Legal source | I1: Fact-base tab
A2: 1 | B2: Information is already 'in the public domain' (published by a third party without restriction) | C2: EVIDENCE | D2: CONDITIONAL | E2: Wassenaar General Technology Note: controls on 'technology' do not apply to information 'in the public domain'. The evidence reference shows the same information was made available without restriction on further dissemination. Copyright restrictions do not remove information from the public domain. CAUTION: the company's own unpermitted publication cannot be used to 'launder' controlled technology — the publisher must be a third party or the publication must have had NCACC approval. | F2: The ground is valid in principle, but no evidence reference was given. Cite the publication (title, date, URL/ISBN/standard number) that already contains this information without dissemination restrictions. Until then the document REMAINS Export Controlled. | G2: Ground not applicable. | H2: Wassenaar GTN; Definitions 'in the public domain' | I2: Definitions
A3: 2 | B3: Content is 'basic scientific research' (fundamental principles, not aimed at a product) | C3: NOTPRODUCT | D3: CONDITIONAL | E3: Ground accepted. | F3: Wassenaar GTN exempts 'basic scientific research': experimental or theoretical work undertaken principally to acquire new knowledge of fundamental principles, not primarily directed towards a specific practical aim. The Export Control Officer must confirm the document is not directed at any product, system or LRU. | G3: The document type is inherently product-specific (default classification YES). Work directed at the development, production or use of a specific system or LRU is by definition NOT 'basic scientific research'. | H3: Wassenaar GTN; Definitions 'basic scientific research' | I3: Definitions
A4: 3 | B4: Document is the minimum information necessary for a patent application | C4: REVIEW | D4: CONDITIONAL | E4: Ground accepted. | F4: The GTN exempts only 'the minimum necessary information for patent applications'. The Export Control Officer must confirm this document IS the patent application text and contains nothing beyond that minimum. Supporting design documents, test data and drawings are NOT covered by this exemption. | G4: Ground not applicable. | H4: Wassenaar GTN (patent exemption) | I4: Definitions
A5: 4 | B5: Document contains no technical data — administrative, process or quality content only | C5: NOHITS | D5: ACCEPTED | E5: No controlled keywords were found in the scope text and the document type is not inherently technical. 'Technology' (Wassenaar; NCAC Act s1) means specific information necessary for the development, production or use of a controlled item; purely administrative, process or quality content is not technology. | F5: Ground conditional. | G5: The claim contradicts the document itself: either the document type is inherently technical (default YES) or the scope text contains controlled technical terms. Remove all technical data (sanitise) and re-classify the sanitised version as a NEW document number (see ground 15). | H5: Wassenaar Definitions 'technology'; NCAC Act s1 | I5: Definitions
A6: 5 | B6: Technology is not 'required' — parameters are below the control-list threshold / generic engineering | C6: REVIEW | D6: CONDITIONAL | E6: Ground accepted. | F6: Wassenaar 'required' technology is only that portion peculiarly responsible for achieving or exceeding the controlled performance levels. The Export Control Officer must compare the document's parameters against the specific ML / Dual-Use entry cited by the author (Wassenaar_ML and Wassenaar_DualUse tabs). NOTE: Munitions List entries generally have NO performance threshold — an item 'specially designed for military use' is controlled regardless of performance; thresholds only exist in the Dual-Use List. | G6: Ground not applicable. | H6: Wassenaar Definitions 'required'; ML/DU entry thresholds | I6: Wassenaar_DualUse
A7: 6 | B7: Content is COTS / 'generally available' software (General Software Note) | C7: REVIEW | D7: CONDITIONAL | E7: Ground accepted. | F7: General Software Note: software generally available to the public (sold from stock at retail, installable by the user without substantial supplier support) or 'in the public domain' is not controlled. This exempts ONLY the COTS product itself — never the company's integration, configuration, mission-specific or embedded software for a military system (ML21). The Export Control Officer must confirm the document contains only the COTS content. | G7: Ground not applicable. | H7: Wassenaar GSN | I7: Definitions
A8: 7 | B8: Recipient is a South African company / citizen inside South Africa | C8: NONE | D8: REJECTED | E8: Ground not applicable. | F8: Ground not applicable. | G8: Classification describes the DOCUMENT, not the recipient. A controlled document stays controlled inside South Africa; only the permit requirement changes at the moment of transfer — including transfer to a foreign national on-site, by e-mail, cloud share or remote support (intangible technology transfer). Irrelevant to classification. | H8: NCAC Act s13, s14; Wassenaar ITT Best Practices | I8: SA_Law
A9: 8 | B9: Customer is an allied / friendly government (NATO, EU, SADC) | C9: NONE | D9: REJECTED | E9: Ground not applicable. | F9: Ground not applicable. | G9: Destination never changes classification. Destination is one of the NCACC's section 15 criteria when deciding whether to GRANT a permit — a permit is still required for every transfer. | H9: NCAC Act s13, s15 | I9: SA_Law
A10: 9 | B10: A marketing / contracting / export permit already exists for this programme | C10: NONE | D10: REJECTED | E10: Ground not applicable. | F10: Ground not applicable. | G10: A permit AUTHORISES a specific controlled transfer under conditions (s14); it does not declassify the document. Controlled + permitted is not the same as not controlled. Each transfer must fall within the permit's scope and conditions. | H10: NCAC Act s14(2) | I10: SA_Law
A11: 10 | B11: Document is an internal draft / not intended for release | C11: NONE | D11: REJECTED | E11: Ground not applicable. | F11: Ground not applicable. | G11: Classification is content-based; intent is irrelevant. Drafts must carry the marking so that access by foreign nationals, external e-mail, cloud storage, offshore backups or remote support (intangible technology transfer) is prevented. | H11: NCAC Act s1 'technology', s13; Wassenaar ITT Best Practices | I11: SA_Law
A12: 11 | B12: Content is purely commercial (pricing, terms, schedule) with no technical data | C12: NOHITS | D12: ACCEPTED | E12: No controlled keywords were found in the scope text and the document type is not inherently technical. Pricing, commercial terms and schedules are not 'technology'. NOTE: offering or tendering conventional arms abroad is 'marketing' under the NCAC Act and needs its own permit even though the document is not controlled. | F12: Ground conditional. | G12: The claim contradicts the document itself: either the document type is inherently technical (default YES) or the scope text contains controlled technical terms. Move technical content to a separate, controlled annex and re-classify the commercial-only version as a NEW document. | H12: Wassenaar Definitions 'technology'; NCAC Act s1 'marketing' | I12: Definitions
A13: 12 | B13: Technology is civil / dual-use only — no military application | C13: NONE | D13: REJECTED | E13: Ground not applicable. | F13: Ground not applicable. | G13: 'Not military' does not mean 'not controlled'. Dual-use items and their technology are controlled goods under the Non-Proliferation of Weapons of Mass Destruction Act 87 of 1993 (NPC) per the Wassenaar Dual-Use List (e.g. 3A001, 5A001, 5A002, 6A008, 7A003, 9A012). Re-classify as DUAL-USE CONTROLLED and route to the NPC permit process — see Wassenaar_DualUse tab. | H13: Non-Proliferation Act 87/1993 s13; Wassenaar Dual-Use List | I13: Wassenaar_DualUse
... A17: 16 | B17: Content is generic engineering knowledge found in standard textbooks / university curricula | C17: EVIDENCE | D17: CONDITIONAL | E17: Generic engineering principles that appear in standard textbooks, open standards or university curricula are 'in the public domain' (Wassenaar GTN). The cited reference demonstrates this. Ensure the document adds no system-specific parameters or design choices beyond the cited source. | F17: Cite the textbook, open standard (e.g. IEEE, IPC, ISO) or curriculum reference that contains this content. Without a reference the ground cannot be verified and the document REMAINS Export Controlled. | G17: Ground not applicable. | H17: Wassenaar GTN; Definitions 'in the public domain' | I17: Definitions
B19: Rule code | C19: How the Mitigation tab decides
B20: EVIDENCE | C20: ACCEPTED if an evidence reference is given in column E, otherwise CONDITIONAL.
B21: NOHITS | C21: REJECTED if the document type is by default 'Yes' or the scope text contains any controlled keyword; otherwise ACCEPTED.
B22: NOTPRODUCT | C22: REJECTED if the document type is by default 'Yes' (product-specific); otherwise CONDITIONAL (ECO confirms).
B23: REVIEW | C23: Always CONDITIONAL — the Export Control Officer must perform the check described.
B24: NONE | C24: Base outcome applies as written (used for grounds that are always REJECTED).
B25: (all) | C25: INCOMPLETE if the author's justification (column D) is empty.

Sheet Wassenaar_ML
A1: WASSENAAR MUNITIONS LIST — categories ML1 to ML22 (source: WA-LIST (25) 1 Corr.; SA implementation: Controlled Items Schedule GN 321, GG 35272, 20 Apr 2012 — permit authority NCACC)
A2: Entry | B2: Scope of the entry (summary of the heading text) | C2: Relevance to an EW / military-aviation design house | D2: Typical company documents that fall under it
A3: ML1 | B3: Smooth-bore weapons with a calibre of less than 20 mm, other arms and automatic weapons with a calibre of 12.7 mm or less and accessories, and specially designed components. | C3: Low | D3: Firearm integration on platforms; also falls under the Firearms Control Act.
A4: ML2 | B4: Smooth-bore weapons with a calibre of 20 mm or more, other weapons or armament with a calibre greater than 12.7 mm, projectors and accessories, and specially designed components. | C4: Low | D4: Gun/turret integration, ICDs with weapon systems.
A5: ML3 | B5: Ammunition and fuze setting devices, and specially designed components. | C5: Low | D5: Fuze-setting interfaces in stores management.
A6: ML4 | B6: Bombs, torpedoes, rockets, missiles, other explosive devices and charges and related equipment and accessories, and specially designed components. | C6: Medium | D6: Missile seekers, decoys, chaff/flare dispensers, weapon ICDs.
A7: ML5 | B7: Fire control, and related alerting and warning equipment, and related systems, test and alignment and countermeasure equipment, specially designed for military use, and specially designed components and accessories. | C7: High | D7: Missile/laser warning systems, target acquisition, fire-control ICDs, test equipment.
A8: ML6 | B8: Ground vehicles and components. | C8: Low | D8: Vehicle-mounted EW / C2 installations.
A9: ML7 | B9: Chemical or biological toxic agents, 'riot control agents', radioactive materials, related equipment, components and materials. | C9: Low | D9: Not typical.
A10: ML8 | B10: 'Energetic materials', and related substances. | C10: Low | D10: Pyrotechnic flares/cartridges only.
A11: ML9 | B11: Vessels of war (surface or underwater), special naval equipment, accessories, components and other surface vessels. | C11: Low | D11: Naval EW suites, shipboard installations.
A12: ML10 | B12: 'Aircraft', 'lighter-than-air vehicles', 'Unmanned Aerial Vehicles' ('UAVs'), aero-engines and 'aircraft' equipment, related equipment, and components, specially designed or modified for military use. | C12: High | D12: Military aircraft LRUs, avionics, mission computers, pods, pylons, UAV payloads, aircraft-integration ICDs, flight test reports.
A13: ML11 | B13: Electronic equipment, 'spacecraft' and components, not specified elsewhere on the Munitions List — includes ECM/ECCM equipment, jamming and counter-jamming, frequency-agile and spread-spectrum military communications, electronic countermeasure and support equipment, signals-intelligence demodulators, automated C2 systems, guidance and navigation equipment specially designed for military use. | C13: High | D13: THE core entry for an EW house: jammers, RWR/ESM/ELINT receivers, DRFM, DF systems, EW controllers, secure tactical comms, IFF, data links, EW test equipment.
... A24: ML22 | B24: 'Technology' — 'required' for the 'development', 'production', operation, installation, maintenance (checking), repair, overhaul or refurbishing of items specified by the Munitions List; 'technology' for design, assembly, operation, maintenance and repair of complete production installations; specific 'technology' for military-use items (e.g. ECM/ECCM, signature reduction). | C24: High | D24: EVERY specification, design description, drawing, ICD, test procedure/report, manual and training document for a Munitions List item. Governed by the General Technology Note (see Definitions tab).
A26: Key principle: the Munitions List controls by DESIGN INTENT ('specially designed for military use'), not by performance threshold. ML21 (software) and ML22 (technology) attach to every other entry — so a document about an ML11 jammer is ML22 technology even if the jammer itself never leaves the country. Full text: https://www.wassenaar.org/control-lists/

Sheet Wassenaar_DualUse
A1: WASSENAAR LIST OF DUAL-USE GOODS AND TECHNOLOGIES — Categories 0 to 9 (SA permit authority: South African Council for the Non-Proliferation of WMD — NPC, dtic — under Act 87 of 1993)
A2: Category | B2: Title | C2: Key entries for an EW / avionics house | D2: Why it matters | E2: SA authority
A3: Cat 0 | B3: Nuclear Materials, Facilities and Equipment | C3: — | D3: Not typical for an EW / avionics house. | E3: NPC (Act 87/1993)
A4: Cat 1 | B4: Special Materials and Related Equipment | C4: 1C001 (radar-absorbent materials), 1C010 (fibrous materials), 1E | D4: RAM coatings and composite structures used for signature control or airframes. | E4: NPC (Act 87/1993)
A5: Cat 2 | B5: Materials Processing | C5: 2B (machine tools), 2E (technology) | D5: Specialised machining of RF components and airframe parts. | E5: NPC (Act 87/1993)
A6: Cat 3 | B6: Electronics | C6: 3A001 (ADCs/DACs, MMIC amplifiers, TWTs, high-frequency transistors, FPGAs, phase shifters), 3A002 (signal analysers, signal generators, frequency synthesisers), 3D, 3E001 (technology) | D6: The building blocks of every EW receiver and transmitter; component BOMs and schematics frequently trigger these entries even in 'civil' projects. | E6: NPC (Act 87/1993)
A7: Cat 4 | B7: Computers | C7: 4A003 (high-performance computers), 4D, 4E | D7: Signal-processing servers and embedded processing above APP thresholds. | E7: NPC (Act 87/1993)
A8: Cat 5 Part 1 | B8: Telecommunications | C8: 5A001 (spread-spectrum/frequency-hopping radios, jamming equipment, direction finding, electronically steerable phased-array antennas), 5D001, 5E001 | D8: Frequency-agile comms, jammers and DF equipment presented as 'civil' are still controlled here. | E8: NPC (Act 87/1993)
A9: Cat 5 Part 2 | B9: Information Security | C9: 5A002 (cryptographic equipment), 5A003, 5A004, 5D002 (crypto software), 5E002 (technology) | D9: Encryption in data links, key management, secure voice, TEMPEST. | E9: NPC (Act 87/1993)
A10: Cat 6 | B10: Sensors and 'Lasers' | C10: 6A001 (acoustic), 6A002 (optical sensors/detectors, image intensifiers, focal plane arrays), 6A003 (cameras/thermal imagers), 6A004, 6A005 (lasers), 6A006 (magnetometers), 6A008 (radar, SAR, phased-array, ESM-related radar tech), 6D, 6E | D10: EO/IR sensors, laser rangefinders/designators, radar and ESM sensor technology. | E10: NPC (Act 87/1993)
A11: Cat 7 | B11: Navigation and Avionics | C11: 7A002 (gyros), 7A003 (inertial navigation), 7A005 (GNSS receivers with anti-jam/CRPA), 7A006 (radar altimeters), 7A008 (underwater nav), 7D, 7E (flight-control and avionics technology) | D11: INS/GPS integration, anti-jam GNSS, flight-control laws, avionics integration technology. | E11: NPC (Act 87/1993)
A12: Cat 8 | B12: Marine | C12: 8A, 8E | D12: Naval installation only. | E12: NPC (Act 87/1993)
A13: Cat 9 | B13: Aerospace and Propulsion | C13: 9A001-9A004 (engines), 9A012 (UAVs), 9B, 9D, 9E003 (engine technology) | D13: UAV platforms and payload integration, propulsion. | E13: NPC (Act 87/1993)
... A15: SA note | B15: In South Africa Wassenaar Dual-Use items are declared 'controlled goods' by the South African Council for the Non-Proliferation of WMD (NPC, dtic) under Act 87 of 1993 (latest consolidated declaration GN 319, GG 44423, April 2021). The NCACC's 2012 controlled-items schedule (GN 321, GG 35272) also carries a short 'Dual Use' list (e.g. ballistic body armour). | C15: — | D15: Two regulators: NCACC for the Munitions List, NPC for the Dual-Use List. Many EW documents fall under BOTH. | E15: NCACC + NPC

Sheet Definitions
A1: DEFINITIONS & GENERAL NOTES — the exact wording the Mitigation rules rely on
A2: Term | B2: Definition (Wassenaar / South African statute) | C2: Why it matters for document classification | D2: Source
A3: General Technology Note (GTN) | B3: The export of 'technology' which is 'required' for the 'development', 'production' or 'use' of items controlled in the Dual-Use List (and, by ML22, the Munitions List) is controlled. Controls on 'technology' transfer do NOT apply to information 'in the public domain', to 'basic scientific research' or to the minimum necessary information for patent applications. | C3: This is the legal source of the three exemptions used in the Mitigation tab (grounds 1, 2, 3, 16). | D3: Wassenaar List WA-LIST (25) 1 Corr., General Technology Note
A4: General Software Note (GSN) | B4: The Dual-Use List does not control 'software' which is (a) generally available to the public by being sold from stock at retail selling points without restriction and designed for installation by the user without further substantial support by the supplier, or (b) 'in the public domain', or (c) the minimum necessary 'object code' for the installation, operation, maintenance or repair of items whose export has been authorised. | C4: Source of Mitigation ground 6 (COTS software). | D4: Wassenaar List, General Software Note
A5: 'Technology' | B5: Specific information necessary for the 'development', 'production' or 'use' of a product. The information takes the form of 'technical data' or 'technical assistance'. | C5: Every design, specification, test and support document is potentially 'technology'. | D5: Wassenaar Definitions of Terms
A6: 'Technical data' | B6: May take forms such as blueprints, plans, diagrams, models, formulae, tables, engineering designs and specifications, manuals and instructions written or recorded on other media or devices such as disk, tape, read-only memories. | C6: Format is irrelevant — a PDF, e-mail, slide, wiki page or repository is technical data. | D6: Wassenaar Definitions of Terms
A7: 'Technical assistance' | B7: May take forms such as instruction, skills, training, working knowledge, consulting services. 'Technical assistance' may involve transfer of 'technical data'. | C7: Training a foreign engineer, answering a support ticket or remote debugging is a controlled transfer even with no document. | D7: Wassenaar Definitions of Terms; NCAC Act s1 'services'
A8: 'Required' | B8: As applied to 'technology', refers to only that portion of 'technology' which is peculiarly responsible for achieving or exceeding the controlled performance levels, characteristics or functions. Such 'required' 'technology' may be shared by different products. | C8: Basis of Mitigation ground 5 — but Munitions List items have no performance threshold, so this ground mostly applies to Dual-Use items. | D8: Wassenaar Definitions of Terms
A9: 'In the public domain' | B9: 'Technology' or 'software' which has been made available without restrictions upon its further dissemination. Copyright restrictions do not remove 'technology' or 'software' from being 'in the public domain'. | C9: Basis of Mitigation grounds 1 and 16. The company publishing controlled technology without a permit does not make it public domain — it is an offence. | D9: Wassenaar Definitions of Terms
A10: 'Basic scientific research' | B10: Experimental or theoretical work undertaken principally to acquire new knowledge of the fundamental principles of phenomena or observable facts, not primarily directed towards a specific practical aim or objective. | C10: Basis of Mitigation ground 2. Work on a product/LRU is never basic research. | D10: Wassenaar Definitions of Terms
A11: 'Development' | B11: Related to all stages prior to serial production, such as: design, design research, design analyses, design concepts, assembly and testing of prototypes, pilot production schemes, design data, process of transforming design data into a product, configuration design, integration design, layouts. | C11: Maps directly onto the left leg of the V-model — requirements, architecture, design, prototyping. | D11: Wassenaar Definitions of Terms
A12: 'Production' | B12: All production stages, such as: product engineering, manufacture, integration, assembly (mounting), inspection, testing, quality assurance. | C12: Maps onto the right leg of the V-model and manufacturing — including test and QA documents. | D12: Wassenaar Definitions of Terms
A13: 'Use' | B13: Operation, installation (including on-site installation), maintenance (checking), repair, overhaul and refurbishing. | C13: Manuals, installation and maintenance documents are 'use' technology. | D13: Wassenaar Definitions of Terms
... A21: Intangible Technology Transfer (ITT) | B21: Transfer of controlled technology or software by non-physical means — e-mail, fax, telephone, video conference, cloud storage, remote server access, face-to-face briefing, training or on-site support to a foreign person. | C21: The classification marking must drive access control inside the company, not only shipping. | D21: Wassenaar 'Best Practices for Implementing Intangible Transfer of Technology Controls' (2006)

Sheet SA_Law
A1: SOUTH AFRICAN LEGAL FRAMEWORK — NCAC Act 41/2002, NCAC Regulations & Controlled Items Schedule 2012, Firearms Control Act 60/2000, Non-Proliferation Act 87/1993, Criminal Procedure Act s332, Wassenaar
A2: Instrument | B2: Section / reference | C2: What it says | D2: Why it matters to document classification | E2: Band
A3: NCAC Act 41 of 2002 | B3: s1 Definitions | C3: Defines 'conventional arms' (incl. components, technology and dual-use goods), 'technology', 'marketing', 'export', 'services'. | D3: A document is a 'controlled item' when it carries 'technology' for a conventional arm. | E3: Framework
A4: NCAC Act 41 of 2002 | B4: s2 Objects; s4 NCACC | C4: Establishes the National Conventional Arms Control Committee (Cabinet ministers) to control trade in conventional arms; the Directorate Conventional Arms Control (DCAC) is its secretariat and inspectorate. | D4: NCACC is the permit authority for everything on the Munitions List. | E4: Framework
A5: NCAC Act 41 of 2002 | B5: s13 Prohibition | C5: 'No person may trade in conventional arms unless that person is registered with the secretariat and in possession of a permit authorised by the Committee.' | D5: Registration AND a permit are both required before any marketing, contracting, export or transfer of controlled technology. | E5: Offence trigger
A6: NCAC Act 41 of 2002 | B6: s14 Permits | C6: The Committee may authorise, subject to conditions, or refuse: development/manufacturing, marketing, contracting, export, import and conveyance permits. Applications in the prescribed manner. | D6: Each document transfer must fall inside the scope and conditions of a specific permit type. | E6: Offence trigger
A7: NCAC Act 41 of 2002 | B7: s15 Guiding principles | C7: Case-by-case assessment; national security of SA and allies; no contribution to internal repression, human-rights violations, regional instability or terrorism; adherence to international law and arms-control regimes; recipient's legitimate defence needs. | D7: Destination and end-use affect whether a PERMIT is granted — they never affect whether the document is CONTROLLED (Mitigation grounds 7, 8). | E7: Permit criteria
A8: NCAC Act 41 of 2002 | B8: s18-s21 Inspections, search & seizure | C8: s18 routine inspection without warrant in office hours; s19 warrant-based entry incl. private dwellings to inspect, photograph, copy and seize; s20 warrantless entry with consent or in emergencies; s21 seized items handed to SAPS under the Criminal Procedure Act. | D8: Unmarked or wrongly marked documents found during inspection are direct evidence of non-compliance. | E8: Enforcement
A9: NCAC Act 41 of 2002 | B9: s23 Reporting | C9: Quarterly and annual reporting by the Committee to Parliament and Cabinet; registered persons must keep records and report. | D9: Classification records (the Register tab) support the company's statutory reporting and audit trail. | E9: Compliance
A10: NCAC Act 41 of 2002 | B10: s24 Offences and penalties | C10: Offences: trading without registration/permit, breaching permit conditions, false information, obstructing inspectors, failing to disclose conflicts of interest. Penalties: fine or imprisonment up to 25 years (trading/permit offences), up to 20 years (false information), up to 10 years (obstruction and related). | D10: Releasing a controlled document without a permit = trading without a permit = up to 25 years. | E10: Criminal
A11: NCAC Act 41 of 2002 | B11: s27 Regulations & controlled-items list | C11: Minister publishes regulations and the schedule of controlled items by notice. | D11: The SA controlled-items list is the legal text; Wassenaar is its source. | E11: Framework
A12: NCAC Amendment Act 73 of 2008 | B12: Whole Act | C12: Widened the Act to 'controlled items' (conventional arms, dual-use goods, technology and services); strengthened intangible-transfer coverage and the inspectorate. | D12: Confirms that technology and services — not only hardware — are permit-controlled. | E12: Framework
A13: NCAC Regulations, 2012 | B13: GN R.326, GG 35272, 20 April 2012 | C13: Prescribes registration, permit application forms, end-user certificates, record-keeping and reporting obligations of registered persons. | D13: Defines the company's administrative duties around every controlled transfer. | E13: Compliance
... A22: Wassenaar Arrangement | B22: Best Practices for Implementing Intangible Transfer of Technology Controls (2006) | C22: Participating States control technology transferred by intangible means (electronic media, oral, visual) and encourage internal compliance programmes, record-keeping and awareness. | D22: Markings must drive IT access control, e-mail rules and foreign-national access — not only shipping. | E22: Compliance
A24: Sources: NCAC Act 41 of 2002 — https://www.gov.za/documents/national-conventional-arms-control-act ; Controlled Items Schedule GN 321/2012 — https://www.gov.za/sites/default/files/gcis_document/201409/35272gon321.pdf ;
A25: Firearms Control Act 60 of 2000 — https://www.gov.za/documents/firearms-control-act ; Non-Proliferation of WMD Act 87 of 1993 — https://www.gov.za/documents/non-proliferation-weapons-mass-destruction-act-2-jul-1993-0000 ;
A26: Wassenaar Arrangement control lists — https://www.wassenaar.org/control-lists/ ; ITT Best Practices — https://www.wassenaar.org/app/uploads/2019/consolidated/ITT_Best_Practices_for_public_statement_2006.pdf

Sheet Penalties
A1: CONSEQUENCES OF MIS-CLASSIFICATION — what the company and its directors face when a controlled document leaves without a permit
A2: Consequence | B2: Category | C2: Statutory basis | D2: Who is exposed | E2: Severity
A3: Fine and/or imprisonment for trading, manufacturing, marketing, contracting or exporting conventional arms (including technology) without a valid NCACC permit, or in breach of permit conditions | B3: Criminal | C3: NCAC Act s13, s24(2) — up to 25 years | D3: Company + responsible directors/officers | E3: Critical
A4: Fine and/or imprisonment for furnishing false or misleading information to the NCACC / DCAC | B4: Criminal | C4: NCAC Act s24 — up to 20 years | D4: Individuals who sign applications and declarations | E4: Critical
A5: Fine and/or imprisonment for obstructing or hindering inspectors | B5: Criminal | C5: NCAC Act s24 — up to 10 years | D5: Any employee | E5: High
A6: Suspension, cancellation or revocation of existing development/manufacturing, marketing, contracting, export or import permits | B6: Administrative | C6: NCAC Act s14 (permit conditions), Regulations 2012 | D6: Company (whole order book) | E6: Critical
A7: Disqualification from future trade authorisations after conviction of directors or executive officers | B7: Administrative | C7: NCAC Act s14, s24; Regulations 2012 (registration fitness) | D7: Company | E7: Critical
A8: Entry, search and seizure of undocumented or non-compliant items, documents, data and manufacturing equipment | B8: Enforcement | C8: NCAC Act s18-s21 | D8: Premises, IT systems, records | E8: High
A9: Personal criminal liability of directors and managers for the company's statutory offence unless they prove they took no part and could not have prevented it | B9: Director liability | C9: Criminal Procedure Act s332 | D9: Directors, executives, managers | E9: Critical
A10: Dual-use technology transferred without an NPC permit — fine or imprisonment (5-15 years; life for WMD-related) | B10: Criminal | C10: Non-Proliferation of WMD Act s13, s26 | D10: Company + individuals | E10: Critical
A11: Firearm-related products handled without SAPS licences/permits — imprisonment up to 25 years | B11: Criminal | C11: Firearms Control Act s31, s45, s73, s121 & Schedule 4 | D11: Company + individuals | E11: High
A12: Intangible transfer (e-mail, cloud, remote support, source code repository, briefing a foreign national) of controlled technology to an unapproved foreign entity — treated as an unpermitted export | B12: Criminal / cross-border | C12: NCAC Act s1 'export', s13, s24; Wassenaar ITT Best Practices | D12: Company, parent group, individual engineers | E12: Critical
A13: Secondary sanctions, foreign legal action and loss of international partner/customer trust | B13: Commercial / reputational | C13: Partner-country export regimes (e.g. ITAR/EAR re-export rules, EU Dual-Use Regulation) triggered by SA non-compliance | D13: Company and international parent group | E13: High
A14: Loss of programme: customer termination, debarment from defence tenders, Armscor/DoD vendor status | B14: Commercial | C14: Contractual export-compliance clauses; Armscor vendor requirements | D14: Company | E14: High

Sheet Markings_QA
A1: DOCUMENT MARKINGS & QA WORKFLOW
A3: Marking | B3: Verbatim text for the document header / footer (Classify!C30 pulls from here) | C3: When used
A5: EXPORT CONTROLLED | B5: EXPORT CONTROLLED — This document contains technology controlled under the National Conventional Arms Control Act 41 of 2002 (Wassenaar Munitions List / SA Controlled Items Schedule). It may not be exported, disclosed, e-mailed, uploaded or otherwise transferred to any foreign person, entity or destination — including by intangible means — without a valid NCACC permit. Unauthorised transfer is a criminal offence (s24: up to 25 years imprisonment). | C5: Classify decision = YES, or Final = YES
A6: NOT EXPORT CONTROLLED | B6: NOT EXPORT CONTROLLED — Reviewed against the SA Controlled Items Schedule and the Wassenaar Lists on [date] by [name]. No controlled technology identified. Re-classify if technical content is added. | C6: Classify decision = NO, or downgrade signed off by ECO
A7: DUAL-USE CONTROLLED | B7: DUAL-USE CONTROLLED — This document contains technology controlled under the Non-Proliferation of Weapons of Mass Destruction Act 87 of 1993 (Wassenaar Dual-Use List). Transfer outside South Africa requires a permit from the South African Council for the Non-Proliferation of WMD (NPC). | C7: ECO re-classifies under the Non-Proliferation Act (Mitigation ground 12)
A9: Step / Role | B9: QA checklist action | C9: Note
A10: 1. Author | B10: Select the document type and paste the scope / general paragraphs on the Classify tab. | C10: Every new or revised document, before first release.
A11: 2. Author | B11: Read the automatic decision and its reason; check the matched keywords make sense in context. | C11: If a keyword is a false hit (e.g. 'flare' in a photography document) note it in the Register.
A12: 3. Author | B12: If YES and you disagree, enter 1-3 grounds on the Mitigation tab with justification and evidence. | C12: Grounds 7-10, 12, 13 are always rejected — do not waste time on them.
A13: 4. Checker / QA | B13: Verify the document type is the closest match and the scope text is representative of the WHOLE document (not just the introduction). | C13: A wrong document type is the commonest error.
A14: 5. Export Control Officer | B14: For CONDITIONAL outcomes, perform the check described in column G of the Mitigation tab against the Wassenaar_ML / Wassenaar_DualUse tabs. | C14: Only the ECO may confirm a downgrade.
A15: 6. Export Control Officer | B15: Record the final classification, ECO name and date in the Register tab; apply the marking text from this tab to the document header/footer. | C15: Marking wording must be verbatim.
A16: 7. Document Control | B16: Set access rights: EXPORT CONTROLLED documents to the controlled repository; no foreign-national access; no external cloud sync; no e-mail outside SA without permit reference in the Register. | C16: Intangible transfer is an export.
A17: 8. Export Control Officer | B17: Before any release abroad, quote the permit number and check the recipient is within the permit scope; log the transfer. | C17: NCAC Act s13/s14.
A19: Access-control rules that follow from the marking: controlled repository only · no foreign-national access without a permit covering that person · no external cloud sync · no e-mail outside SA without a permit reference in the Register · no remote support sessions abroad without a permit (intangible transfer is an export).

Sheet Register
A1: Date | B1: Document number | C1: Title | D1: Document type | E1: Initial decision | F1: Mitigation verdict | G1: FINAL classification | H1: Control entry | I1: ECO | J1: Permit ref. (if released abroad) | K1: Notes / false keyword hits
A2: 2026-09-17 | B2: EW-SRS-0042 | C2: Radar Warning Receiver LRU — System Requirements Specification | D2: System Requirements Specification (SRS) | E2: YES | F2: n/a | G2: EXPORT CONTROLLED | H2: ML11 / ML22 | I2: T. Naidoo | J2: — | K2: Example row — delete when the first real entry is made
