Workbook

Sheet Requirements
A1: TrustSquare — What the AI must do PER LISTING PHOTO (the anonymity gate)
A3: ID | B3: Requirement | C3: Detail | D3: Why it matters
A4: R1 | B4: Detect identifying content | C4: Number plates (incl. ~60px background plates), dealer strips with phone/web text, signage, house numbers, licence discs, contact overlays | D4: Recall failure = privacy leak on a live advert (the 11 Jul incident)
A5: R2 | B5: Box precisely | C5: 0-1000 normalised boxes; zoom-refine to the CHARACTER strip; report text tilt angle for the capsule blur | D5: Box slop = the 'butchered photo' David rejected
A6: R3 | B6: Verify after blur | C6: Re-scan the blurred image; flag any single readable character at a patch edge | D6: THE leak guarantee — the verifier's quality IS the safety bar
A7: R4 | B7: Classify & moderate | C7: subject (2-4 words) + inappropriate flag (nudity/violence/degrading) — added 15 Jul, same call | D7: Abuse defence, zero extra calls
A8: R5 | B8: Strict JSON at <=1400 output tokens | C8: Salvage exists but malformed output = held photo = seller friction
A9: R6 | B9: Ops integration | C9: Fail-closed; $100/day ceiling (C1); per-call spend logging; provider seam (ai_provider.py task routing) | D9: Any replacement model must slot into the SAME seam
A11: History that matters: the scan WAS Haiku-routed until 7 Jul 2026 — upgraded to Sonnet because Haiku MISSED plates (~3.75x cost, CHANGELOG). 'Cheapest model' has already failed this task once; any switch needs the eval in 'Switch Test Plan'.

Sheet Pricing (Jul 2026)
A1: Provider pricing — web-verified 16 Jul 2026 · RE-VERIFY BEFORE ANY SWITCH (prices move monthly)
A3: Provider / model | B3: $ per 1M input | C3: $ per 1M output | D3: Image billing | E3: Source / note
A4: Anthropic Claude Sonnet 5 (current) | B4: 3 | C4: 15 | D4: (w x h)/750 tokens | E4: platform.claude.com — intro $2/$10 until 31 Aug 2026; Batch API -50%
A5: Anthropic Claude Haiku 4.5 | B5: 1 | C5: 5 | D5: (w x h)/750 tokens | E5: platform.claude.com — FAILED this task pre-7-Jul (missed plates)
A6: OpenAI GPT-4.1-mini | B6: 0.4 | C6: 1.6 | D6: patch tokens, ~1.6x multiplier | E6: developers.openai.com/api/docs/pricing
A7: OpenAI GPT-4.1-nano | B7: 0.1 | C7: 0.4 | D7: patch tokens, ~2.5x multiplier | E7: cheapest OpenAI vision; recall risk highest
A8: Google Gemini 2.5 Flash-Lite | B8: 0.1 | C8: 0.4 | D8: images billed AS TOKENS at same rate | E8: ai.google.dev — cheapest capable candidate
A9: Google Gemini 3 Flash (preview) | B9: 0.5 | C9: 3 | D9: per-image token schedule | E9: tldl.io roundup — preview pricing, confirm at GA
A10: Z.ai GLM-5.2 | B10: 1.4 | C10: 4.4 | D10: same per-token as text | E10: docs.z.ai — $0.95/$3.00 via OpenRouter; see sovereignty note
A11: Z.ai GLM-4.6V-FlashX (budget vision) | B11: 0.04 | C11: 0.4 | D11: same per-token as text | E11: docs.z.ai — GLM-4.6V-Flash tier is FREE (rate-limited); 5.2 above is their FLAGSHIP, not the fair comparator
A16: Yellow/blue cells are editable inputs — the whole model recalculates from them.

Sheet Per-photo model
A1: Per-photo cost model — every figure below is a FORMULA from these assumptions
A3: Assumption | B3: Value | C3: Note
A4: Probe image tokens (1344px, Anthropic /750 rule) | B4: 1806 | C4: raised 896->1344 on 11 Jul (small plates) — THE step that moved $4.80 to ~$13
A5: Scan prompt tokens | B5: 650 | C5: incl. 15 Jul moderation clause
A6: Scan output tokens | B6: 80 | C6: verdict+boxes+subject+flag
A7: Refine call input tokens (crop+prompt) | B7: 1000 | C7: per redacted photo
A8: Refine output tokens | B8: 60
A9: Verify = one more full scan | B9: 1 | C9: 1 = yes
A10: Share of photos needing redaction | B10: 0.3 | C10: car-heavy mix; lower for property
A11: Extra rounds share (stubborn photos) | B11: 0.05 | C11: multi-round verify
A12: Extra rounds cost multiplier | B12: 2.5 | C12: x the redacted-photo cost
A15: Provider | B15: Img tok factor | C15: $ clean photo | D15: $ redacted photo | E15: $ avg photo | F15: $ per 1,000 | G15: $ per 20,000
A16: Claude Sonnet 5 (today) | B16: 1 | C16: =(($B$4*B16)+$B$5)*'Pricing (Jul 2026)'!$B$4/1000000+$B$6*'Pricing (Jul 2026)'!$C$4/1000000 | D16: =C16+($B$7*'Pricing (Jul 2026)'!$B$4/1000000+$B$8*'Pricing (Jul 2026)'!$C$4/1000000)+IF($B$9=1,C16,0) | E16: =(1-$B$10)*C16+$B$10*D16+$B$11*($B$12-1)*D16 | F16: =E16*1000 | G16: =E16*20000
A17: Claude Haiku 4.5 | B17: 1 | C17: =(($B$4*B17)+$B$5)*'Pricing (Jul 2026)'!$B$5/1000000+$B$6*'Pricing (Jul 2026)'!$C$5/1000000 | D17: =C17+($B$7*'Pricing (Jul 2026)'!$B$5/1000000+$B$8*'Pricing (Jul 2026)'!$C$5/1000000)+IF($B$9=1,C17,0) | E17: =(1-$B$10)*C17+$B$10*D17+$B$11*($B$12-1)*D17 | F17: =E17*1000 | G17: =E17*20000
A18: GPT-4.1-mini | B18: 1.45 | C18: =(($B$4*B18)+$B$5)*'Pricing (Jul 2026)'!$B$6/1000000+$B$6*'Pricing (Jul 2026)'!$C$6/1000000 | D18: =C18+($B$7*'Pricing (Jul 2026)'!$B$6/1000000+$B$8*'Pricing (Jul 2026)'!$C$6/1000000)+IF($B$9=1,C18,0) | E18: =(1-$B$10)*C18+$B$10*D18+$B$11*($B$12-1)*D18 | F18: =E18*1000 | G18: =E18*20000
A19: GPT-4.1-nano | B19: 2.2 | C19: =(($B$4*B19)+$B$5)*'Pricing (Jul 2026)'!$B$7/1000000+$B$6*'Pricing (Jul 2026)'!$C$7/1000000 | D19: =C19+($B$7*'Pricing (Jul 2026)'!$B$7/1000000+$B$8*'Pricing (Jul 2026)'!$C$7/1000000)+IF($B$9=1,C19,0) | E19: =(1-$B$10)*C19+$B$10*D19+$B$11*($B$12-1)*D19 | F19: =E19*1000 | G19: =E19*20000
A20: Gemini 2.5 Flash-Lite | B20: 0.6 | C20: =(($B$4*B20)+$B$5)*'Pricing (Jul 2026)'!$B$8/1000000+$B$6*'Pricing (Jul 2026)'!$C$8/1000000 | D20: =C20+($B$7*'Pricing (Jul 2026)'!$B$8/1000000+$B$8*'Pricing (Jul 2026)'!$C$8/1000000)+IF($B$9=1,C20,0) | E20: =(1-$B$10)*C20+$B$10*D20+$B$11*($B$12-1)*D20 | F20: =E20*1000 | G20: =E20*20000
A21: Gemini 3 Flash (preview) | B21: 0.6 | C21: =(($B$4*B21)+$B$5)*'Pricing (Jul 2026)'!$B$9/1000000+$B$6*'Pricing (Jul 2026)'!$C$9/1000000 | D21: =C21+($B$7*'Pricing (Jul 2026)'!$B$9/1000000+$B$8*'Pricing (Jul 2026)'!$C$9/1000000)+IF($B$9=1,C21,0) | E21: =(1-$B$10)*C21+$B$10*D21+$B$11*($B$12-1)*D21 | F21: =E21*1000 | G21: =E21*20000
A22: GLM-5.2 | B22: 1 | C22: =(($B$4*B22)+$B$5)*'Pricing (Jul 2026)'!$B$10/1000000+$B$6*'Pricing (Jul 2026)'!$C$10/1000000 | D22: =C22+($B$7*'Pricing (Jul 2026)'!$B$10/1000000+$B$8*'Pricing (Jul 2026)'!$C$10/1000000)+IF($B$9=1,C22,0) | E22: =(1-$B$10)*C22+$B$10*D22+$B$11*($B$12-1)*D22 | F22: =E22*1000 | G22: =E22*20000
A23: GLM-4.6V-FlashX (budget) | B23: 1 | C23: =(($B$4*B23)+$B$5)*'Pricing (Jul 2026)'!$B$11/1000000+$B$6*'Pricing (Jul 2026)'!$C$11/1000000 | D23: =C23+($B$7*'Pricing (Jul 2026)'!$B$11/1000000+$B$8*'Pricing (Jul 2026)'!$C$11/1000000)+IF($B$9=1,C23,0) | E23: =(1-$B$10)*C23+$B$10*D23+$B$11*($B$12-1)*D23 | F23: =E23*1000 | G23: =E23*20000
A25: Anthropic Batch API (-50%) applies to agency imports (async): Sonnet avg x0.5 — see Scenarios.

Sheet Scenarios
A1: What it actually costs — scenarios (formulas pull from 'Per-photo model')
A3: Scenario | B3: Photos | C3: Sonnet today | D3: Sonnet Batch (-50%) | E3: GPT-4.1-mini | F3: Gemini 2.5 Flash-Lite | G3: Ceiling headroom note
A4: David's challenge: 20,000 photos in a day | B4: 20000 | C4: =B4*'Per-photo model'!$E$16 | D4: =B4*'Per-photo model'!$E$16*0.5 | E4: =B4*'Per-photo model'!$E$18 | F4: =B4*'Per-photo model'!$E$20 | G4: =IF(C4>100,"exceeds $100/day on Sonnet","fits under the daily ceiling")
A5: Large agency import: 300 adverts x 5 | B5: 1500 | C5: =B5*'Per-photo model'!$E$16 | D5: =B5*'Per-photo model'!$E$16*0.5 | E5: =B5*'Per-photo model'!$E$18 | F5: =B5*'Per-photo model'!$E$20 | G5: =IF(C5>100,"exceeds $100/day on Sonnet","fits under the daily ceiling")
A6: Monster agency: 1,000 adverts x 5 | B6: 5000 | C6: =B6*'Per-photo model'!$E$16 | D6: =B6*'Per-photo model'!$E$16*0.5 | E6: =B6*'Per-photo model'!$E$18 | F6: =B6*'Per-photo model'!$E$20 | G6: =IF(C6>100,"exceeds $100/day on Sonnet","fits under the daily ceiling")
A7: 1,000 photos (the reference unit) | B7: 1000 | C7: =B7*'Per-photo model'!$E$16 | D7: =B7*'Per-photo model'!$E$16*0.5 | E7: =B7*'Per-photo model'!$E$18 | F7: =B7*'Per-photo model'!$E$20 | G7: =IF(C7>100,"exceeds $100/day on Sonnet","fits under the daily ceiling")
A8: Year-1 volume (~11,700 listings, 24-cap, 70% use) | B8: 197000 | C8: =B8*'Per-photo model'!$E$16 | D8: =B8*'Per-photo model'!$E$16*0.5 | E8: =B8*'Per-photo model'!$E$18 | F8: =B8*'Per-photo model'!$E$20 | G8: =IF(C8>100,"exceeds $100/day on Sonnet","fits under the daily ceiling")

Sheet Switch Test Plan
A1: Model switch-over: how we test WITHOUT risking a single live leak
A3: Step | B3: What | C3: Detail
A4: 0 | B4: Freeze the eval set | C4: ~30 photos: listing-246 originals (real plates incl. the tiny background one), the synthetic skew/word-plate set, 5 clean interiors, 3 'inappropriate' samples, 3 off-category. Stored privately; never changes, so every model scores on identical evidence.
A5: 1 | B5: Score candidates offline | C5: Run each candidate on the eval set via the ai_provider seam. Score: plate recall (MUST be 100% on the set), box tightness (IoU vs hand-drawn truth), angle accuracy, JSON validity rate, subject/flag accuracy. One afternoon, costs cents.
A6: 2 | B6: Mixed-roles canary (the safe money-saver) | C6: Cheap model as SCANNER+REFINER, Sonnet stays as VERIFIER on every redaction. A weak scanner then degrades to more verify rounds — never to a leak. Saving depends on the clean-photo share: the scanner is the only call on clean photos, so this is where recall matters most. Gate: 2 weeks, zero verifier catches of scanner-missed plates.
A7: 3 | B7: Full switch decision | C7: Only after the canary: verifier moves last, because the verifier IS the leak guarantee. Keep Sonnet routing one env-var away (the seam already supports per-task providers) as the rollback.
B8: Immediate savings needing NO vendor risk | C8: (a) Anthropic Batch API for agency imports: -50%, async fits imports naturally. (b) Sonnet intro pricing $2/$10 until 31 Aug already ~33% off the modelled $3. (c) Property/LM photos rarely carry plates — a per-category redaction-mix assumption cuts the blended average further.

Sheet Pricing (Aug 2026) swap
A1: Blur-lane swap costing — 19 Aug 2026 · same per-photo assumptions as 'Per-photo model' sheet · RUL-031
A2: Model | B2: $/M in | C2: $/M out | D2: $ clean photo | E2: $ redacted | F2: $ avg photo | G2: $ / 1,000 | H2: $ Year-1 (197k) | I2: Note
A3: OpenAI gpt-5.6-terra (TODAY) | B3: 2 | C3: 12 | D3: 0.00587 | E3: 0.01446 | F3: 0.00878 | G3: 8.78 | H3: 1729 | I3: current standing lane — the one that just failed
A4: Anthropic Sonnet 4.6 (failover) | B4: 3 | C4: 15 | D4: 0.00857 | E4: 0.02104 | F4: 0.01278 | G4: 12.78 | H4: 2518 | I4: pre-14-Aug lane — failed the same way
A5: Scaleway mistral-medium-3.5 (net) | B5: 1.56 | C5: 9.37 | D5: 0.00458 | E5: 0.01128 | F5: 0.00685 | G5: 6.85 | H5: 1349 | I5: derived from 0.781x baseline multiple
A6: Gemini 3.7 Flash | B6: 0.75 | C6: 3.75 | D6: 0.0016 | E6: 0.00418 | F6: 0.00269 | G6: 2.69 | H6: 529 | I6: CORRECTED 26 Aug 2026 — first-party ai.google.dev STANDARD tier $0.75/$3.75 (the 19 Aug row used $0.375 = the BATCH rate, and a $1.50 out ESTIMATE). Was modelled $224/yr.
A7: Grok 4.1 Fast | B7: 0.2 | C7: 0.5 | D7: 0.00053 | E7: 0.00129 | F7: 0.00079 | G7: 0.79 | H7: 155 | I7: xAI volume tier
A8: Grok 4.6 | B8: 2 | C8: 6 | D8: 0.00539 | E8: 0.01314 | F8: 0.00801 | G8: 8.01 | H8: 1579 | I8: xAI flagship
A9: Qwen3-VL (EU host) | B9: 0.4 | C9: 1.2 | D9: 0.00108 | E9: 0.00263 | F9: 0.0016 | G9: 1.6 | H9: 316 | I9: ESTIMATE — no EU-host price sheet yet
A10: Local CV detector (YOLO+OCR) | B10: 0 | C10: 0 | D10: 0 | E10: 0 | F10: 0 | G10: 0 | H10: 0 | I10: $0 marginal; our CPU
A11: CANARY: Gemini scans+refines, terra verifies every redaction (their own Switch Test Plan step 2 — a weak scanner degrades to more verify rounds, never to a leak) | D11: 0.0016 | E11: 0.00845 | F11: 0.00429 | G11: 4.29 | H11: 845 | I11: CORRECTED 26 Aug 2026 on first-party prices. Was modelled $548/yr. Still the cheapest zero-leak-risk step: vs terra-only $1,729/yr.
A13: Context: gate history — Haiku FAILED this task pre-7-Jul (missed plates); 'cheapest' already lost once. Recall on the 30-photo eval set must be 100% BEFORE any traffic (Switch Test Plan). Gemini uniquely returns segmentation MASKS (surgical, not rectangles); Qwen3-VL is grounding-trained; Grok/Mistral are general LLMs like the two that failed. Local CV = $0/call, needs ~2 days + eval.
A15: PRICE STEP — Gemini introductory pricing EXPIRES 31 Dec 2026; from 1 Jan 2027 standard is $1.50 in / $7.50 out (2x). Same assumptions, re-costed:
A16: Model | B16: $/M in | C16: $/M out | D16: $ clean photo | E16: $ redacted | F16: $ avg photo | G16: $ / 1,000 | H16: $ Year-1 (197k) | I16: Note
A17: Gemini 3.7 Flash (from 1 Jan 2027) | B17: 1.5 | C17: 7.5 | D17: 0.0032 | E17: 0.00835 | F17: 0.00537 | G17: 5.37 | H17: 1058 | I17: full switch at post-intro pricing
A18: CANARY (gemini scan+refine, terra verify) — from 1 Jan 2027 | B18: 1.5 | C18: 7.5 | D18: 0.0032 | E18: 0.01102 | F18: 0.00637 | G18: 6.37 | H18: 1256 | I18: canary at post-intro pricing; margin vs terra-only ($1,729) narrows sharply — decide before the step whether to promote to full switch or move to the local CV detector ($0 marginal).
