Workbook

Sheet REVIEW 18 Aug 2026
A1: PRE-LAUNCH COST REVIEW — Rev C, 18 August 2026 (soft launch 29 Aug · full launch 1 Sep, RUL-001)
A2: Rev A (as filed) and Rev B (16 Jul audit) sheets are preserved UNCHANGED below. Rev C ADDS sheets; it does not overwrite history — same convention the 16 Jul audit used. The Rev C sheets are now the live model.
A4: Area | B4: Was (Rev B, 16 Jul) | C4: Now (Rev C, 18 Aug) | D4: Impact | E4: Why / source
A5: ZAR/USD rate | B5: 18.50 | C5: 16.21 (live, 18 Aug 2026) | D5: ZAR costs +14% in USD; ZAR revenue +14% | E5: Frankfurter/ECB + open.er-api, read live 18 Aug 2026. RUL-022 made FX live and keyless in the app; the model was still on a hardcoded 18.50 from June.
A6: Hetzner — list price | B6: CPX32 €15.49/mo | C6: €15.49 GRANDFATHERED; new-order price €35.49 | D6: +129% if the box is ever rescaled | E6: Hetzner raised cloud prices twice in 2026: ~+30% on 1 Apr, then CPX/CCX up to +176% on 15 Jun. Existing servers keep legacy terms — but ANY rescale reprices. This is a live single-point risk, not a cost today.
A7: Hetzner — better box exists | B7: n/a | C7: CX43: 8 vCPU / 16 GB / 160 GB at €15.99 | D7: 2x the CPU and RAM for +€0.50/mo | E7: The June repricing hit CPX/CCX hard and left the new CX line cheap. CX43 beats our grandfathered CPX32 on every spec at the same money. See 'Infrastructure Rev C'.
A8: Hetzner — storage | B8: Volume €0.052/GB | C8: €0.0572/GB (+10%) | D8: +€0.52/mo on the 100 GB volume | E8: Hetzner published block-storage rates, Aug 2026.
A9: Hetzner — actual bill | B9: modelled €15.49 only | C9: $32.00/mo all-in (server+volume+object storage) | D9: +$16/mo vs the modelled line | E9: David's actual last-month bill, 15 Aug 2026 (STATUS.md; AI_TOKEN_ECONOMICS rev3 §5). The Rev B workbook never carried the volume or the backup bucket.
A10: PostgreSQL | B10: absent from the model | C10: Budgeted from Month 7, 5 options priced | D10: +$22/mo default (2nd Hetzner box) | E10: David's own ruling stands: DB_DECISION_2026-07-29 — launch runs on SQLite, Postgres is a post-launch trigger-driven project. Rev C budgets it rather than leaving it unfunded; see 'Infrastructure Rev C'.
A11: Third-party subscriptions | B11: 5 lines (infra only) | C11: Full 40-line register, every dependency | D11: Nothing is off-budget any more | E11: Built from the Ops Dashboard infrastructure panel (bea_main.py _INFRA_CHECKS) + subscription_monitor.py CATALOG + feature_flags.json. LIVE / PLANNED / HELD / CLOSED status per row.
A12: AI subscriptions | B12: Claude Pro $20 | C12: Claude $230.00 + Higgsfield $44.85 | D12: +$254.85/mo | E12: David's actuals, 15 Aug 2026 (incl. 15% ZA import levy). The Claude subscription is the fix-agent's brain, so it is a platform cost, not a personal one.
A13: AI swap-out provision | B13: $20 x 6 lanes = $120/500 users | C13: $40 per model x 7 models = $280 launch provision | D13: One-off $280 at launch | E13: David's instruction, 18 Aug 2026. Covers key provisioning and opening credit float on every lane in the swap chain so a failover is never blocked on a payment. Reserve, not spend — unspent provision is runway.
A14: AI running cost | B14: services on Sonnet; photos on Gemini 3 Flash | C14: Base lane = OpenAI (Luna/Terra); premier models demoted to failover | D14: ~72-78% cut in AI API cost | E14: RUL-002 (14 Aug): OpenAI base, Anthropic auto-failover, Scaleway EU safety net. Luna scores 51.24 AA vs Haiku's 29.58 at 77-79% less. David's read is correct — the better-capable model is now the cheaper one; premier models earn their keep as continuity insurance.
A15: Accountant | B15: R2,000/mo from Year 2 | C15: R2,000/mo from MONTH 1 | D15: +$1,481/yr in Year 1 | E15: David's instruction, 18 Aug 2026 — and FINANCE_CANON §4 already recommended exactly this: 'engage at FIRST REVENUE, not Year 2; a Year-1 structuring consult is cheap vs one wrong VAT call.' Year 1 crosses the R2.3m compulsory VAT threshold if the ramp holds.
... A18: Two rival workbooks | B18: GlobalLaunch vs v2_AIcosts disagreed | C18: THIS workbook is the single live model | D18: One source of truth | E18: Cost_Breakdown_GlobalLaunch.xlsx carried the newer infra rows but the older 2.5%-Stripe assumptions; v2_AIcosts carried the 16 Jul audit but no storage rows. Rev C folds both in here. GlobalLaunch is superseded — do not update it.
A20: HEADLINE
A21: The tech stack was never the problem. Rev C's restated Year-1 cost is dominated by ONE new line — human operations — which the old model did not carry at all.
A22: Every technology cost in this business, added together and rounded up, is smaller than three part-time people.
A23: That is the business case question this review puts to David: not 'can we afford the servers' (trivially yes) but 'what are the three people FOR, and does the ramp fund them'.

Sheet Business Case Rev C
A1: BUSINESS CASE — RESTATED · Rev C 18 Aug 2026 · supersedes the '3-Year Summary' sheet
A2: The '3-Year Summary' sheet below is preserved as filed and is now HISTORY. This is the live business case. Revenue is unchanged — the Rev C work was entirely on the cost side.
B4: Year 1 | C4: Year 2 | D4: Year 3 | E4: 3-year | F4: Note
A5: ── SCALE ──────────────────────────────────────────────────────
A6: Sellers | B6: ='Assumptions Rev C'!$B$9 -> 7790 | C6: ='Assumptions Rev C'!$B$10 -> 4368 | D6: ='Assumptions Rev C'!$B$11 -> 16872 | F6: As filed. Year 2 is lower than Year 1 — a cumulative-vs-incremental inconsistency in the original model, never reconciled. Flagged, not fixed: fixing it is a revenue-model job, not a costing one.
A7: ── REVENUE (unchanged from the audited model) ─────────────────
A8: TOTAL REVENUE | B8: ='Assumptions Rev C'!$B$12 -> 235154 | C8: ='Assumptions Rev C'!$B$13 -> 691173 | D8: ='Assumptions Rev C'!$B$14 -> 3995294 | E8: =SUM(B8:D8) -> 4921621 | F8: Subscriptions + Tuppence introductions + AI services.
A9: ── COSTS (Rev C — restated) ───────────────────────────────────
A10: Subscriptions — PAID + COMMITTED | B10: ='Subscriptions Register'!$E$59*12 -> 3982.2 | C10: ='Subscriptions Register'!$E$59*12 -> 3982.2 | D10: ='Subscriptions Register'!$E$59*12 -> 3982.2 | E10: =SUM(B10:D10) -> 11946.6 | F10: Held flat deliberately. The stack is fixed-cost: one server, one design subscription, one image tool. It does not scale with sellers, which is the whole architectural bet.
A11: Human operations | B11: =IF('Assumptions Rev C'!$B$41>99,0,'Assumptions Rev C'!$B$44*12) -> 20280.814 | C11: =IF('Assumptions Rev C'!$B$41>99,0,'Assumptions Rev C'!$B$44*12) -> 20280.814 | D11: =IF('Assumptions Rev C'!$B$41>99,0,'Assumptions Rev C'!$B$44*12*2) -> 40561.629 | E11: =SUM(B11:D11) -> 81123.257 | F11: Flat in Years 1-2; DOUBLED in Year 3 on the assumption that 148 cities and 16,872 sellers cannot be served by the same three people. That is an assumption, and a conservative one.
A12: Accountant + software | B12: =IF('Assumptions Rev C'!$B$48>12,0,'Assumptions Rev C'!$B$49*(13-'Assumptions Rev C'!$B$48)) -> 1850.7094 | C12: ='Assumptions Rev C'!$B$49*12 -> 1850.7094 | D12: ='Assumptions Rev C'!$B$49*12 -> 1850.7094 | E12: =SUM(B12:D12) -> 5552.1283 | F12: From month 1 in Year 1 (David, 18 Aug). Year 2+ full year.
A13: PostgreSQL hosting | B13: =IF('Assumptions Rev C'!$B$25>12,0,'Assumptions Rev C'!$B$26*(13-'Assumptions Rev C'!$B$25)) -> 133.38 | C13: ='Assumptions Rev C'!$B$26*12 -> 266.76 | D13: ='Assumptions Rev C'!$B$26*12 -> 266.76 | E13: =SUM(B13:D13) -> 666.9 | F13: Budgeted from month 7 of Year 1.
A14: Payment processing (Paystack effective) | B14: =B8*'Assumptions Rev C'!$B$54 -> 8957.2296 | C14: =C8*'Assumptions Rev C'!$B$54 -> 26327.408 | D14: =D8*'Assumptions Rev C'!$B$54 -> 152184.38 | E14: =SUM(B14:D14) -> 187469.02 | F14: Formula-driven off the assumption — change the rate once and all three years reprice. Kept from the 16 Jul audit, which fixed this exact class of error.
A15: AI metered API | B15: ='AI Lanes Rev C'!B22 -> 250.8 | C15: ='AI Lanes Rev C'!C22 -> 516.8 | D15: ='AI Lanes Rev C'!D22 -> 3359.2 | E15: =SUM(B15:D15) -> 4126.8 | F15: Restated onto the OpenAI base lane. Premier models are now insurance, not the default.
A16: AI swap-out launch provision (one-off) | B16: ='Assumptions Rev C'!$B$32 -> 280 | C16: 0 | D16: 0 | E16: =SUM(B16:D16) -> 280 | F16: $40 x 7 models, at launch only.
A17: TOTAL COSTS | B17: =SUM(B10:B16) -> 35735.133 | C17: =SUM(C10:C16) -> 53224.692 | D17: =SUM(D10:D16) -> 202204.88 | E17: =SUM(B17:D17) -> 291164.7
A18: ── RESULT ─────────────────────────────────────────────────────
A19: NET INCOME | B19: =B8-B17 -> 199418.87 | C19: =C8-C17 -> 637948.31 | D19: =D8-D17 -> 3793089.1 | E19: =SUM(B19:D19) -> 4630456.3
A20: Operating margin | B20: =IFERROR(B19/B8,0) -> 0.84803519 | C20: =IFERROR(C19/C8,0) -> 0.92299368 | D20: =IFERROR(D19/D8,0) -> 0.94938924 | F20: Rev B reported 95.3% / 95.3% / 95.8%. The fall is entirely the people line — and it is the honest number.
A21: Margin as reported in Rev B (16 Jul) | B21: 0.9527 | C21: 0.9525 | D21: 0.9583 | F21: For comparison.
A22: Cost per seller per year | B22: =IFERROR(B17/B6,0) -> 4.5873085 | C22: =IFERROR(C17/C6,0) -> 12.18514 | D22: =IFERROR(D17/D6,0) -> 11.984642 | F22: Rev B reported $1 / $5 / $7. Revenue per seller is $30 / $158 / $237.
A24: ── BREAK-EVEN — what it now takes to cover the fixed base ─────
A25: Break-even measure | B25: Count | F25: Basis
A26: Starter subscriptions ($5/mo) | B26: =ROUNDUP('Cash Reserve'!$B$10/5,0) -> 436 | F26: Pure $5 Starters.
A27: Pro subscriptions ($20/mo) | B27: =ROUNDUP('Cash Reserve'!$B$10/20,0) -> 109 | F27: Pure $20 Pros.
A28: Sellers at the modelled mix (25% Starter, 8% Pro) | B28: =ROUNDUP('Cash Reserve'!$B$10/(0.25*5+0.08*20),0) -> 764 | F28: The realistic figure. 65% Free, 2% Agency free.
A29: Founding cities of 60 sellers | B29: =ROUNDUP('Cash Reserve'!$B$10/(0.25*5+0.08*20)/60,1) -> 12.8 | F29: How many city cohorts the fixed base needs.
A30: Rev B / token-economics equivalent (tech stack only) | B30: 131 | F30: AI_TOKEN_ECONOMICS rev3 put break-even at ~131 sellers on a $327.85 tech floor, ~2.2 cities. Rev C's figure is the same calculation with the people line included.
A32: ── CASH ───────────────────────────────────────────────────────
A33: Cash measure | B33: $ | F33: Note
A34: Deepest cumulative cash deficit in Year 1 | B34: =-MIN(0,MIN('Year 1 Cash Flow Rev C'!$B$20:$M$20)) -> 5361.402 | F34: The real capital requirement. Read live from the cash-flow sheet.
A35: First month cumulative cash turns positive | B35: =IF('Year 1 Cash Flow Rev C'!$N$32=99,"not in Year 1",'Year 1 Cash Flow Rev C'!$N$32) -> 7 | F35: Month number. If this reads 'not in Year 1', the ramp does not self-fund and the reserve must carry the whole year.
A36: Recommended opening cash reserve | B36: ='Cash Reserve'!$B$22 -> 16400 | F36: From 'Cash Reserve' — the largest of three sizings, plus stress.
A37: Year-1 net cash | B37: ='Year 1 Cash Flow Rev C'!$N$19 -> 199418.87 | F37: Cross-check against NET INCOME above; small differences are the one-off provision timing.
A39: ── SCENARIOS ──────────────────────────────────────────────────
A40: Scenario | B40: Y1 revenue | C40: Y1 costs | D40: Y1 net | E40: Margin | F40: What it tests
A41: PLAN — as modelled | B41: =B8 -> 235154 | C41: =B17 -> 35735.133 | D41: =B41-C41 -> 199418.87 | E41: =IFERROR(D41/B41,0) -> 0.84803519 | F41: The base case.
A42: Ramp lands at 50% | B42: =B8*0.5 -> 117577 | C42: =B17-B8*'Assumptions Rev C'!$B$54*0.5 -> 31256.519 | D42: =B42-C42 -> 86320.481 | E42: =IFERROR(D42/B42,0) -> 0.73416129 | F42: Revenue halves; only payment fees fall with it. Everything else is fixed. This is the scenario that matters, because the ramp is a projection and marketplace ramps miss.
A43: Ramp lands at 25% | B43: =B8*0.25 -> 58788.5 | C43: =B17-B8*'Assumptions Rev C'!$B$54*0.75 -> 29017.211 | D43: =B43-C43 -> 29771.289 | E43: =IFERROR(D43/B43,0) -> 0.50641348 | F43: The pessimistic case: one city works, the waves stall.
A44: People deferred to month 7 | B44: =B8 -> 235154 | C44: =B17-'Assumptions Rev C'!$B$44*6 -> 25594.726 | D44: =B44-C44 -> 209559.27 | E44: =IFERROR(D44/B44,0) -> 0.8911576 | F44: Hire when the waves start rather than at launch. Tests how much of the cash trough the people line actually causes.
A45: Tech-only (no people, no accountant) | B45: =B8 -> 235154 | C45: =B17-'Assumptions Rev C'!$B$44*12-'Assumptions Rev C'!$B$49*12 -> 13603.61 | D45: =B45-C45 -> 221550.39 | E45: =IFERROR(D45/B45,0) -> 0.94215021 | F45: The Rev B world, for comparison. Shows exactly what the two new lines cost.
A46: Hetzner rescale forced (+129%) | B46: =B8 -> 235154 | C46: =B17+('Assumptions Rev C'!$B$17-'Assumptions Rev C'!$B$16)*'Assumptions Rev C'!$B$7*12 -> 36013.197 | D46: =B46-C46 -> 199140.8 | E46: =IFERROR(D46/B46,0) -> 0.84685271 | F46: The grandfathering is lost. Barely visible — which is the useful answer: this risk is real but small, and should not drive a pre-launch server migration.

Sheet Assumptions Rev C
A1: ASSUMPTIONS — Rev C · 18 Aug 2026 · EDIT THE BLUE CELLS ONLY
A2: LEGEND: | B2: blue = you edit | C2: black = formula | D2: Yellow fill = the number most worth arguing about. Every other sheet reads from here — change a value once and the whole model reprices.
A4: Assumption | B4: Value | C4: Unit | D4: Source / note
A5: ── FOREIGN EXCHANGE ──────────────────────────────────────────
A6: ZAR per USD | B6: 16.21 | C6: R/$ | D6: LIVE 18 Aug 2026 (Frankfurter/ECB + open.er-api). WAS 18.50 in Rev B — a 14% stale assumption. RUL-022 made FX live in the app; this model had not followed. Re-read this monthly.
A7: USD per EUR | B7: 1.1586 | C7: $/€ | D7: Live 18 Aug 2026 (open.er-api, USD/EUR 0.863128 inverted). Hetzner bills in EUR.
A8: ── SCALE & REVENUE (carried unchanged from the 16 Jul audited model) ──
A9: Sellers — Year 1 | B9: 7790 | C9: count | D9: '3-Year Summary' as filed. PROJECTION, not a decision.
A10: Sellers — Year 2 | B10: 4368 | C10: count | D10: As filed. NOTE: lower than Year 1 — a cumulative-vs-incremental inconsistency never reconciled. Treat Y2/Y3 seller counts with caution.
A11: Sellers — Year 3 | B11: 16872 | C11: count | D11: As filed.
A12: Revenue — Year 1 | B12: 235154 | C12: $ | D12: As filed (subs 158,968 + intros 42,228 + AI 33,958).
A13: Revenue — Year 2 | B13: 691173 | C13: $ | D13: As filed.
A14: Revenue — Year 3 | B14: 3995294 | C14: $ | D14: As filed.
A15: ── HETZNER (2026 repricing — see 'Infrastructure Rev C') ─────
A16: Hetzner CPX32 — OUR legacy price | B16: 15.49 | C16: €/mo | D16: Grandfathered from the 25 May 2026 order. Hetzner protects existing servers — but ANY rescale reprices to the line below.
A17: Hetzner CPX32 — current NEW-ORDER price | B17: 35.49 | C17: €/mo | D17: +129% vs our legacy price. Two 2026 increases: ~+30% on 1 Apr, then CPX/CCX up to +176% on 15 Jun. Source: Hetzner price-adjustment notice + Aug 2026 price tables.
A18: Hetzner CX43 (8 vCPU / 16 GB / 160 GB) | B18: 15.99 | C18: €/mo | D18: The June repricing hit CPX/CCX and left the new CX line cheap. CX43 doubles our CPU and RAM for +€0.50/mo vs the legacy CPX32. This is the migration target.
A19: Block storage volume — 100 GB | B19: 5.72 | C19: €/mo | D19: €0.0572/GB/mo (was €0.052 — +10%). Holds the 39 GB Overpass DB.
A20: Object storage — daily DB backups | B20: 5.99 | C20: €/mo | D20: 14-day retention. canon.yml.
A21: Storage Box BX11 — 1 TB offsite (3-2-1 tier 2) | B21: 3.8 | C21: €/mo | D21: ops/backup/SETUP_RUNBOOK.md designs it; provisioning status UNKNOWN on disk and it appears in NO cost model. Budgeted here so it stops being invisible.
A22: Hetzner — ACTUAL bill, last month | B22: 32 | C22: $/mo | D22: David's actual, 15 Aug 2026. Used as the Rev C infrastructure base in preference to the component sum, because it is measured.
A23: ── POSTGRESQL (post-launch per David's DB ruling, 29 Jul 2026) ──
A24: Postgres option in force (A / B / C / D / E) | B24: B | C24: letter | D24: A=self-host on existing box · B=2nd Hetzner CX43 (DEFAULT) · C=Hetzner CCX23 dedicated · D=Neon Launch managed · E=Supabase Pro. Priced on 'Infrastructure Rev C'.
A25: Postgres starts in month | B25: 7 | C25: month 1-12 | D25: David's DB ruling: launch runs on SQLite, no engine migration inside the launch window; Postgres is post-launch and TRIGGER-driven (db-locked errors / write growth / a second app server). Month 7 = budgeted placeholder, NOT a decision to migrate. Set 99 to switch it off.
A26: Postgres — monthly cost once running | B26: 22.23 | C26: $/mo | D26: Option B: Hetzner CX43 €15.99 + 20% automatic backups €3.20 = €19.19. Change this if the option changes.
A27: ── AI — SUBSCRIPTIONS, LANES AND THE SWAP-OUT PROVISION ──────
A28: Claude subscription ($200 + 15%) | B28: 230 | C28: $/mo | D28: David's actual, 15 Aug 2026. Includes the 15% ZA import levy. Booked as a PLATFORM cost because it is also the fix-agent's brain (RUL-013).
A29: Higgsfield Ultra ($39 + 15%) | B29: 44.85 | C29: $/mo | D29: David's actual, 15 Aug 2026. Listing exemplars and feature video.
A30: Launch provision PER AI MODEL | B30: 40 | C30: $ one-off | D30: David's instruction, 18 Aug 2026. Opens a funded key on every lane in the swap chain so a failover is never blocked on a payment. Supersedes the $20/lane figure in AI_TOKEN_ECONOMICS rev3.
A31: Number of swap-out models provisioned | B31: 7 | C31: count | D31: luna · terra · sol (OpenAI base) · haiku-4.5 · sonnet-4.6 (Anthropic failover) · mistral-medium-3.5 (Scaleway EU safety net) · grok-4.6 (4th, text only). Listed on 'AI Lanes Rev C'.
A32: AI swap-out launch provision — TOTAL | B32: ='Assumptions Rev C'!$B$30*'Assumptions Rev C'!$B$31 -> 280 | C32: $ one-off | D32: One-off at launch. A RESERVE, not a spend — unspent provision is runway.
A33: Treat the provision as recurring monthly? (1=yes, 0=no) | B33: 0 | C33: flag | D33: 0 = one-off launch cost (David's wording). Set to 1 to stress-test it as a monthly float top-up.
A34: Base-lane cost factor vs Sonnet 4.6 | B34: 0.72 | C34: x | D34: gpt-5.6-terra $2/$12 vs claude-sonnet-4-6 $3/$15 = 0.67 in / 0.80 out; 0.72 blended at our observed in:out shape. Lower = cheaper.
A35: Base-lane cost factor vs the Rev B photo-gate model | B35: 0.4 | C35: x | D35: gpt-5.6-luna $0.20/$1.20 vs Gemini 3 Flash $0.50/$3.00 = exactly 0.40 on both. Against Haiku 4.5 ($1/$5) the factor is 0.20-0.24 — the 77-79% saving in RUL-002.
A36: ── HUMAN OPERATIONS (David's instruction, 18 Aug 2026) ───────
A37: People — headcount | B37: 3 | C37: people | D37: David: 'at least three people'.
A38: Hours per person per day | B38: 2 | C38: hrs | D38: David: '2 hours a day'.
A39: Days worked per month | B39: 30.44 | C39: days | D39: 30.44 = every day (365/12). Use 21.7 for weekdays only. A marketplace does not close at weekends — but three people covering 7 days is a roster, not a job.
A40: Nominal rate per hour | B40: 150 | C40: R/hr | D40: DEFAULT SET BY CLAUDE, not by David — a nominal ZA rate for skilled part-time support work. Change it: the sensitivity grid on 'People & Accountant' shows R100 / R150 / R250 side by side.
A41: Human ops start in month | B41: 1 | C41: month 1-12 | D41: Set 99 to switch the line off entirely and see the tech-only case.
A42: Hours per month — total | B42: ='Assumptions Rev C'!$B$37*'Assumptions Rev C'!$B$38*'Assumptions Rev C'!$B$39 -> 182.64 | C42: hrs/mo
A43: Human ops — cost per month | B43: ='Assumptions Rev C'!$B$42*'Assumptions Rev C'!$B$40 -> 27396 | C43: R/mo
A44: Human ops — cost per month | B44: ='Assumptions Rev C'!$B$43/'Assumptions Rev C'!$B$6 -> 1690.0679 | C44: $/mo
A45: ── ACCOUNTANT (David's instruction: from Month 1) ─────────────
A46: Accountant fee | B46: 2000 | C46: R/mo | D46: David, 18 Aug 2026.
A47: Accounting software | B47: 500 | C47: R/mo | D47: Carried from the Rev B assumption. Zero it if it is bundled in the fee.
A48: Accountant starts in month | B48: 1 | C48: month 1-12 | D48: David's instruction — and FINANCE_CANON §4 independently recommended engaging at FIRST REVENUE rather than Year 2: 'a Year-1 structuring consult is cheap vs one wrong VAT call.' Year 1 on plan crosses the R2.3m compulsory VAT threshold.
A49: Accountant + software — per month | B49: =('Assumptions Rev C'!$B$46+'Assumptions Rev C'!$B$47)/'Assumptions Rev C'!$B$6 -> 154.22579 | C49: $/mo
A50: ── PAYMENTS ───────────────────────────────────────────────────
A51: Paystack percentage fee | B51: 0.029 | C51: % | D51: 2.9% (VAT excl.). Account 1777715 Live/Approved; international acceptance already enabled (RUL-019).
A52: Paystack fixed fee | B52: 1 | C52: R/tx | D52: Waived under R10.
A53: Blended average transaction size | B53: 110 | C53: R | D53: Mix of R36 single-T, R72-180 packs, R90/R360 subs. TUNE FROM LIVE PAYSTACK DATA once settlements start.
A54: Paystack effective blended rate | B54: ='Assumptions Rev C'!$B$51+'Assumptions Rev C'!$B$52/'Assumptions Rev C'!$B$53 -> 0.038090909 | C54: %
A55: ── CASH RESERVE POLICY ────────────────────────────────────────
A56: Reserve — months of fixed cost to hold | B56: 6 | C56: months | D56: Recommended 6. Covers the whole pre-revenue-scale window: the model's 95% margin is ANNUAL, and the cash risk is entirely in months 1-6 where fixed cost runs ahead of the ramp.
A57: Reserve stress factor | B57: 1.25 | C57: x | D57: 25% headroom for the things a plan does not know about. Set 1.00 for the bare figure.

Sheet Subscriptions Register
A1: THIRD-PARTY SUBSCRIPTION REGISTER — every external dependency, Rev C 18 Aug 2026
A2: Built from the Ops Dashboard infrastructure panel (bea_main.py _INFRA_CHECKS), subscription_monitor.py CATALOG (41 external deps) and feature_flags.json. STATUS drives the totals below: PAID and COMMITTED are in the launch cost base; PLANNED is budgeted but uncontracted; HELD is wired-but-off (B7 rule: stays false until David enables it WITH a hard monthly ceiling); CLOSED is a tombstone kept so it cannot return by accident.
A4: Service | B4: Category | C4: What it is for | D4: Status | E4: $/month | F4: $/year | G4: Cost basis · cap · risk
A5: Claude (Anthropic) sub | B5: AI | C5: Design/guidance tool + the fix agent's brain | D5: PAID | E5: 230 | F5: =E5*12 -> 2760 | G5: $200 + 15% ZA import levy. David's actual. Platform cost per RUL-013, not a personal one. Largest single line in the tech stack.
A6: Higgsfield Ultra | B6: AI | C6: Listing exemplar imagery + feature video | D6: PAID | E6: 44.85 | F6: =E6*12 -> 538.2 | G6: $39 + 15%. Nano Banana Pro 2 = 2 credits/image; Kling 3.0 = 12 credits/clip. Credit balance ~1,988 at Jul 2026.
A7: Hetzner Cloud | B7: Infrastructure | C7: CPX32: FastAPI + SQLite + Redis + nginx + volume + backup bucket | D7: PAID | E7: 32 | F7: =E7*12 -> 384 | G7: ACTUAL last-month bill. Grandfathered at €15.49 for the box; new-order price is €35.49. See 'Infrastructure Rev C'.
A8: Domain trustsquare.co | B8: Infrastructure | C8: Domain registration | D8: PAID | E8: 1 | F8: =E8*12 -> 12 | G8: ~$12/yr amortised.
A9: Resend | B9: Email | C9: Transactional, magic-link and support email | D9: COMMITTED | E9: 20 | F9: =E9*12 -> 240 | G9: Free tier today (1 domain, <3k/mo); paid 50k tier B7-approved, activation 27 Aug 2026 — inside the launch window. Ceiling $20/mo.
A10: OpenAI API | B10: AI | C10: BASE usage lane (RUL-002) — the runtime inside the app | D10: PAID | E10: 0 | F10: =E10*12 -> 0 | G10: Metered, not a subscription — modelled in 'AI Lanes Rev C'. gpt-5.6-luna $0.20/$1.20, terra $2/$12. FLIP NOT DONE: P1-P6 preconditions outstanding.
A11: Anthropic API | B11: AI | C11: AUTO-FAILOVER lane | D11: PAID | E11: 0 | F11: =E11*12 -> 0 | G11: Metered. Haiku 4.5 $1/$5, Sonnet 4.6 $3/$15. Dearer than base BY DESIGN — continuity insurance. Continuity tolerance 6.0x base.
A12: Scaleway | B12: AI | C12: EU SAFETY NET — bans and jurisdiction only | D12: PAID | E12: 0 | F12: =E12*12 -> 0 | G12: Metered, cost-exempt by role, alert-on-use. mistral-medium-3.5 €1.50/€7.50. GAP: free-tier monthly cap and expiry are recorded as null — an unknown cliff.
A13: Cloudflare (CDN/DNS/WAF) | B13: Infrastructure | C13: TLS, CDN, DDoS, cache purge, WAF origin lockdown | D13: FREE | E13: 0 | F13: =E13*12 -> 0 | G13: Free tier carries us today. Origin CA cert valid to 2041 — no renewal.
A14: Cloudflare R2 | B14: Infrastructure | C14: Primary photo/video object storage, $0 egress | D14: PAID | E14: 4 | F14: =E14*12 -> 48 | G14: ~$4/mo at Year-1 scale; modelled at $1/city/mo in the original Assumptions. Mirrored to Hetzner local disk.
A15: Paystack | B15: Payments | C15: ZAR + worldwide card acceptance | D15: PAID | E15: 0 | F15: =E15*12 -> 0 | G15: No monthly fee — 2.9% + R1 per transaction, 3.81% effective blended. Modelled as a % of revenue, not a subscription.
A16: GeoNames | B16: Data | C16: Country/region/city/suburb seeding | D16: FREE | E16: 0 | F16: =E16*12 -> 0 | G16: Free signup, one-time seed. Not a runtime dependency.
... A49: Amadeus | B49: Data | C49: (would have been) flight data | D49: CLOSED | E49: 0 | F49: =E49*12 -> 0 | G49: Self-service portal shut 17 Jul 2026. Slot repointed to Travelpayouts.
A51: ── TOTALS BY STATUS ───────────────────────────────────────────
A52: In the cost base now — PAID | D52: PAID | E52: =SUMIFS($E$5:$E$49,$D$5:$D$49,"PAID") -> 311.85 | F52: =E52*12 -> 3742.2 | G52: =COUNTIFS($D$5:$D$49,"PAID") -> 9
A53: Committed before launch — COMMITTED | D53: COMMITTED | E53: =SUMIFS($E$5:$E$49,$D$5:$D$49,"COMMITTED") -> 20 | F53: =E53*12 -> 240 | G53: =COUNTIFS($D$5:$D$49,"COMMITTED") -> 1
A54: Free tier — FREE (the quiet backbone: 20 dependencies at zero) | D54: FREE | E54: =SUMIFS($E$5:$E$49,$D$5:$D$49,"FREE") -> 0 | F54: =E54*12 -> 0 | G54: =COUNTIFS($D$5:$D$49,"FREE") -> 19
A55: Budgeted, not contracted — PLANNED | D55: PLANNED | E55: =SUMIFS($E$5:$E$49,$D$5:$D$49,"PLANNED") -> 176.63 | F55: =E55*12 -> 2119.56 | G55: =COUNTIFS($D$5:$D$49,"PLANNED") -> 8
A56: Wired but OFF — HELD (B7 rule) | D56: HELD | E56: =SUMIFS($E$5:$E$49,$D$5:$D$49,"HELD") -> 0 | F56: =E56*12 -> 0 | G56: =COUNTIFS($D$5:$D$49,"HELD") -> 4
A57: Tombstones — CLOSED (must never return) | D57: CLOSED | E57: =SUMIFS($E$5:$E$49,$D$5:$D$49,"CLOSED") -> 0 | F57: =E57*12 -> 0 | G57: =COUNTIFS($D$5:$D$49,"CLOSED") -> 4
A59: SUBSCRIPTION COST BASE AT LAUNCH (PAID + COMMITTED) | E59: =E52+E53 -> 331.85 | F59: =E59*12 -> 3982.2 | G59: This is the number to compare against revenue. AI metered spend is NOT here — it is on 'AI Lanes Rev C'.
A60: FULL STACK IF EVERY PLANNED ROW ACTIVATES | E60: =E52+E53+E55 -> 508.48 | F60: =E60*12 -> 6101.76 | G60: Includes Mapbox at $50, which the file itself recommends leaving off — the honest ceiling, not the plan.
A62: WHAT THIS REGISTER CHANGES: before Rev C, five infrastructure lines were modelled and thirty-five dependencies were not. Most of the thirty-five are free — which is the point. The platform's data layer (maps, geocoding, FX, heritage, property comps, card catalogues) runs on open data and free tiers by deliberate design, and that design is worth defending: it is why the tech stack costs under $350/month at launch.
A63: THE THREE ROWS THAT DESERVE A DECISION: (1) Mapbox $50 — the file's own recommendation is to leave it off; OSM already works and paid tiles buy no trust. (2) External uptime monitor — a LAUNCH GATE with no vendor and no price, currently the cheapest unclosed risk on the board. (3) eBay Browse — flagged live with a keyset still pending, so a lane the app believes is working is not.

Sheet Infrastructure Rev C
A1: INFRASTRUCTURE — Hetzner 2026 repricing and the PostgreSQL question · Rev C 18 Aug 2026
A2: A. THE HETZNER REPRICING — what happened, and what it costs us
A3: Hetzner raised cloud prices TWICE in 2026: roughly +30% on 1 April, then a much larger adjustment on 15 June in which the CPX and CCX lines rose by up to +176%. Existing servers keep their legacy terms — but the price adjustment applies to new orders AND to rescales. Our production box was ordered on 25 May 2026, so it sits between the two increases and is grandfathered at €15.49.
A4: The consequence is not a bill today. It is that our production server is now a thing we cannot resize without repricing it by +129%, and that fact appears nowhere in the project's documentation or its cost model. That is the finding.
A6: Hetzner line | B6: €/month | C6: $/month | D6: $/year | E6: Status | F6: Note
A7: Production box — CPX32 (4 vCPU / 8 GB / 160 GB), OUR legacy price | B7: ='Assumptions Rev C'!$B$16 -> 15.49 | C7: =B7*'Assumptions Rev C'!$B$7 -> 17.946714 | D7: =C7*12 -> 215.36057 | E7: GRANDFATHERED | F7: Ordered 25 May 2026, before the 15 June adjustment. Protected while untouched.
A8: Same box at the CURRENT new-order price | B8: ='Assumptions Rev C'!$B$17 -> 35.49 | C8: =B8*'Assumptions Rev C'!$B$7 -> 41.118714 | D8: =C8*12 -> 493.42457 | E8: RISK | F8: What we would pay on any rescale, rebuild or migration. +129%. Treat a resize as a €240/yr decision, not a click.
A9: Block storage volume — 100 GB (Overpass DB) | B9: ='Assumptions Rev C'!$B$19 -> 5.72 | C9: =B9*'Assumptions Rev C'!$B$7 -> 6.627192 | D9: =C9*12 -> 79.526304 | E9: ACTIVE | F9: €0.0572/GB/mo, up ~10%. Expand only above 80% disk.
A10: Object storage — daily DB backups, 14-day retention | B10: ='Assumptions Rev C'!$B$20 -> 5.99 | C10: =B10*'Assumptions Rev C'!$B$7 -> 6.940014 | D10: =C10*12 -> 83.280168 | E10: ACTIVE | F10: canon.yml.
A11: Storage Box BX11 — 1 TB offsite (3-2-1 tier 2) | B11: ='Assumptions Rev C'!$B$21 -> 3.8 | C11: =B11*'Assumptions Rev C'!$B$7 -> 4.40268 | D11: =C11*12 -> 52.83216 | E11: UNVERIFIED | F11: Designed in ops/backup/SETUP_RUNBOOK.md and referenced by the laptop backup runbook — but in NO cost model and its provisioning state is unknown on disk. Budgeted here. ACTION: confirm whether this exists.
A12: Component sum (legacy box + volume + object storage + storage box) | B12: =B7+B9+B10+B11 -> 31 | C12: =B12*'Assumptions Rev C'!$B$7 -> 35.9166 | D12: =C12*12 -> 430.9992 | F12: Bottom-up.
A13: ACTUAL last-month Hetzner bill (David, 15 Aug 2026) — USED IN THE MODEL | C13: ='Assumptions Rev C'!$B$22 -> 32 | D13: =C13*12 -> 384 | F13: Measured beats modelled. The gap to the component sum is the Storage Box question above.
A14: Variance: actual less component sum | C14: =C13-C12 -> -3.9166 | F14: A positive variance means we are paying for something the component list does not name. A negative means the Storage Box is not provisioned.
A16: B. THE OPPORTUNITY THE REPRICING CREATED — CX43
A17: Option | B17: €/month | C17: vCPU | D17: RAM (GB) | E17: Disk (GB) | F17: Verdict
A18: Our CPX32 today (legacy price) | B18: ='Assumptions Rev C'!$B$16 -> 15.49 | C18: 4 | D18: 8 | E18: 160 | F18: Baseline. Cheap, but frozen — cannot be resized without repricing.
A19: CPX32 at today's new-order price | B19: ='Assumptions Rev C'!$B$17 -> 35.49 | C19: 4 | D19: 8 | E19: 160 | F19: What a rebuild costs. Same machine, +129%.
A20: CX43 — the migration target | B20: ='Assumptions Rev C'!$B$18 -> 15.99 | C20: 8 | D20: 16 | E20: 160 | F20: TWICE the CPU and TWICE the RAM for +€0.50/mo over our legacy price. The June increase hit CPX/CCX and left the CX line cheap.
A21: CX43 premium over our legacy price, per month | B21: =B20-B18 -> 0.5 | F21: The 16 GB box that ROADMAP_4_AI_INDEPENDENCE says we would need before hosting any local model is now within fifty cents a month of what we already pay.
A23: CAUTION, and it is the reason this is a finding rather than a recommendation: migrating to CX43 means BUILDING A NEW SERVER, eleven days before a launch. David's own doctrine (Addendum 4) is 'don't change a tested tool mid-design'. The right shape is to record the option now, and take it the first time the box needs to change anyway — a disk expansion, a Postgres split, or the day a local model is wanted. Not this month.
A25: C. POSTGRESQL — what it costs, and when
A26: DAVID'S RULING STANDS AND HAS NOT CHANGED. DB_DECISION_2026-07-29: 'Launch runs on SQLite. No engine migration inside the launch window.' Postgres is a post-launch project, executed when a TRIGGER fires — database-locked errors under real concurrency, sustained write growth, or the need for a second app server. The reason given was: 'Migration pre-launch = new bug surface at maximum stakes for a problem we do not have.' Rev C therefore does NOT move the launch to Postgres. It BUDGETS the move from month 7 so that when a trigger fires the money is already provided for, and prices the five ways of doing it.
A28: Option | B28: € or $ basis | C28: $/month | D28: $/year | E28: Ops burden | F28: Assessment
A29: A — Self-host on the EXISTING box | B29: included | C29: 0 | D29: =C29*12 -> 0 | E29: none (until it isn't) | F29: Free, and wrong past a point. Postgres on the same 8 GB box that runs FastAPI, Redis, nginx, n8n and a 39 GB Overpass DB competes for the RAM that made us want Postgres. Fine as a first step, not as the answer.
A30: B — Second Hetzner box, CX43 + backups ← DEFAULT | B30: €15.99 + 20% | C30: 22.23 | D30: =C30*12 -> 266.76 | E30: low | F30: 8 vCPU / 16 GB dedicated to the database, at new-order pricing, with Hetzner's 20% automatic-backup add-on. Satisfies the ruling's own third trigger ('the need for a second app server') in the same move. Same provider, same network, same invoice.
A31: C — Hetzner CCX23 dedicated vCPU | B31: €85.99 | C31: 99.63 | D31: =C31*12 -> 1195.56 | E31: low | F31: Dedicated cores, no noisy neighbours. 4.5x option B for a workload we have not yet measured. Right answer later, wrong answer now.
A32: D — Neon Launch (managed, serverless) | B32: $0.106/CU-hr + $0.35/GB | C32: 77.38 | D32: =C32*12 -> 928.56 | E32: very low | F32: 1 CU (1 vCPU / 4 GB) running 24/7 = 730 hrs x $0.106 = $77.38, plus storage. Scale-to-zero saves nothing for an always-on marketplace. Managed backups and branching are real benefits; the price is not.
A33: E — Supabase Pro | B33: $25 flat + compute | C33: 25 | D33: =C33*12 -> 300 | E33: very low | F33: Cheapest managed option, but it is a backend PLATFORM (auth, storage, realtime, edge functions) and we already have all of those. We would be buying a bundle to use one part of it — and adding a US-hosted data dependency to a stack whose jurisdiction posture is deliberate.
A35: IN FORCE IN THE MODEL — option | B35: ='Assumptions Rev C'!$B$24 -> B | C35: ='Assumptions Rev C'!$B$26 -> 22.23 | D35: =C35*12 -> 266.76 | E35: ="from month "&'Assumptions Rev C'!$B$25 -> from month 7 | F35: Change the option letter and the cost on 'Assumptions Rev C'. Set the start month to 99 to remove it entirely.
A37: THE PART THAT IS NOT A MONEY QUESTION: the migration is cheap only if the descent rule is actually walking. It is not. The SQLite-specific surface in bea_main.py measured 53 datetime('now') expressions at the 29 July ruling and measures 53 today — the apparent improvement in the other counters was a measurement fix, not work, and one expression has actually been ADDED since. The ratchet is holding the line but the descent is not happening. Whatever Postgres costs in euros, the real price is the code conversion, and three weeks of pre-launch work have paid none of it down.

Sheet AI Lanes Rev C
A1: AI — LANES, SWAP-OUT PROVISION AND THE RESTATED RUNNING COST · Rev C 18 Aug 2026
A2: DAVID'S THESIS, TESTED: 'AI costs will be less due to our AI changes where we will be using better capable models costing less, and placing the premier models only as backups or third order swap outs in emergencies.' The register supports it. On the tiers that carry the volume, the base lane now scores HIGHER and costs 77-79% LESS than the model it replaces. The thesis is correct — with one qualification that matters for budgeting, in section D.
A4: A. THE SWAP-OUT CHAIN AND THE $40-PER-MODEL LAUNCH PROVISION
A5: Model | B5: Lane / role | C5: $/Mtok in | D5: $/Mtok out | E5: x base (in) | F5: Provision $ | G5: Why it is in the chain
A6: gpt-5.6-luna | B6: OpenAI — BASE (haiku/vision/triage) | C6: 0.2 | D6: 1.2 | E6: =IFERROR(C6/$C$6,0) -> 1 | F6: ='Assumptions Rev C'!$B$30 -> 40 | G6: Anthropic base for months; 80% price cut 30 Jul 2026. Scores 51.24 AA vs Haiku's 29.58. Golden set 8/8 on production prompts.
A7: gpt-5.6-terra | B7: OpenAI — BASE (sonnet tier, paid 5T deep-dives) | C7: 2 | D7: 12 | E7: =IFERROR(C7/$C$6,0) -> 10 | F7: ='Assumptions Rev C'!$B$30 -> 40 | G7: Carries the buyer-funded work. Watch reasoning-token burn — observed twice on this project (17 Jul, 31 Jul).
A8: gpt-5.6-sol | B8: OpenAI — DESIGN tier (from 1 Sep, RUL-013) | C8: 5 | D8: 30 | E8: =IFERROR(C8/$C$6,0) -> 25 | F8: ='Assumptions Rev C'!$B$30 -> 40 | G8: Takes over design work when Fable's pre-launch arrangement ends on 1 Sep. Expensive per token, low volume.
A9: claude-haiku-4-5 | B9: Anthropic — AUTO-FAILOVER | C9: 1 | D9: 5 | E9: =IFERROR(C9/$C$6,0) -> 5 | F9: ='Assumptions Rev C'!$B$30 -> 40 | G9: First lane on a dropout. Months live, prompts tuned, production-gated. Dearer than base BY DESIGN: continuity is worth a cost spike.
A10: claude-sonnet-4-6 | B10: Anthropic — AUTO-FAILOVER (reason tier) | C10: 3 | D10: 15 | E10: =IFERROR(C10/$C$6,0) -> 15 | F10: ='Assumptions Rev C'!$B$30 -> 40 | G10: 1.35x base on its tier. Also the guidance layer that authored this codebase — a different job from serving users.
A11: mistral-medium-3.5-128b | B11: Scaleway EU — SAFETY NET | C11: 1.65 | D11: 8.25 | E11: =IFERROR(C11/$C$6,0) -> 8.25 | F11: ='Assumptions Rev C'!$B$30 -> 40 | G11: Bans and EU jurisdiction only. COST-EXEMPT by role: gating a last resort on price means choosing to be down. Alert on use, time-box. €1.50/€7.50.
A12: grok-4.6 | B12: xAI — FOURTH, text tiers only | C12: 2 | D12: 6 | E12: =IFERROR(C12/$C$6,0) -> 10 | F12: ='Assumptions Rev C'!$B$30 -> 40 | G12: Placed fourth deliberately: promoting a third US lane above the EU one would leave three US lanes before any non-US one, and a ban hits all three at once. HARD 200K context cap mandatory — past it xAI rebills the ENTIRE request.
A13: MODELS PROVISIONED | B13: =COUNTA(A6:A12) -> 7 | F13: =SUM(F6:F12) -> 280 | G13: One-off at launch. Cross-check against 'Assumptions Rev C' models x $/model.
A14: Assumptions cross-check (models x $/model) | F14: ='Assumptions Rev C'!$B$32 -> 280 | G14: =IF(ROUND(F13,2)=ROUND(F14,2),"AGREES","MISMATCH — fix the model count on Assumptions Rev C") -> AGREES
A16: WHAT THE $280 ACTUALLY BUYS: a funded, tested key on every lane in the chain BEFORE launch. The failure it prevents is specific and has already nearly happened here — OPENAI_API_KEY was never provisioned on the server, so the 'swap-out switch' that the architecture describes could not have been thrown. A failover lane with no credit on it is not a lane. It is a reserve, not a spend: unspent provision is runway.
A18: B. RUNNING COST RESTATED — premier models demoted to insurance
A19: AI API cost line | B19: Year 1 | C19: Year 2 | D19: Year 3 | E19: 3-yr total | G19: Basis
A20: Rev A as filed (services only — photo gate NOT included) | B20: 349 | C20: 1136 | D20: 7797 | E20: =SUM(B20:D20) -> 9282 | G20: The line that never contained the photo anonymity gate — the silent gap David caught on 16 Jul.
A21: Rev B (16 Jul) — services on Sonnet + photo gate on Gemini 3 Flash | B21: 627 | C21: 1292 | D21: 8398 | E21: =SUM(B21:D21) -> 10317 | G21: The line in the model until today.
A22: REV C — everything on the OpenAI base lane | B22: =B21*'Assumptions Rev C'!$B$35 -> 250.8 | C22: =C21*'Assumptions Rev C'!$B$35 -> 516.8 | D22: =D21*'Assumptions Rev C'!$B$35 -> 3359.2 | E22: =SUM(B22:D22) -> 4126.8 | G22: Applies the base-lane factor from 'Assumptions Rev C'. Luna is exactly 0.40x Gemini 3 Flash on both input and output, so the photo gate and the cheap-class services scale cleanly.
A23: SAVING — Rev C vs Rev B | B23: =B21-B22 -> 376.2 | C23: =C21-C22 -> 775.2 | D23: =D21-D22 -> 5038.8 | E23: =SUM(B23:D23) -> 6190.2 | G23: Real, but note the scale before celebrating it — see section D.
A24: Saving as % of the Rev B line | B24: =IFERROR(1-B22/B21,0) -> 0.6 | C24: =IFERROR(1-C22/C21,0) -> 0.6 | D24: =IFERROR(1-D22/D21,0) -> 0.6
A26: C. WHAT A FAILOVER COSTS — the price of the insurance
A27: Scenario | B27: Serving lane | C27: Cost multiple | D27: Y1 AI cost at that lane | G27: Rule
A28: Normal running | B28: OpenAI base | C28: 1 | D28: =$B$22*C28 -> 250.8 | G28: The plan. Alert AL-1 fires if we are off-base for more than 60 minutes.
A29: Anthropic failover — haiku/vision/triage tiers | B29: Anthropic | C29: 4.55 | D29: =$B$22*C29 -> 1141.14 | G29: Within the 6.0x continuity tolerance. Accepted: every failover is now a cost increase BY DEFINITION, because the cheapest lane is the base.
A30: Anthropic failover — sonnet tier | B30: Anthropic | C30: 1.35 | D30: =$B$22*C30 -> 338.58 | G30: Cheap insurance on the tier that matters most for quality.
A31: Scaleway EU safety net | B31: Scaleway | C31: 7.85 | D31: =$B$22*C31 -> 1968.78 | G31: COST-EXEMPT by ruling. Reached only when the alternative is being down or banned. Alert AL-2 immediately and time-box.
A33: Read that table as an insurance premium, not a threat. A full year served entirely off the Anthropic failover lane costs a few hundred dollars more than the plan — less than one month of the human operations line. Continuity is, in this business, extremely cheap. That is the strongest argument for keeping the premier models exactly where David has put them.
A35: D. THE QUALIFICATION — where the AI money actually is
A36: AI cost | B36: Year 1 $ | C36: Share of AI spend
A37: Metered API — everything the app does for users, all year | B37: =B22 -> 250.8 | C37: =IFERROR(B37/$B$40,0) -> 0.065500131
A38: Subscriptions — Claude + Higgsfield, 12 months | B38: =('Assumptions Rev C'!$B$28+'Assumptions Rev C'!$B$29)*12 -> 3298.2 | C38: =IFERROR(B38/$B$40,0) -> 0.86137373
A39: Swap-out launch provision (one-off) | B39: ='Assumptions Rev C'!$B$32 -> 280 | C39: =IFERROR(B39/$B$40,0) -> 0.073126143
A40: TOTAL YEAR-1 AI COST | B40: =SUM(B37:B39) -> 3829
A42: THE POINT: optimising the metered lane is correct and David's reasoning is sound — but the metered lane is a rounding error next to the subscriptions. Cutting the API bill by 60% saves a few hundred dollars a year. The Claude and Higgsfield subscriptions cost $3,298 a year between them, and the swap-out provision costs $280 once. The AI cost question that is worth an hour of David's time is not which model serves a photo — it is whether the $230/month design subscription is still the right shape after 1 September, when RUL-013 ends Fable's pre-launch arrangement and design work moves to the gpt-5.6-sol lane. That is a real decision with a real number on it, and it is due in two weeks.
A44: STILL TRUE, STILL NOT DONE: the flip to the OpenAI base lane has SIX outstanding preconditions (P1-P6 in AI_LANE_GUIDANCE.md). P1 is David's — provision OPENAI_API_KEY on the server. P6 must be done BEFORE the shadow period, because _log_ai_spend currently records the INTENDED lane, not the serving one — meaning a sustained failover would quadruple haiku-tier cost and be invisible in the spend log. Until P6 lands, none of the savings in section B are measurable in production.

Sheet People & Accountant
A1: HUMAN OPERATIONS AND THE ACCOUNTANT · Rev C 18 Aug 2026
A2: This sheet contains the largest cost in the business, and it is the one the model has never carried. Everything on it is driven from the blue cells on 'Assumptions Rev C'. The hourly rate is a placeholder Claude chose, not a number David gave — the sensitivity grid below exists so he can settle it in one glance.
A4: A. HUMAN MAINTENANCE AND FOLLOW-UP — 3 people, 2 hours a day
A5: Driver | B5: Value | C5: Unit | G5: Note
A6: People | B6: ='Assumptions Rev C'!$B$37 -> 3 | C6: count | G6: David: 'at least three'. Three is the minimum that gives 7-day cover without one person carrying every weekend.
A7: Hours per person per day | B7: ='Assumptions Rev C'!$B$38 -> 2 | C7: hrs | G7: David: '2 hours a day'.
A8: Days per month | B8: ='Assumptions Rev C'!$B$39 -> 30.44 | C8: days | G8: 30.44 = every day. Change to 21.7 on 'Assumptions Rev C' for weekdays only.
A9: Total hours per month | B9: ='Assumptions Rev C'!$B$42 -> 182.64 | C9: hrs | G9: 3 x 2 x days.
A10: Nominal rate | B10: ='Assumptions Rev C'!$B$40 -> 150 | C10: R/hr | G10: THE number to settle. See the grid below.
A11: COST PER MONTH | B11: ='Assumptions Rev C'!$B$43 -> 27396 | C11: ='Assumptions Rev C'!$B$44 -> 1690.0679
A12: COST PER YEAR | B12: =B11*12 -> 328752 | C12: =C11*12 -> 20280.814
A13: Cost per seller per year at Year-1 scale | C13: =IFERROR(C12/'Assumptions Rev C'!$B$9,0) -> 2.6034421 | G13: For comparison: annual revenue per seller in the model is $30.
A14: Starter subscriptions ($5/mo) needed to fund this line alone | C14: =ROUNDUP(C11/5,0) -> 339 | G14: Compare with the whole tech stack, which needs about 70.
A16: B. SENSITIVITY — the rate against the roster
A17: $ per month · rows = rate (R/hr) · columns = days worked per month | B17: 21.7 (weekdays) | C17: 26.0 (6-day roster) | D17: 30.44 (every day)
A18: Rate R/hr \ Days per month | B18: 21.7 | C18: 26 | D18: 30.44
A19: 100 | B19: =($A19*'Assumptions Rev C'!$B$37*'Assumptions Rev C'!$B$38*B$18)/'Assumptions Rev C'!$B$6 -> 803.2079 | C19: =($A19*'Assumptions Rev C'!$B$37*'Assumptions Rev C'!$B$38*C$18)/'Assumptions Rev C'!$B$6 -> 962.36891 | D19: =($A19*'Assumptions Rev C'!$B$37*'Assumptions Rev C'!$B$38*D$18)/'Assumptions Rev C'!$B$6 -> 1126.7119
A20: 150 | B20: =($A20*'Assumptions Rev C'!$B$37*'Assumptions Rev C'!$B$38*B$18)/'Assumptions Rev C'!$B$6 -> 1204.8118 | C20: =($A20*'Assumptions Rev C'!$B$37*'Assumptions Rev C'!$B$38*C$18)/'Assumptions Rev C'!$B$6 -> 1443.5534 | D20: =($A20*'Assumptions Rev C'!$B$37*'Assumptions Rev C'!$B$38*D$18)/'Assumptions Rev C'!$B$6 -> 1690.0679
A21: 200 | B21: =($A21*'Assumptions Rev C'!$B$37*'Assumptions Rev C'!$B$38*B$18)/'Assumptions Rev C'!$B$6 -> 1606.4158 | C21: =($A21*'Assumptions Rev C'!$B$37*'Assumptions Rev C'!$B$38*C$18)/'Assumptions Rev C'!$B$6 -> 1924.7378 | D21: =($A21*'Assumptions Rev C'!$B$37*'Assumptions Rev C'!$B$38*D$18)/'Assumptions Rev C'!$B$6 -> 2253.4238
A22: 250 | B22: =($A22*'Assumptions Rev C'!$B$37*'Assumptions Rev C'!$B$38*B$18)/'Assumptions Rev C'!$B$6 -> 2008.0197 | C22: =($A22*'Assumptions Rev C'!$B$37*'Assumptions Rev C'!$B$38*C$18)/'Assumptions Rev C'!$B$6 -> 2405.9223 | D22: =($A22*'Assumptions Rev C'!$B$37*'Assumptions Rev C'!$B$38*D$18)/'Assumptions Rev C'!$B$6 -> 2816.7798
A23: 350 | B23: =($A23*'Assumptions Rev C'!$B$37*'Assumptions Rev C'!$B$38*B$18)/'Assumptions Rev C'!$B$6 -> 2811.2276 | C23: =($A23*'Assumptions Rev C'!$B$37*'Assumptions Rev C'!$B$38*C$18)/'Assumptions Rev C'!$B$6 -> 3368.2912 | D23: =($A23*'Assumptions Rev C'!$B$37*'Assumptions Rev C'!$B$38*D$18)/'Assumptions Rev C'!$B$6 -> 3943.4917
G24: Highlighted cell = the current assumption.
A26: C. WHAT THIS LINE HAS TO EARN
A27: Three people at two hours a day is 182 hours a month — roughly one full-time person, split three ways for cover. At R150/hr that is about $1,690 a month, which is 5.2 times the entire technology stack and roughly 86% of the restated fixed cost base.
A28: That is not an argument against it. Marketplaces fail on the human side — unanswered sellers, stale listings, introductions that go nowhere — and the whole product thesis here is TRUST, which is a human output. Three people doing seller follow-up is very plausibly the highest-return line in this budget.
A29: It is an argument for being explicit about what they do, because the number is now big enough to deserve a job description. The model can carry it; the question is whether the ramp does. On the modelled Year-1 curve the line is comfortably covered from about month 7. Months 1 to 6 are where it hurts — see 'Year 1 Cash Flow Rev C'.
A30: One structural note worth putting on the table: this cost is denominated in rand and the revenue is denominated in dollars. That is a favourable exposure right now — the rand has strengthened from 18.50 to 16.21 against the dollar since the model was last touched, which makes the people MORE expensive in dollars but the R36 Tuppence worth MORE too. The two do not cancel: revenue is mostly dollar-priced subscriptions, cost is mostly rand. A weakening rand would be good for this business, and that is worth knowing before anyone hedges anything.
A32: D. ACCOUNTANT — from month 1
A33: Line | B33: R/month | C33: $/month | D33: $/year | G33: Note
A34: Accountant fee | B34: ='Assumptions Rev C'!$B$46 -> 2000 | C34: =B34/'Assumptions Rev C'!$B$6 -> 123.38063 | D34: =C34*12 -> 1480.5676 | G34: David's instruction, 18 Aug 2026.
A35: Accounting software | B35: ='Assumptions Rev C'!$B$47 -> 500 | C35: =B35/'Assumptions Rev C'!$B$6 -> 30.845157 | D35: =C35*12 -> 370.14189 | G35: Carried from Rev B. Zero it on 'Assumptions Rev C' if the fee is inclusive.
A36: TOTAL — from month 1 | B36: =SUM(B34:B35) -> 2500 | C36: ='Assumptions Rev C'!$B$49 -> 154.22579 | D36: =C36*12 -> 1850.7094
A37: Rev B treatment, for comparison: $0 in Year 1, R2,000/mo from Year 2 | D37: 0 | G37: The change costs about $1,850 in Year 1 and is worth it — see below.
A39: MOVING THE ACCOUNTANT TO MONTH 1 IS THE CHEAPEST RISK REDUCTION IN THIS WHOLE REVIEW. FINANCE_CANON §4 had already recommended it in July, unprompted: 'engage at FIRST REVENUE, not Year 2 — a Year-1 structuring consult is cheap vs one wrong VAT call.'
A40: The specific exposure: South Africa's compulsory VAT registration threshold is R2.3m of taxable supplies in any twelve months, and zero-rated exports COUNT toward it. On the modelled Year-1 ramp, revenue of about $235,000 is roughly R3.8m — the platform crosses the threshold DURING Year 1, not after it. Registering late carries penalties and interest; getting the Tuppence treatment wrong (it is deferred revenue: a liability on sale, income on settle) would misstate the books from the first month.
A41: There are six questions already written down and waiting for whoever is engaged — VAT timing, whether revenue through a merchant of record is a zero-rated export, the Tuppence deferred-revenue treatment, Small Business Corporation eligibility, director remuneration, and provisional tax estimates on a ramping year. That list is the brief. It is in FINANCE_CANON §4 and it is ready to hand over.

Sheet Year 1 Cash Flow Rev C
A1: YEAR 1 MONTHLY CASH FLOW — Rev C restated cost base · 18 Aug 2026
A2: Revenue and seller counts are read live from the 'Year 1 Monthly' sheet — unchanged, still the audited 16 Jul ramp. Every COST line is Rev C. Ramp: months 1-3 Pretoria only · months 4-6 Wave 1 (4 cities) · month 7+ eight cities a month.
A4: Line | B4: M1 | C4: M2 | D4: M3 | E4: M4 | F4: M5 | G4: M6 | H4: M7 | I4: M8 | J4: M9 | K4: M10 | L4: M11 | M4: M12 | N4: YEAR 1 | O4: Note
A5: ── REVENUE (unchanged — the audited ramp) ─────────────────────
A6: Total revenue | B6: ='Year 1 Monthly'!H5 -> 457 | C6: ='Year 1 Monthly'!H6 -> 500 | D6: ='Year 1 Monthly'!H7 -> 549 | E6: ='Year 1 Monthly'!H8 -> 2417 | F6: ='Year 1 Monthly'!H9 -> 2668 | G6: ='Year 1 Monthly'!H10 -> 2952 | H6: ='Year 1 Monthly'!H11 -> 9818 | I6: ='Year 1 Monthly'!H12 -> 18179 | J6: ='Year 1 Monthly'!H13 -> 28327 | K6: ='Year 1 Monthly'!H14 -> 40608 | L6: ='Year 1 Monthly'!H15 -> 55425 | M6: ='Year 1 Monthly'!H16 -> 73254 | N6: =SUM(B6:M6) -> 235154 | O6: Subscriptions + Tuppence introductions + AI services.
A7: Sellers (cumulative) | B7: ='Year 1 Monthly'!C5 -> 64 | C7: ='Year 1 Monthly'!C6 -> 69 | D7: ='Year 1 Monthly'!C7 -> 74 | E7: ='Year 1 Monthly'!C8 -> 318 | F7: ='Year 1 Monthly'!C9 -> 343 | G7: ='Year 1 Monthly'!C10 -> 370 | H7: ='Year 1 Monthly'!C11 -> 1198 | I7: ='Year 1 Monthly'!C12 -> 2161 | J7: ='Year 1 Monthly'!C13 -> 3277 | K7: ='Year 1 Monthly'!C14 -> 4570 | L7: ='Year 1 Monthly'!C15 -> 6065 | M7: ='Year 1 Monthly'!C16 -> 7790 | N7: =SUM(B7:M7) -> 26299 | O7: For the cost-per-seller check at the foot of this sheet.
A8: ── FIXED COSTS (Rev C) ────────────────────────────────────────
A9: Subscriptions — PAID + COMMITTED | B9: ='Subscriptions Register'!$E$59 -> 331.85 | C9: ='Subscriptions Register'!$E$59 -> 331.85 | D9: ='Subscriptions Register'!$E$59 -> 331.85 | E9: ='Subscriptions Register'!$E$59 -> 331.85 | F9: ='Subscriptions Register'!$E$59 -> 331.85 | G9: ='Subscriptions Register'!$E$59 -> 331.85 | H9: ='Subscriptions Register'!$E$59 -> 331.85 | I9: ='Subscriptions Register'!$E$59 -> 331.85 | ... M9: ='Subscriptions Register'!$E$59 -> 331.85 | N9: =SUM(B9:M9) -> 3982.2 | O9: Claude, Higgsfield, Hetzner, domain, R2, Resend. From 'Subscriptions Register'.
A10: Human operations — 3 people x 2 hrs | B10: =IF(1>='Assumptions Rev C'!$B$41,'Assumptions Rev C'!$B$44,0) -> 1690.0679 | C10: =IF(2>='Assumptions Rev C'!$B$41,'Assumptions Rev C'!$B$44,0) -> 1690.0679 | D10: =IF(3>='Assumptions Rev C'!$B$41,'Assumptions Rev C'!$B$44,0) -> 1690.0679 | E10: =IF(4>='Assumptions Rev C'!$B$41,'Assumptions Rev C'!$B$44,0) -> 1690.0679 | F10: =IF(5>='Assumptions Rev C'!$B$41,'Assumptions Rev C'!$B$44,0) -> 1690.0679 | G10: =IF(6>='Assumptions Rev C'!$B$41,'Assumptions Rev C'!$B$44,0) -> 1690.0679 | H10: =IF(7>='Assumptions Rev C'!$B$41,'Assumptions Rev C'!$B$44,0) -> 1690.0679 | I10: =IF(8>='Assumptions Rev C'!$B$41,'Assumptions Rev C'!$B$44,0) -> 1690.0679 | J10: =IF(9>='Assumptions Rev C'!$B$41,'Assumptions Rev C'!$B$44,0) -> 1690.0679 | K10: =IF(10>='Assumptions Rev C'!$B$41,'Assumptions Rev C'!$B$44,0) -> 1690.0679 | L10: =IF(11>='Assumptions Rev C'!$B$41,'Assumptions Rev C'!$B$44,0) -> 1690.0679 | M10: =IF(12>='Assumptions Rev C'!$B$41,'Assumptions Rev C'!$B$44,0) -> 1690.0679 | N10: =SUM(B10:M10) -> 20280.814 | O10: The largest line in the business. Starts month 1 unless changed.
A11: Accountant + software | B11: =IF(1>='Assumptions Rev C'!$B$48,'Assumptions Rev C'!$B$49,0) -> 154.22579 | C11: =IF(2>='Assumptions Rev C'!$B$48,'Assumptions Rev C'!$B$49,0) -> 154.22579 | D11: =IF(3>='Assumptions Rev C'!$B$48,'Assumptions Rev C'!$B$49,0) -> 154.22579 | E11: =IF(4>='Assumptions Rev C'!$B$48,'Assumptions Rev C'!$B$49,0) -> 154.22579 | F11: =IF(5>='Assumptions Rev C'!$B$48,'Assumptions Rev C'!$B$49,0) -> 154.22579 | G11: =IF(6>='Assumptions Rev C'!$B$48,'Assumptions Rev C'!$B$49,0) -> 154.22579 | H11: =IF(7>='Assumptions Rev C'!$B$48,'Assumptions Rev C'!$B$49,0) -> 154.22579 | I11: =IF(8>='Assumptions Rev C'!$B$48,'Assumptions Rev C'!$B$49,0) -> 154.22579 | J11: =IF(9>='Assumptions Rev C'!$B$48,'Assumptions Rev C'!$B$49,0) -> 154.22579 | K11: =IF(10>='Assumptions Rev C'!$B$48,'Assumptions Rev C'!$B$49,0) -> 154.22579 | L11: =IF(11>='Assumptions Rev C'!$B$48,'Assumptions Rev C'!$B$49,0) -> 154.22579 | M11: =IF(12>='Assumptions Rev C'!$B$48,'Assumptions Rev C'!$B$49,0) -> 154.22579 | N11: =SUM(B11:M11) -> 1850.7094 | O11: R2,500/mo from month 1 (David, 18 Aug 2026).
A12: PostgreSQL hosting | B12: =IF(1>='Assumptions Rev C'!$B$25,'Assumptions Rev C'!$B$26,0) -> 0 | C12: =IF(2>='Assumptions Rev C'!$B$25,'Assumptions Rev C'!$B$26,0) -> 0 | D12: =IF(3>='Assumptions Rev C'!$B$25,'Assumptions Rev C'!$B$26,0) -> 0 | E12: =IF(4>='Assumptions Rev C'!$B$25,'Assumptions Rev C'!$B$26,0) -> 0 | F12: =IF(5>='Assumptions Rev C'!$B$25,'Assumptions Rev C'!$B$26,0) -> 0 | G12: =IF(6>='Assumptions Rev C'!$B$25,'Assumptions Rev C'!$B$26,0) -> 0 | H12: =IF(7>='Assumptions Rev C'!$B$25,'Assumptions Rev C'!$B$26,0) -> 22.23 | I12: =IF(8>='Assumptions Rev C'!$B$25,'Assumptions Rev C'!$B$26,0) -> 22.23 | J12: =IF(9>='Assumptions Rev C'!$B$25,'Assumptions Rev C'!$B$26,0) -> 22.23 | K12: =IF(10>='Assumptions Rev C'!$B$25,'Assumptions Rev C'!$B$26,0) -> 22.23 | L12: =IF(11>='Assumptions Rev C'!$B$25,'Assumptions Rev C'!$B$26,0) -> 22.23 | M12: =IF(12>='Assumptions Rev C'!$B$25,'Assumptions Rev C'!$B$26,0) -> 22.23 | N12: =SUM(B12:M12) -> 133.38 | O12: Budgeted from month 7. NOT a decision to migrate — trigger-driven per the 29 Jul ruling.
A13: ── VARIABLE AND ONE-OFF COSTS ─────────────────────────────────
A14: Payment processing (Paystack effective) | B14: =B6*'Assumptions Rev C'!$B$54 -> 17.407545 | C14: =C6*'Assumptions Rev C'!$B$54 -> 19.045455 | D14: =D6*'Assumptions Rev C'!$B$54 -> 20.911909 | E14: =E6*'Assumptions Rev C'!$B$54 -> 92.065727 | F14: =F6*'Assumptions Rev C'!$B$54 -> 101.62655 | G14: =G6*'Assumptions Rev C'!$B$54 -> 112.44436 | H14: =H6*'Assumptions Rev C'!$B$54 -> 373.97655 | I14: =I6*'Assumptions Rev C'!$B$54 -> 692.45464 | ... M14: =M6*'Assumptions Rev C'!$B$54 -> 2790.3115 | N14: =SUM(B14:M14) -> 8957.2296 | O14: 2.9% + R1 per transaction = 3.81% effective at an R110 average. Tune from live settlements.
A15: AI metered API | B15: =IFERROR('AI Lanes Rev C'!$B$37/'Year 1 Monthly'!$H$17*B6,0) -> 0.48740655 | C15: =IFERROR('AI Lanes Rev C'!$B$37/'Year 1 Monthly'!$H$17*C6,0) -> 0.53326756 | D15: =IFERROR('AI Lanes Rev C'!$B$37/'Year 1 Monthly'!$H$17*D6,0) -> 0.58552778 | E15: =IFERROR('AI Lanes Rev C'!$B$37/'Year 1 Monthly'!$H$17*E6,0) -> 2.5778154 | F15: =IFERROR('AI Lanes Rev C'!$B$37/'Year 1 Monthly'!$H$17*F6,0) -> 2.8455157 | G15: =IFERROR('AI Lanes Rev C'!$B$37/'Year 1 Monthly'!$H$17*G6,0) -> 3.1484117 | H15: =IFERROR('AI Lanes Rev C'!$B$37/'Year 1 Monthly'!$H$17*H6,0) -> 10.471242 | I15: =IFERROR('AI Lanes Rev C'!$B$37/'Year 1 Monthly'!$H$17*I6,0) -> 19.388542 | ... M15: =IFERROR('AI Lanes Rev C'!$B$37/'Year 1 Monthly'!$H$17*M6,0) -> 78.127964 | N15: =SUM(B15:M15) -> 250.8 | O15: Year-1 total from 'AI Lanes Rev C', spread in proportion to revenue.
A16: AI swap-out launch provision (one-off) | B16: =IF(1=1,'Assumptions Rev C'!$B$32,IF('Assumptions Rev C'!$B$33=1,'Assumptions Rev C'!$B$32,0)) -> 280 | C16: =IF(2=1,'Assumptions Rev C'!$B$32,IF('Assumptions Rev C'!$B$33=1,'Assumptions Rev C'!$B$32,0)) -> 0 | D16: =IF(3=1,'Assumptions Rev C'!$B$32,IF('Assumptions Rev C'!$B$33=1,'Assumptions Rev C'!$B$32,0)) -> 0 | E16: =IF(4=1,'Assumptions Rev C'!$B$32,IF('Assumptions Rev C'!$B$33=1,'Assumptions Rev C'!$B$32,0)) -> 0 | F16: =IF(5=1,'Assumptions Rev C'!$B$32,IF('Assumptions Rev C'!$B$33=1,'Assumptions Rev C'!$B$32,0)) -> 0 | G16: =IF(6=1,'Assumptions Rev C'!$B$32,IF('Assumptions Rev C'!$B$33=1,'Assumptions Rev C'!$B$32,0)) -> 0 | H16: =IF(7=1,'Assumptions Rev C'!$B$32,IF('Assumptions Rev C'!$B$33=1,'Assumptions Rev C'!$B$32,0)) -> 0 | I16: =IF(8=1,'Assumptions Rev C'!$B$32,IF('Assumptions Rev C'!$B$33=1,'Assumptions Rev C'!$B$32,0)) -> 0 | J16: =IF(9=1,'Assumptions Rev C'!$B$32,IF('Assumptions Rev C'!$B$33=1,'Assumptions Rev C'!$B$32,0)) -> 0 | K16: =IF(10=1,'Assumptions Rev C'!$B$32,IF('Assumptions Rev C'!$B$33=1,'Assumptions Rev C'!$B$32,0)) -> 0 | L16: =IF(11=1,'Assumptions Rev C'!$B$32,IF('Assumptions Rev C'!$B$33=1,'Assumptions Rev C'!$B$32,0)) -> 0 | M16: =IF(12=1,'Assumptions Rev C'!$B$32,IF('Assumptions Rev C'!$B$33=1,'Assumptions Rev C'!$B$32,0)) -> 0 | N16: =SUM(B16:M16) -> 280 | O16: $40 x 7 models, month 1. Set the recurring flag on 'Assumptions Rev C' to stress-test it monthly.
A17: ── RESULT ─────────────────────────────────────────────────────
A18: TOTAL COSTS | B18: =SUM(B9:B16) -> 2474.0386 | C18: =SUM(C9:C16) -> 2195.7224 | D18: =SUM(D9:D16) -> 2197.6411 | E18: =SUM(E9:E16) -> 2270.7872 | F18: =SUM(F9:F16) -> 2280.6157 | G18: =SUM(G9:G16) -> 2291.7364 | H18: =SUM(H9:H16) -> 2582.8214 | I18: =SUM(I9:I16) -> 2910.2168 | ... M18: =SUM(M9:M16) -> 5066.8131 | N18: =SUM(B18:M18) -> 35735.133
A19: NET CASH FOR THE MONTH | B19: =B6-B18 -> -2017.0386 | C19: =C6-C18 -> -1695.7224 | D19: =D6-D18 -> -1648.6411 | E19: =E6-E18 -> 146.21281 | F19: =F6-F18 -> 387.38429 | G19: =G6-G18 -> 660.26358 | H19: =H6-H18 -> 7235.1786 | I19: =I6-I18 -> 15268.783 | ... M19: =M6-M18 -> 68187.187 | N19: =SUM(B19:M19) -> 199418.87 | O19: Revenue less every cost above. This is the number that matters in months 1-6.
A20: CUMULATIVE CASH POSITION | B20: =B19 -> -2017.0386 | C20: =B20+C19 -> -3712.761 | D20: =C20+D19 -> -5361.402 | E20: =D20+E19 -> -5215.1892 | F20: =E20+F19 -> -4827.8049 | G20: =F20+G19 -> -4167.5414 | H20: =G20+H19 -> 3067.6372 | I20: =H20+I19 -> 18336.42 | J20: =I20+J19 -> 43355.834 | ... M20: =L20+M19 -> 199418.87 | N20: =M20 -> 199418.87 | O20: Running total from a zero start. The trough of this row is the money the business must have in the bank on day one.
A21: Operating margin for the month | B21: =IFERROR(B19/B6,0) -> -4.4136512 | C21: =IFERROR(C19/C6,0) -> -3.3914447 | D21: =IFERROR(D19/D6,0) -> -3.0029892 | E21: =IFERROR(E19/E6,0) -> 0.060493509 | F21: =IFERROR(F19/F6,0) -> 0.14519651 | G21: =IFERROR(G19/G6,0) -> 0.22366652 | H21: =IFERROR(H19/H6,0) -> 0.73692998 | I21: =IFERROR(I19/I6,0) -> 0.83991326 | ... N21: =IFERROR(N19/N6,0) -> 0.84803519
A22: Cost per seller for the month | B22: =IFERROR(B18/B7,0) -> 38.656853 | C22: =IFERROR(C18/C7,0) -> 31.822063 | D22: =IFERROR(D18/D7,0) -> 29.697852 | E22: =IFERROR(E18/E7,0) -> 7.1408402 | F22: =IFERROR(F18/F7,0) -> 6.6490254 | G22: =IFERROR(G18/G7,0) -> 6.1938822 | H22: =IFERROR(H18/H7,0) -> 2.1559444 | I22: =IFERROR(I18/I7,0) -> 1.3466991 | ... M22: =IFERROR(M18/M7,0) -> 0.6504253
A24: ── WHAT THE MONTHLY VIEW SHOWS THAT THE ANNUAL VIEW HIDES ──
A25: The 3-year model reports a Year-1 operating margin in the mid-nineties, and after the Rev C restatement it still reports something respectable. Both are true and both are useless for the decision in front of David, because they are ANNUAL averages of a curve that is deeply negative at the start and steeply positive at the end.
A26: The cost base is now essentially FLAT and front-loaded — people, accountant and subscriptions all start in month 1 at close to full rate — while revenue is a ramp that does not get going until the city waves start in month 7. The trough in the cumulative row is the real capital requirement of this business, and until this sheet existed nobody had computed it.
A27: That trough is the single most useful number this review produces. It is what 'Cash Reserve' turns into a recommendation.
A29: ── HELPER ROWS (used by 'Cash Reserve' and 'Business Case Rev C' — do not delete) ──
A30: Half-ramp net (revenue at 50%, fixed costs unchanged) | B30: =B6*0.5-(B18-B6*'Assumptions Rev C'!$B$54*0.5) -> -2236.8348 | C30: =C6*0.5-(C18-C6*'Assumptions Rev C'!$B$54*0.5) -> -1936.1996 | D30: =D6*0.5-(D18-D6*'Assumptions Rev C'!$B$54*0.5) -> -1912.6851 | E30: =E6*0.5-(E18-E6*'Assumptions Rev C'!$B$54*0.5) -> -1016.2543 | F30: =F6*0.5-(F18-F6*'Assumptions Rev C'!$B$54*0.5) -> -895.80243 | G30: =G6*0.5-(G18-G6*'Assumptions Rev C'!$B$54*0.5) -> -759.51424 | H30: =H6*0.5-(H18-H6*'Assumptions Rev C'!$B$54*0.5) -> 2513.1668 | I30: =I6*0.5-(I18-I6*'Assumptions Rev C'!$B$54*0.5) -> 6525.5105 | ... M30: =M6*0.5-(M18-M6*'Assumptions Rev C'!$B$54*0.5) -> 32955.343 | O30: Only payment fees scale down with revenue; every other cost is fixed.
A31: Half-ramp cumulative cash | B31: =B30 -> -2236.8348 | C31: =B31+C30 -> -4173.0345 | D31: =C31+D30 -> -6085.7196 | E31: =D31+E30 -> -7101.9739 | F31: =E31+F30 -> -7997.7764 | G31: =F31+G30 -> -8757.2906 | H31: =G31+H30 -> -6244.1238 | I31: =H31+I30 -> 281.38674 | J31: =I31+J30 -> 11676.801 | ... M31: =L31+M30 -> 86320.481
A32: Month number if cumulative cash is positive, else 99 | B32: =IF(B20>0,1,99) -> 99 | C32: =IF(C20>0,2,99) -> 99 | D32: =IF(D20>0,3,99) -> 99 | E32: =IF(E20>0,4,99) -> 99 | F32: =IF(F20>0,5,99) -> 99 | G32: =IF(G20>0,6,99) -> 99 | H32: =IF(H20>0,7,99) -> 7 | I32: =IF(I20>0,8,99) -> 8 | J32: =IF(J20>0,9,99) -> 9 | K32: =IF(K20>0,10,99) -> 10 | L32: =IF(L20>0,11,99) -> 11 | M32: =IF(M20>0,12,99) -> 12 | N32: =MIN(B32:M32) -> 7 | O32: MIN of this row = the first month cumulative cash turns positive. 99 = never within Year 1.
A33: Quarter-ramp cumulative cash (revenue at 25%) | B33: =B6*0.25-(B18-B6*'Assumptions Rev C'!$B$54*0.75) -> -2346.7329 | C33: =B33+C6*0.25-(C18-C6*'Assumptions Rev C'!$B$54*0.75) -> -4403.1712 | D33: =C33+D6*0.25-(D18-D6*'Assumptions Rev C'!$B$54*0.75) -> -6447.8784 | E33: =D33+E6*0.25-(E18-E6*'Assumptions Rev C'!$B$54*0.75) -> -8045.3663 | F33: =E33+F6*0.25-(F18-F6*'Assumptions Rev C'!$B$54*0.75) -> -9582.7621 | G33: =F33+G6*0.25-(G18-G6*'Assumptions Rev C'!$B$54*0.75) -> -11052.165 | H33: =G33+H6*0.25-(H18-H6*'Assumptions Rev C'!$B$54*0.75) -> -10900.004 | I33: =H33+I6*0.25-(I18-I6*'Assumptions Rev C'!$B$54*0.75) -> -8746.1301 | J33: =I33+J6*0.25-(J18-J6*'Assumptions Rev C'!$B$54*0.75) -> -4162.7158 | ... M33: =L33+M6*0.25-(M18-M6*'Assumptions Rev C'!$B$54*0.75) -> 29771.289

Sheet Cash Reserve
A1: CASH RESERVE — the backup David asked for · Rev C 18 Aug 2026
A2: A 95% operating margin does not make a business safe. It makes it safe ONCE IT IS RUNNING. What kills marketplaces at this stage is a flat, front-loaded cost base meeting a revenue ramp that has not started — and after Rev C, this cost base is flat and front-loaded. The reserve is the bridge over that gap.
A4: A. MONTHLY FIXED CASH COST — what must be paid whether or not anyone signs up
A5: Line | B5: $/month | C5: $/year | D5: Note
A6: Subscriptions (PAID + COMMITTED) | B6: ='Subscriptions Register'!$E$59 -> 331.85 | C6: =B6*12 -> 3982.2 | D6: Claude, Higgsfield, Hetzner, domain, R2, Resend.
A7: Human operations | B7: ='Assumptions Rev C'!$B$44 -> 1690.0679 | C7: =B7*12 -> 20280.814 | D7: 3 people x 2 hrs/day at the assumed rate.
A8: Accountant + software | B8: ='Assumptions Rev C'!$B$49 -> 154.22579 | C8: =B8*12 -> 1850.7094 | D8: From month 1.
A9: PostgreSQL (from month 7) | B9: ='Assumptions Rev C'!$B$26 -> 22.23 | C9: =B9*12 -> 266.76 | D9: Excluded from the month-1 reserve base; included in the full-stack figure below.
A10: FIXED CASH COST AT LAUNCH (excludes Postgres) | B10: =SUM(B6:B8) -> 2176.1436 | C10: =B10*12 -> 26113.724
A11: Fixed cash cost with Postgres running | B11: =SUM(B6:B9) -> 2198.3736 | C11: =B11*12 -> 26380.484
A12: Of which is TECHNOLOGY | B12: =B6 -> 331.85 | C12: =IFERROR(B12/B10,0) -> 0.15249453 | D12: Share of the fixed base. The whole technology estate of this business.
A13: Of which is PEOPLE | B13: =B7+B8 -> 1844.2936 | C13: =IFERROR(B13/B10,0) -> 0.84750547 | D13: Human operations plus the accountant.
A15: B. THE RESERVE — three ways of sizing it, take the largest
A16: Method | B16: $ | D16: Reasoning
A17: 1. Policy reserve — N months of fixed cost | B17: =B10*'Assumptions Rev C'!$B$56 -> 13056.862 | D17: The conventional runway test. Months set on 'Assumptions Rev C' (currently 6). Answers: 'if nothing at all comes in, how long do we last?'
A18: 2. Modelled trough — deepest cumulative cash deficit | B18: =-MIN(0,MIN('Year 1 Cash Flow Rev C'!$B$20:$M$20)) -> 5361.402 | D18: Read live from 'Year 1 Cash Flow Rev C'. Answers: 'if the plan happens exactly as modelled, what is the most we are ever down?' Zero here would mean the ramp self-funds from month 1.
A19: 3. Half-ramp trough — revenue lands at 50% of plan | B19: =-MIN(0,MIN('Year 1 Cash Flow Rev C'!$B$31:$M$31)) -> 8757.2906 | D19: A crude but honest stress: the ramp is a projection, not a measurement, and marketplace ramps miss. Computed on a helper row in 'Year 1 Cash Flow Rev C' — only payment fees fall with revenue; everything else is fixed.
A20: LARGEST OF THE THREE | B20: =MAX(B17:B19) -> 13056.862 | D20: Quarter-ramp trough (25% of plan) is shown on 'Business Case Rev C' scenarios — deliberately NOT in this MAX, because sizing a reserve for a 75% miss is sizing for a different business.
A21: Stress factor | B21: ='Assumptions Rev C'!$B$57 -> 1.25 | D21: 25% headroom for what a plan does not know. Set to 1.00 on 'Assumptions Rev C' for the bare figure.
A22: RECOMMENDED OPENING CASH RESERVE | B22: =ROUNDUP(B20*B21/100,0)*100 -> 16400 | C22: =B22*'Assumptions Rev C'!$B$6 -> 265844 | D22: Held SEPARATELY from the operating account and not counted as working capital. Rounded up to the nearest $100.
A23: Months of cover it actually buys | B23: =IFERROR(B22/B10,0) -> 7.5362672
A25: C. HOW TO HOLD IT — the practical shape
A26: Separate account, not a mental note. The reserve must be somewhere that requires a deliberate act to spend. The FNB business account already exists; a linked savings or notice account costs nothing and makes the balance visible without making it convenient.
A27: Denominate it in rand. The costs it covers are overwhelmingly rand costs — people and the accountant — so holding the reserve in rand removes the currency mismatch entirely. The dollar-priced subscriptions are the smaller half.
A28: Top it up from settlement, not from profit. The cleanest rule is a fixed percentage of every Paystack settlement batch swept into the reserve until it reaches target, then stopped. That way the reserve builds automatically as revenue arrives and needs no monthly decision.
A29: Rebuild the moment it is drawn on. A reserve used once and not replaced is a reserve that existed once.
A30: Review the size at the first month where cumulative cash turns positive. At that point the trough is behind the business and the reserve can be re-sized to a smaller steady-state number — probably three months rather than six.
A32: D. THE THINGS THIS RESERVE DOES NOT COVER
A33: A Hetzner rescale. The production box is grandfathered at a price that no longer exists; resizing it costs +129% forever. That is not a cash-flow event, it is a permanent step-up, and no reserve fixes it — only a decision does.
A34: A Paystack chargeback run. Paystack reverses fraudulent international transactions from the account balance, and international acceptance is now live. The credit-on-verified-webhook discipline is the control; the reserve is what absorbs the timing.
A35: A VAT registration that arrives late. Crossing R2.3m without having registered is a penalty-and-interest event, not a budget line. The month-1 accountant is the mitigation.
A36: A silent metered bill. The ~$360 Google Places charge is the precedent, and the B7 rule with hard monthly caps is the control that came out of it. Every PLANNED row on the subscription register needs its cap agreed at signup, not after the first invoice.

Sheet AUDIT 16 Jul 2026
A1: FULL WORKBOOK AUDIT — 16 Jul 2026 (Claude Fable) — every change from 'as filed' to current, in one place
A2: Rev A as filed is preserved UNCHANGED as its own file: MarketSquare_Cost_Breakdown_RevA_ARCHIVE_pre-16Jul2026.xlsx. This workbook is the LIVE model.
A4: Sheet | B4: Cell(s) | C4: Was | D4: Now | E4: Why
A5: Assumptions | B5: B36 | C5: 0.025 (2.5% 'blended') | D5: 0.0381 | E5: Live money is Paystack SA: 2.9% + R1 at ~R110 avg transaction = 3.81% effective. Old 2.5% was the Stripe assumption.
A6: Assumptions | B6: C34 | C6: 'Required for Wave 1 Stripe (IoM/Singapore)' | D6: shelved note | E6: David SHELVED the Stripe entity on 16 Jul until income funds it (triggers in BACKLOG). Monthly $100 resumes only at unshelve.
A7: Assumptions | B7: C28 | C7: 'What we pay per $2 of AI revenue' | D7: clarified | E7: 0.004/T stays valid for Tuppence-charged SERVICES (Sonnet). The photo anonymity gate is NOT per-T and NOT user-charged — costed separately (Rev B, Gemini 3 Flash).
A8: Assumptions | B8: B37 vs app | C8: ZAR 18.50 here; app charges R36 = $2 (implies 18.00) | D8: NOTE only | E8: 1T=R36 is a product constant; at R18.50 it's worth $1.95 not $2.00 — a 2.6% FX drag on Tuppence revenue. Finding noted, no change (David's pricing canon).
A9: 3-Year Summary | B9: B16 | C9: Int'l entity Y1 = 1,100 | D9: 0 | E9: Stripe entity shelved 16 Jul — no Y1 spend. Y2/Y3 keep 1,200 assuming unshelve at Year-2 triggers.
A10: 3-Year Summary | B10: B18:D18 | C10: 'Payment processing (2.5%)' 5,879 / 17,279 / 99,882 | E10: Paystack real blended rate, now a FORMULA off Assumptions B36 — changing the assumption reprices every year automatically. Label renamed.
A11: 3-Year Summary | B11: B19:D19 | C11: 'Anthropic API cost' 349 / 1,136 / 7,797 | D11: 'AI API cost' 627 / 1,292 / 8,398 | E11: Old line never contained the photo anonymity gate (built after budget). New = services (Sonnet, as before) + photo gate on Gemini 3 Flash (Rev B). Values from 'AI Costs Rev B' sheet.
A12: 3-Year Summary | B12: B20:D20 | C12: hardcoded totals 8,873 / 23,595 / 113,609 | E12: Total now recomputes from its parts — the class of error you kept finding cannot recur on this row.
A13: 3-Year Summary | B13: B21:D21 | C13: hardcoded NET | E13: formula
A14: 3-Year Summary | B14: B22:D22 | C14: 0.962 / 0.965 / 0.971 | E14: True margins after Paystack + full AI cost. Still exceptional; now honest.
A15: 3-Year Summary | B15: B29:D29 | C15: cost/seller 1 / 5 / 7 (hardcoded) | E15: formula
A16: 3-Year Summary | B16: B30 | C16: 'Free users 1x Standard sub covers' 1757 | D16: NOTE only | E16: 'Standard' is a legacy tier name (retired for new sellers). Figure kept; label is historical.
A17: Year 1 Monthly | B17: J col / A19 | C17: 'Net $' silently excluded payments + AI COGS | D17: note added | E17: The monthly Net overstated by ~4% of revenue. Structure preserved; the exclusion is now stated on the sheet.
A18: AI Cost Ceilings | B18: A5:A6 | C18: 'Sonnet 4.6' | D18: '= Sonnet 5 pricing, Jul 2026' | E18: Model name was stale; the $3/$15 basis is still correct for the current Sonnet 5. Intro pricing noted.
A19: AI Cost Ceilings | B19: J:K | C19: (added earlier today) | D19: Gemini worst-case / COGS columns | E19: Worst function COGS 6.8% (Sonnet) vs ~1.1% (Gemini 3 Flash) — functions stay Sonnet-routed until the frozen-eval test passes.
A20: AI Revenue Analysis | B20: A21 | C20: photo gate absent from margins, unstated | D20: scope note added | E20: Prevents the same silent-cost confusion recurring on this sheet.
A22: HEADLINE AFTER AUDIT — Year 1: costs $11,131 · net $224,023 · margin 95.27% | Year 2: 95.25% | Year 3: 95.83%
A23: Guards: MODEL-COST-GUARD-1 (daily $/photo drift check) · payment line now formula-driven off Assumptions!B36 · totals/net/margin are formulas, not hardcodes.

Sheet 3-Year Summary
A1: MarketSquare — Revised 3-Year Financial Model (Session 90) · AUDITED 16 Jul 2026 — Rev B: Paystack real rates + AI on Gemini plan + Stripe shelved
A2: New tier prices · AI as profit centre · Realistic city ramp
A4: Metric | B4: Year 1 | C4: Year 2 | D4: Year 3
A5: ── SCALE ──────────────────────────
A6: Live cities (end of year) | B6: 52 | C6: 52 | D6: 148
A7: Total sellers | B7: 7790 | C7: 4368 | D7: 16872
A8: Total buyers | B8: 38952 | C8: 24024 | D8: 118104
A9: ── REVENUE ────────────────────────
A10: Subscription revenue | B10: 158968 | C10: 478348 | D10: 2645192
A11: Introduction (Tuppence) revenue | B11: 42228 | C11: 102313 | D11: 592799
A12: AI services revenue | B12: 33958 | C12: 110512 | D12: 757303
A13: TOTAL REVENUE | B13: 235154 | C13: 691173 | D13: 3995294
A14: ── COSTS ──────────────────────────
A15: Infrastructure & operations | B15: 1545 | C15: 2358 | D15: 3108
A16: International entity (Stripe — SHELVED, resumes Y2) | B16: 0 | C16: 1200 | D16: 1200
A17: Accountant (from Year 2) | B17: 0 | C17: 1622 | D17: 1622
A18: Payment processing (Paystack blended — Assumptions!B36) | B18: =B13*Assumptions!$B$36 -> 8959.3674 | C18: =C13*Assumptions!$B$36 -> 26333.691 | D18: =D13*Assumptions!$B$36 -> 152220.7
A19: AI API cost (services Sonnet + photo gate Gemini — Rev B) | B19: 627 | C19: 1292 | D19: 8398
A20: TOTAL COSTS | B20: =SUM(B15:B19) -> 11131.367 | C20: =SUM(C15:C19) -> 32805.691 | D20: =SUM(D15:D19) -> 166548.7
A21: NET INCOME | B21: =B13-B20 -> 224022.63 | C21: =C13-C20 -> 658367.31 | D21: =D13-D20 -> 3828745.3
A22: Operating margin | B22: =B21/B13 -> 0.9526635 | C22: =C21/C13 -> 0.95253621 | D22: =D21/D13 -> 0.95831378
A23: ── REVENUE MIX ─────────────────────
A24: Subscriptions % | B24: 0.676 | C24: 0.692 | D24: 0.662
A25: Introductions % | B25: 0.18 | C25: 0.148 | D25: 0.148
A26: AI services % | B26: 0.144 | C26: 0.16 | D26: 0.19
A27: ── UNIT ECONOMICS ─────────────────
A28: Annual revenue per seller | B28: 30 | C28: 158 | D28: 237
A29: Annual cost per seller | B29: =B20/B7 -> 1.4289303 | C29: =C20/C7 -> 7.5104605 | D29: =D20/D7 -> 9.8713076
A30: Free users 1x Standard sub covers | B30: 1757 | C30: 1757 | D30: 1757
A32: ⚠ SUPERSEDED 18 Aug 2026 — this sheet is HISTORY. The live business case is 'Business Case Rev C'.
A33: It remains correct as filed on 16 Jul 2026 and is kept so the audit trail is unbroken. What changed: human operations and a month-1 accountant were added; the AI line was restated onto the OpenAI base lane; Hetzner moved to the actual bill; PostgreSQL, the swap-out provision and thirty-five previously unmodelled third-party dependencies were brought on-budget; and the ZAR/USD rate moved from 18.50 to 16.21. Every change is itemised on 'REVIEW 18 Aug 2026'.

Sheet Year 1 Monthly
A1: Year 1 Monthly Revenue — City Launch Ramp
A2: Mo 1-3: Pretoria only · Mo 4-6: Wave 1 (4 cities) · Mo 7+: +8 cities/month
A4: Mo | B4: Cities | C4: Sellers | D4: Buyers | E4: Subs $ | F4: Intros $ | G4: AI net $ | H4: Total $ | I4: Infra $ | J4: Net $ | K4: Sub% | L4: Int% | M4: AI%
A5: 1 | B5: 1 | C5: 64 | D5: 144 | E5: 388 | F5: 30 | G5: 39 | H5: 457 | I5: 37 | J5: 420 | K5: 0.85 | L5: 0.07 | M5: 0.08
A6: 2 | B6: 1 | C6: 69 | D6: 172 | E6: 416 | F6: 38 | G6: 46 | H6: 500 | I6: 37 | J6: 463 | K6: 0.83 | L6: 0.08 | M6: 0.09
A7: 3 | B7: 1 | C7: 74 | D7: 203 | E7: 447 | F7: 48 | G7: 54 | H7: 549 | I7: 37 | J7: 512 | K7: 0.81 | L7: 0.09 | M7: 0.1
A8: 4 | B8: 4 | C8: 318 | D8: 954 | E8: 1922 | F8: 242 | G8: 254 | H8: 2417 | I8: 140 | J8: 2277 | K8: 0.8 | L8: 0.1 | M8: 0.1
A9: 5 | B9: 4 | C9: 343 | D9: 1113 | E9: 2071 | F9: 300 | G9: 298 | H9: 2668 | I9: 140 | J9: 2528 | K9: 0.78 | L9: 0.11 | M9: 0.11
A10: 6 | B10: 4 | C10: 370 | D10: 1294 | E10: 2234 | F10: 369 | G10: 349 | H10: 2952 | I10: 140 | J10: 2812 | K10: 0.76 | L10: 0.12 | M10: 0.12
A11: 7 | B11: 12 | C11: 1198 | D11: 4493 | E11: 7243 | F11: 1353 | G11: 1223 | H11: 9818 | I11: 148 | J11: 9670 | K11: 0.74 | L11: 0.14 | M11: 0.12
A12: 8 | B12: 20 | C12: 2161 | D12: 8642 | E12: 13061 | F12: 2739 | G12: 2380 | H12: 18179 | I12: 156 | J12: 18023 | K12: 0.72 | L12: 0.15 | M12: 0.13
A13: 9 | B13: 28 | C13: 3277 | D13: 13927 | E13: 19809 | F13: 4634 | G13: 3884 | H13: 28327 | I13: 164 | J13: 28163 | K13: 0.7 | L13: 0.16 | M13: 0.14
A14: 10 | B14: 36 | C14: 4570 | D14: 20564 | E14: 27624 | F14: 7168 | G14: 5816 | H14: 40608 | I14: 172 | J14: 40436 | K14: 0.68 | L14: 0.18 | M14: 0.14
A15: 11 | B15: 44 | C15: 6065 | D15: 28807 | E15: 36660 | F15: 10497 | G15: 8267 | H15: 55425 | I15: 180 | J15: 55245 | K15: 0.66 | L15: 0.19 | M15: 0.15
A16: 12 | B16: 52 | C16: 7790 | D16: 38952 | E16: 47093 | F16: 14811 | G16: 11350 | H16: 73254 | I16: 188 | J16: 73066 | K16: 0.64 | L16: 0.2 | M16: 0.15
A17: YEAR 1 TOTAL | E17: 158968 | F17: 42228 | G17: 33958 | H17: 235154 | I17: 1545 | J17: 233609 | K17: 0.68 | L17: 0.18 | M17: 0.14
A19: AUDIT NOTE (16 Jul 2026): 'Net $' here = revenue − infrastructure ONLY. Payment processing (~3.8% of revenue) and AI COGS are excluded from this monthly view — see the audited 3-Year Summary for true net.

Sheet AI Revenue Analysis
A1: AI Services — 97% Margin Profit Centre
A2: Sellers pay 1T=$2 per call. We pay $0.002-$0.04 to Anthropic. Net margin ~97%.
A4: Scenario | B4: Seller adopt% | C4: Buyer adopt% | D4: Gross rev/mo | E4: API cost/mo | F4: Net margin
A5: Launch: Pretoria, 60 sellers | B5: 0.08 | C5: 0.02 | D5: 67 | E5: 0.24 | F5: 0.99641791
A6: Wave 1: 4 cities, 240 sellers | B6: 0.1 | C6: 0.03 | D6: 295 | E6: 1.06 | F6: 0.99640678
A7: Year 1 end: 52 cities, 7,790 sellers | B7: 0.14 | C7: 0.05 | D7: 8200 | E7: 29.5 | F7: 0.99640244
A8: Year 2: 52 cities, 20% seller adoption | B8: 0.2 | C8: 0.07 | D8: 11400 | E8: 41 | F8: 0.99640351
A9: Year 3: 148 cities, 35% seller adoption | B9: 0.35 | C9: 0.1 | D9: 63000 | E9: 226.8 | F9: 0.9964
A10: Upside: 60% seller adoption (collector-heavy) | B10: 0.6 | C10: 0.15 | D10: 108000 | E10: 388.8 | F10: 0.9964
A12: WHY AI ADOPTION IS STRUCTURALLY HIGH FOR THIS MARKETPLACE
A13: • Collectors: AI price-check (1T=$2) before every intro is rational — item values vary 10-100x. ROI positive from first use.
A14: • Estate agents: rewrite (1T) + yield-calc (1T) per listing = 2T. At 5 new listings/month = $20 AI spend vs $12 sub. Additive, not competitive.
A15: • Property investors: yield calculator run 3-5x per property at different price assumptions. Repeat rational use, not habit.
A16: • Buyers: 1T price-check before committing 1T to an intro = insurance. Self-reinforcing — buyers who check convert better.
A17: • The 'addiction' dynamic is repeated rational economic decisions with positive expected value. Not gamification.
A18: • At 40% seller adoption: AI revenue approaches intro revenue. At 60%: AI becomes the single largest revenue stream.
A19: NOTE (16 Jun): per-call cost above is the 1T guidance case. Advanced functions are capped per 'AI Cost Ceilings' sheet (worst COGS 7.5%); headline margins unchanged.
A21: AUDIT NOTE (16 Jul 2026): margins on this sheet are for Tuppence-CHARGED services and remain valid (services stay Sonnet-routed pending eval). The photo anonymity gate is free to users and is NOT in these margins — it is costed in 'AI Costs Rev B'.

Sheet Assumptions
A1: Model Assumptions — Update blue cells as actuals come in
A2: Blue = hardcoded input. Update monthly_income_usd in BEA after first subscriptions arrive.
A4: SUBSCRIPTION TIERS (Simpler Model — adopted 9-10 Jun 2026)
A5: Free price/month (USD) | B5: 0 | C5: 2 listing slots
A6: Starter price/month (USD) | B6: 5 | C6: 10 slots (R90)
A7: Pro price/month (USD) | B7: 20 | C7: 30 slots (R360)
A8: Agency price/month (USD) | B8: 0 | C8: Free + verified · trust-graduated slot cap
A9: TIER DISTRIBUTION (launch — estimate, update as actuals come in)
A10: % Free | B10: 0.65 | C10: Decreases as platform proves value
A11: % Starter | B11: 0.25
A12: % Pro | B12: 0.08
A13: % Agency | B13: 0.02
A14: Legacy tiers (Standard/Professional/Business/Elite) | C14: Retained for existing users only — not offered to new sellers; see bea_main _SELLER_SUB_TIERS
A15: INTRODUCTIONS
A16: Tuppence value (USD) | B16: 2 | C16: Fixed — 1T = $2
A17: Intros per buyer/month (cold) | B17: 0.15 | C17: Ramps to 0.30 by month 12
A18: Intros per buyer/month (mature) | B18: 0.35 | C18: Year 2+ steady state
A19: Intro acceptance rate | B19: 0.65 | C19: Trust Score drives this up
A20: Buyers per seller (launch) | B20: 2.5 | C20: Conservative — platform unknown
A21: Buyers per seller (mature) | B21: 6 | C21: Year 3 target
A22: AI SERVICES
A23: Seller AI adoption % (launch) | B23: 0.08 | C23: 8% use AI monthly at start
A24: Seller AI adoption % (mature) | B24: 0.35 | C24: Collectors/agents drive this up
A25: Avg Tuppence/seller/month on AI | B25: 3 | C25: Mix of rewrite, audit, yield calc
A26: Buyer AI adoption % (launch) | B26: 0.02 | C26: Price-check before intro
A27: Buyer AI adoption % (mature) | B27: 0.1 | C27: Grows as buyers learn feature
A28: Anthropic blended cost per T | B28: 0.004 | C28: Services only (Sonnet). Photo anonymity gate costed separately — see 'AI Costs Rev B' (Gemini 3 Flash)
A29: INFRASTRUCTURE (monthly USD)
A30: Hetzner CPX32 | B30: 15.49 | C30: Actual — Session 88 upgrade
A31: Cloudflare R2 per city | B31: 1 | C31: Scales linearly with city count
A32: Claude Pro | B32: 20 | C32: Sole dev tool
A33: Domain | B33: 1 | C33: ~$12/yr amortised
A34: International entity | B34: 100 | C34: SHELVED 16 Jul 2026 (David) — resumes only when STRIPE-GLOBAL-1 unshelves (triggers in BACKLOG)
A35: Accountant (from Year 2) | B35: 135.14 | C35: R2,000/mo + R500 software @ R18.5
A36: Payment processing blended | B36: 0.0381 | C36: Paystack SA 2.9%+R1 @ ~R110 avg tx = 3.81% · Stripe intl only when STRIPE-GLOBAL-1 unshelves
A37: ZAR/USD rate | B37: 18.5 | C37: Update periodically
A38: SPEND ALERT CONFIG (BEA)
A39: monthly_income_usd (set in BEA) | B39: 0 | C39: ⚠ Update via PUT /admin/ai-spend/config after first revenue
A40: alert_threshold_pct | B40: 20 | C40: Alert fires when AI spend > this % of income

Sheet AI Cost Ceilings
A1: AI Function Cost Ceilings — bounded by construction
A2: Each function is hard-capped (max input/output tokens, max searches) so its worst-case cost is a known constant. See canon: AI_FUNCTION_COST_CEILINGS.md
A4: COST BASIS (editable)
A5: Sonnet input ($/Mtok) — '4.6' label historical; = Sonnet 5 pricing, Jul 2026 | B5: 3
A6: Sonnet output ($/Mtok) — = Sonnet 5, Jul 2026 (intro $2/$10 to 31 Aug) | B6: 15
A7: Haiku 4.5 input ($/Mtok) | B7: 1
A8: Haiku 4.5 output ($/Mtok) | B8: 5
A9: Web search ($/search) | B9: 0.01
A10: Gemini 3 Flash input ($/Mtok) — Rev B (vs Sonnet input $3.00 = 6x cheaper) | B10: 0.5
A11: Gemini 3 Flash output ($/Mtok) — Rev B (vs Sonnet output $15.00 = 5x cheaper) | B11: 3
A12: Function | B12: Price T | C12: Price $ | D12: Model | E12: Max in | F12: Max out | G12: Searches | H12: Worst-case $ | I12: Max COGS | J12: Gemini worst-case $ | K12: Gemini COGS
A13: introduction | B13: 1 | C13: =B13*Assumptions!$B$16 -> 2 | D13: — | E13: 0 | F13: 0 | G13: 0 | H13: 0 | I13: =IF(C13=0,0,H13/C13) -> 0 | J13: 0 | K13: =IF(C13=0,0,J13/C13) -> 0
A14: fair_price / yield (guidance) | B14: 1 | C14: =B14*Assumptions!$B$16 -> 2 | D14: Haiku | E14: 8000 | F14: 1000 | G14: 0 | H14: =E14/1000000*$B$7+F14/1000000*$B$8+G14*$B$9 -> 0.013 | I14: =IF(C14=0,0,H14/C14) -> 0.0065 | J14: =E14/1000000*$B$10+F14/1000000*$B$11+G14*$B$9 -> 0.007 | K14: =IF(C14=0,0,J14/C14) -> 0.0035
A15: offer_advisor | B15: 2 | C15: =B15*Assumptions!$B$16 -> 4 | D15: Sonnet | E15: 40000 | F15: 3000 | G15: 2 | H15: =E15/1000000*$B$5+F15/1000000*$B$6+G15*$B$9 -> 0.185 | I15: =IF(C15=0,0,H15/C15) -> 0.04625 | J15: =E15/1000000*$B$10+F15/1000000*$B$11+G15*$B$9 -> 0.049 | K15: =IF(C15=0,0,J15/C15) -> 0.01225
A16: study_plan | B16: 3 | C16: =B16*Assumptions!$B$16 -> 6 | D16: Sonnet | E16: 80000 | F16: 5000 | G16: 3 | H16: =E16/1000000*$B$5+F16/1000000*$B$6+G16*$B$9 -> 0.345 | I16: =IF(C16=0,0,H16/C16) -> 0.0575 | J16: =E16/1000000*$B$10+F16/1000000*$B$11+G16*$B$9 -> 0.085 | K16: =IF(C16=0,0,J16/C16) -> 0.014166667
A17: weekend_itinerary | B17: 3 | C17: =B17*Assumptions!$B$16 -> 6 | D17: Sonnet | E17: 100000 | F17: 4000 | G17: 5 | H17: =E17/1000000*$B$5+F17/1000000*$B$6+G17*$B$9 -> 0.41 | I17: =IF(C17=0,0,H17/C17) -> 0.068333333 | J17: =E17/1000000*$B$10+F17/1000000*$B$11+G17*$B$9 -> 0.112 | K17: =IF(C17=0,0,J17/C17) -> 0.018666667
A18: collectables_advert | B18: 5 | C18: =B18*Assumptions!$B$16 -> 10 | D18: Sonnet | E18: 90000 | F18: 4000 | G18: 6 | H18: =E18/1000000*$B$5+F18/1000000*$B$6+G18*$B$9 -> 0.39 | I18: =IF(C18=0,0,H18/C18) -> 0.039 | J18: =E18/1000000*$B$10+F18/1000000*$B$11+G18*$B$9 -> 0.117 | K18: =IF(C18=0,0,J18/C18) -> 0.0117
A19: car_dossier | B19: 5 | C19: =B19*Assumptions!$B$16 -> 10 | D19: Sonnet | E19: 120000 | F19: 5000 | G19: 6 | H19: =E19/1000000*$B$5+F19/1000000*$B$6+G19*$B$9 -> 0.495 | I19: =IF(C19=0,0,H19/C19) -> 0.0495 | J19: =E19/1000000*$B$10+F19/1000000*$B$11+G19*$B$9 -> 0.135 | K19: =IF(C19=0,0,J19/C19) -> 0.0135
A20: property_dossier | B20: 5 | C20: =B20*Assumptions!$B$16 -> 10 | D20: Sonnet | E20: 130000 | F20: 5000 | G20: 7 | H20: =E20/1000000*$B$5+F20/1000000*$B$6+G20*$B$9 -> 0.535 | I20: =IF(C20=0,0,H20/C20) -> 0.0535 | J20: =E20/1000000*$B$10+F20/1000000*$B$11+G20*$B$9 -> 0.15 | K20: =IF(C20=0,0,J20/C20) -> 0.015
A21: heritage_tour | B21: 5 | C21: =B21*Assumptions!$B$16 -> 10 | D21: Sonnet | E21: 170000 | F21: 5000 | G21: 8 | H21: =E21/1000000*$B$5+F21/1000000*$B$6+G21*$B$9 -> 0.665 | I21: =IF(C21=0,0,H21/C21) -> 0.0665 | J21: =E21/1000000*$B$10+F21/1000000*$B$11+G21*$B$9 -> 0.18 | K21: =IF(C21=0,0,J21/C21) -> 0.018
A22: collection_liquidation | B22: 8 | C22: =B22*Assumptions!$B$16 -> 16 | D22: Sonnet | E22: 150000 | F22: 6000 | G22: 8 | H22: =E22/1000000*$B$5+F22/1000000*$B$6+G22*$B$9 -> 0.62 | I22: =IF(C22=0,0,H22/C22) -> 0.03875 | J22: =E22/1000000*$B$10+F22/1000000*$B$11+G22*$B$9 -> 0.173 | K22: =IF(C22=0,0,J22/C22) -> 0.0108125
A23: expedition_dossier | B23: 10 | C23: =B23*Assumptions!$B$16 -> 20 | D23: Sonnet | E23: 200000 | F23: 8000 | G23: 10 | H23: =E23/1000000*$B$5+F23/1000000*$B$6+G23*$B$9 -> 0.82 | I23: =IF(C23=0,0,H23/C23) -> 0.041 | J23: =E23/1000000*$B$10+F23/1000000*$B$11+G23*$B$9 -> 0.224 | K23: =IF(C23=0,0,J23/C23) -> 0.0112
A25: Worst COGS across all functions | I25: =MAX(I13:I23) -> 0.068333333 | J25: =MAX(K13:K23) -> 0.018666667
A26: Target ceiling | I26: 0.1
A27: Rule: price_$ ≥ worst_case_$ ÷ (1 − target). Re-check before promoting a stub or wiring any paid feed.
A28: Rev B note (16 Jul 2026): advanced functions REMAIN Sonnet-routed until the frozen-eval test passes — columns J-K show the ceiling headroom IF switched to Gemini 3 Flash (worst COGS drops ~6x). The PHOTO pipeline is re-costed on Gemini in 'AI Costs Rev B'.

Sheet AI Costs Rev B (16 Jul 2026)
A1: AI COSTS — REVISION B: photo pipeline on Gemini 3 Flash (16 Jul 2026). Original sheets untouched (Rev A stands as filed).
A2: Swap-out principle preserved: ai_provider.py seam routes the photo task by config — this revision changes ROUTING, not architecture. Swap back to Claude, or to OpenAI/GLM, at any time (price triples / access banned / quality drops).
A5: Assumptions (blue = edit)
A6: Listings per seller | B6: 1.5 | C6: planning assumption | D6: Svc API $ Y1/Y2/Y3: | E6: 349 | F6: 1136 | G6: 7797
A7: Avg photos stored per listing (24-cap x 70%) | B7: 16.8 | C7: PHOTO-CAP-1
A8: $ / photo — Claude Sonnet 5 (Rev A reality) | B8: 0.01389 | C8: AI_PHOTO_COST_MODEL.xlsx, mixed 30% redaction
A9: $ / photo — Gemini 3 Flash (Rev B) | B9: 0.001414 | C9: same pipeline; ~560 img tokens; $0.50/$3.00 per M — VERIFY at ai.google.dev before switch
A10: Sellers Year 1 | B10: 7790 | C10: from '3-Year Summary' as filed
A11: Sellers Year 2 | B11: 4368 | C11: as filed
A12: Sellers Year 3 | B12: 16872 | C12: as filed
A13: Other AI services API cost (Rev A line, unchanged) | C13: stays as filed: 349 / 1,136 / 7,797 — Tuppence-funded, 97% margin
A16: THEN vs NOW — total AI API cost per year ($)
A17: Line | B17: Year 1 | C17: Year 2 | D17: Year 3 | E17: Note
A18: Photos per year (sellers x listings x photos) | B18: =$B$10*$B$6*$B$7 -> 196308 | C18: =$B$11*$B$6*$B$7 -> 110073.6 | D18: =$B$12*$B$6*$B$7 -> 425174.4 | E18: volume driver
A19: REV A as FILED — AI line in the old budget | B19: =$E$6 -> 349 | C19: =$F$6 -> 1136 | D19: =$G$6 -> 7797 | E19: the $349 line NEVER included the photo anonymity gate (built 11 Jul, after the budget)
A20: REV A REALITY — old budget + photo gate on Sonnet | B20: =$E$6+B18*$B$8 -> 3075.7181 | C20: =$F$6+C18*$B$8 -> 2664.9223 | D20: =$G$6+D18*$B$8 -> 13702.672 | E20: the silent killer David caught: unbudgeted
A21: REV B — old services + photo gate on GEMINI 3 FLASH | B21: =$E$6+B18*$B$9 -> 626.57951 | C21: =$F$6+C18*$B$9 -> 1291.6441 | D21: =$G$6+D18*$B$9 -> 8398.1966 | E21: the new plan
A22: Saving: Rev B vs Sonnet reality | B22: =B20-B21 -> 2449.1386 | C22: =C20-C21 -> 1373.2782 | D22: =D20-D21 -> 5304.4758
A23: Overrun avoided vs budget as filed | B23: =B20-B19 -> 2726.7181 | C23: =C20-C19 -> 1528.9223 | D23: =D20-D19 -> 5905.6724 | E23: what would have silently hit us
A24: Rev B overshoot vs budget as filed | B24: =B21-B19 -> 277.57951 | C24: =C21-C19 -> 155.64407 | D24: =D21-D19 -> 601.1966 | E24: small, now VISIBLE and budgeted
A26: Operating margin impact (Year 1, revenue $235,154 · other costs $8,524 as filed)
A27: Margin — Rev A as filed | B27: =(235154-8524-B19)/235154 -> 0.96226728
A28: Margin — Sonnet reality | B28: =(235154-8524-B20)/235154 -> 0.95067182
A29: Margin — Rev B (Gemini 3 Flash) | B29: =(235154-8524-B21)/235154 -> 0.96108686
A31: Gate: MODEL-COST-GUARD-1 — daily loop compares actual $/photo to $B$9; >20% drift = amber in the morning brief.
A32: PAYMENTS — REV B: the model charged 2.5% (Stripe); live money runs on PAYSTACK (ZA): 2.9% + R1/transaction
A33: Paystack % fee | B33: 0.029 | C33: paystack.com/pricing — verify; some sources say +R1.50
A34: Paystack fixed fee (R) | B34: 1 | C34: waived under R10
A35: ZAR per USD | B35: 18 | C35: model constant
A36: Blended avg transaction size (R) | B36: 110 | C36: mix of R36 single-T, R72-180 small packs, R90/R360 subs — tune from live Paystack data
A37: Effective blended rate = % + fixed/avg-tx | B37: =B33+B34/B36 -> 0.038090909
A39: Effective rate by transaction size:
A40: 1T top-up (R36) | B40: =$B$33+$B$34/36 -> 0.056777778
A41: 2T (R72) | B41: =$B$33+$B$34/72 -> 0.042888889
A42: 5T (R180) | B42: =$B$33+$B$34/180 -> 0.034555556
A43: Starter sub (R90) | B43: =$B$33+$B$34/90 -> 0.040111111
A44: Pro sub (R360) | B44: =$B$33+$B$34/360 -> 0.031777778
A46: Payments line | B46: Year 1 | C46: Year 2 | D46: Year 3 | E46: Note
A47: As FILED — 2.5% (Stripe assumption) | B47: =235154*0.025 -> 5878.85 | C47: =691173*0.025 -> 17279.325 | D47: =3995294*0.025 -> 99882.35 | E47: the old model line
A48: REV B — Paystack effective blended rate | B48: =235154*$B$37 -> 8957.2296 | C48: =691173*$B$37 -> 26327.408 | D48: =3995294*$B$37 -> 152184.38 | E48: Y2/Y3 international share would move to Stripe when STRIPE-GLOBAL-1 unshelves
A49: Increase vs filed | B49: =B48-B47 -> 3078.3796 | C49: =C48-C47 -> 9048.0829 | D49: =D48-D47 -> 52302.031
A51: Year-1 margin, all Rev B lines together (AI on Gemini + Paystack real)
A52: Margin — fully restated | B52: =(235154-(8873-349-5879)-B21-B48)/235154 -> 0.94799659 | C52: replaces old AI line and old payments line with Rev B values
