Workbook

Sheet Drivers
A1: TrustSquare global launch — budget drivers
A2: Change the blue cells. Everything on Budget & Scenarios recalculates.
A4: Driver | B4: Value | C4: Note
A5: Number of regions (pods) | B5: 4 | C5: continent-level at launch (Africa, N.America, Europe, Oceania)
A6: Per-region — app server ($/mo) | B6: 45 | C6: CPX31-class, POST-15-Jun-2026 price; existing box may be grandfathered ~$17
A7: Per-region — storage: volume + backups ($/mo) | B7: 12 | C7: Hetzner Volume ~$6 + object-storage backups ~$6
A8: Central — ledger/identity server ($/mo) | B8: 45 | C8: the one authoritative money+identity box (can co-locate at launch)
A9: Central — managed Postgres ($/mo) | B9: 25 | C9: managed for the money DB; $0 if self-hosted on the central box
A10: Central — storage/backups ($/mo) | B10: 12 | C10: volume + backups for the central ledger
A11: Cloudflare ($/mo) | B11: 25 | C11: Pro per domain; Business = 200 for PCI/custom-WAF later
A12: Email / Resend ($/mo) | B12: 20 | C12: free under 3k emails/mo; small paid buffer
A13: Domain ($/mo) | B13: 1.25 | C13: ~$15/yr amortised
A14: AI / Claude Pro ($/mo) | B14: 20 | C14: per-use API cost is revenue-linked, tracked separately
A15: Payment fee (%) | B15: 0.029 | C15: blended Paystack/Stripe ~2.9%; revenue-linked, not fixed
A16: Monthly payment volume ($) | B16: 0 | C16: set as revenue arrives — drives the fee line

Sheet Budget
A1: Monthly & annual budget (auto-calculated)
A2: Green = pulled from Drivers. Black = calculated. Change values on the Drivers sheet.
A4: Line | B4: Monthly $ | C4: Annual $
A5: Regional pods (all regions) | B5: =Drivers!$B$5*(Drivers!$B$6+Drivers!$B$7) -> 228 | C5: =B5*12 -> 2736
A6: Central ledger + identity | B6: =Drivers!$B$8+Drivers!$B$9+Drivers!$B$10 -> 82 | C6: =B6*12 -> 984
A7: Global tools (Cloudflare, email, domain, AI) | B7: =Drivers!$B$11+Drivers!$B$12+Drivers!$B$13+Drivers!$B$14 -> 66.25 | C7: =B7*12 -> 795
A8: TOTAL FIXED (infra + tools) | B8: =SUM(B5:B7) -> 376.25 | C8: =B8*12 -> 4515
A10: Payment fees (revenue-linked) | B10: =Drivers!$B$16*Drivers!$B$15 -> 0 | C10: =B10*12 -> 0
A11: GRAND TOTAL (incl. payment fees) | B11: =B8+B10 -> 376.25 | C11: =B11*12 -> 4515
A13: Per-region cost (each pod) = | B13: =Drivers!$B$6+Drivers!$B$7 -> 57

Sheet Scenarios
A1: Scenarios — cost by number of regions
A2: Holds per-unit costs from Drivers; only the region count changes.
A4: Regions | B4: Monthly fixed $ | C4: Annual fixed $
A5: 1 | B5: =(Drivers!$B$8+Drivers!$B$9+Drivers!$B$10)+(Drivers!$B$11+Drivers!$B$12+Drivers!$B$13+Drivers!$B$14)+1*(Drivers!$B$6+Drivers!$B$7) -> 205.25 | C5: =B5*12 -> 2463
A6: 4 | B6: =(Drivers!$B$8+Drivers!$B$9+Drivers!$B$10)+(Drivers!$B$11+Drivers!$B$12+Drivers!$B$13+Drivers!$B$14)+4*(Drivers!$B$6+Drivers!$B$7) -> 376.25 | C6: =B6*12 -> 4515
A7: 6 | B7: =(Drivers!$B$8+Drivers!$B$9+Drivers!$B$10)+(Drivers!$B$11+Drivers!$B$12+Drivers!$B$13+Drivers!$B$14)+6*(Drivers!$B$6+Drivers!$B$7) -> 490.25 | C7: =B7*12 -> 5883
A8: 8 | B8: =(Drivers!$B$8+Drivers!$B$9+Drivers!$B$10)+(Drivers!$B$11+Drivers!$B$12+Drivers!$B$13+Drivers!$B$14)+8*(Drivers!$B$6+Drivers!$B$7) -> 604.25 | C8: =B8*12 -> 7251
A9: 12 | B9: =(Drivers!$B$8+Drivers!$B$9+Drivers!$B$10)+(Drivers!$B$11+Drivers!$B$12+Drivers!$B$13+Drivers!$B$14)+12*(Drivers!$B$6+Drivers!$B$7) -> 832.25 | C9: =B9*12 -> 9987
A11: (payment fees scale separately with revenue, ~2.9%)

Sheet Server options
A1: Server / host options by region (reference)
A2: Prices indicative, post-15-Jun-2026 Hetzner increase; confirm exact on order. Sources in the Word plan.
A4: Region | B4: Recommended host | C4: Datacentre | D4: ~Server $/mo | E4: Residency fit | F4: Notes
A5: Europe | B5: Hetzner Cloud | C5: Germany / Finland | D5: 45 | E5: EU-GDPR ✓ | F5: native, cheapest, EU adequacy covers UK
A6: North America | B6: Hetzner Cloud | C6: Ashburn VA / Hillsboro OR | D6: 45 | E6: US ✓ | F6: native US datacentre
A7: Oceania | B7: Hetzner (Singapore) or AU host | C7: Singapore (nearest) | D7: 45-60 | E7: AU Privacy Act ~ | F7: Singapore latency ok; AU host for true residency
A8: Africa | B8: xneelo (ex-Hetzner SA) or SA host | C8: Cape Town / Samrand (Gauteng) | D8: consumption | E8: POPIA ✓ (in-country) | F8: Hetzner Cloud has NO Africa DC; use xneelo for residency
A9: Central spine | B9: Hetzner Cloud | C9: EU (or co-located) | D9: 45 + DB 25 | E9: global | F9: one authoritative ledger+identity

Sheet Regions
A1: Country / region-specific considerations (reference)
A2: English at launch everywhere; local language default is a future option.
A4: Region / city | B4: Currency | C4: Language (launch → future) | D4: Privacy law | E4: Payment rail | F4: Cultural / religious notes
A5: Africa · Pretoria | B5: ZAR | C5: English → Afrikaans/Zulu | D5: POPIA | E5: Paystack (ZAR) | F5: launch market; local public holidays
A6: N. America · New York | B6: USD | C6: English → ES | D6: US state laws (CCPA…) | E6: Stripe (USD) | F6: tipping/holiday calendar differ
A7: Europe · London | B7: GBP | C7: English → local | D7: UK-GDPR / EU-GDPR | E7: Stripe (GBP/EUR) | F7: cookie/consent prominence
A8: Oceania · Sydney | B8: AUD | C8: English | D8: Australian Privacy Act | E8: Stripe (AUD) | F8: seasons inverted; AU holidays
A9: Future (e.g. Gulf) | B9: local | C9: English → RTL Arabic | D9: local law | E9: local rail | F9: right-to-left UI, religious calendar/imagery
