Workbook

Sheet Read me
A1: TrustSquare · Quick · Trader — translation proofreading table
A2: Source: live database backup 12 Oct 2026 04:40 and the app dictionaries in the MarketSquare project (Trader from the fast-lane branch, not live yet).
A4: Sheets
A5: All strings — every app word or sentence: English on the left, then Afrikaans, isiZulu, isiXhosa, Sepedi.
A6: Afrikaans / isiZulu / isiXhosa / Sepedi review — one sheet per proofreader: English, current text, and yellow columns to fill in.
A7: Content & legal — advert texts, place names, guide and legal passages the app auto-translated on demand (mostly Afrikaans only).
A8: Kept in English — phrases deliberately left in English (legal clauses, acronyms, codes); listed so reviewers do not translate them.
A9: Summary — counts per app and language, calculated from All strings.
A11: Colour code
A12: TrustSquare rows
A13: Quick rows
A14: Trader rows
... A20: How to fill in a review sheet (example)
A21: English | B21: Current Afrikaans | C21: Corrected Afrikaans | D21: Comment
A22: Featured | B22: Uitgelig | C22: Uitgelig | D22: OK as is
A23: World Heritage | B23: Wereld Erfenis | C23: Wêrelderfenis | D23: One word, with ê
A25: {n} in a pattern stands for a number the app fills in; keep it in the translation.

Sheet Summary
A1: App | B1: Strings | C1: Afrikaans translated | D1: isiZulu translated | E1: isiXhosa translated | F1: Sepedi translated | G1: Afrikaans blank | H1: isiZulu blank | I1: isiXhosa blank | J1: Sepedi blank
A2: TrustSquare | B2: =COUNTIF('All strings'!$B$2:$B$3210,A2) -> 2232 | C2: =SUMPRODUCT(('All strings'!$B$2:$B$3210=$A2)*(LEN('All strings'!$E$2:$E$3210)>0)) -> 2210 | D2: =SUMPRODUCT(('All strings'!$B$2:$B$3210=$A2)*(LEN('All strings'!$F$2:$F$3210)>0)) -> 1896 | E2: =SUMPRODUCT(('All strings'!$B$2:$B$3210=$A2)*(LEN('All strings'!$G$2:$G$3210)>0)) -> 1766 | F2: =SUMPRODUCT(('All strings'!$B$2:$B$3210=$A2)*(LEN('All strings'!$H$2:$H$3210)>0)) -> 1773 | G2: =SUMPRODUCT(('All strings'!$B$2:$B$3210=$A2)*(LEN('All strings'!$E$2:$E$3210)=0)) -> 22 | H2: =SUMPRODUCT(('All strings'!$B$2:$B$3210=$A2)*(LEN('All strings'!$F$2:$F$3210)=0)) -> 336 | I2: =SUMPRODUCT(('All strings'!$B$2:$B$3210=$A2)*(LEN('All strings'!$G$2:$G$3210)=0)) -> 466 | J2: =SUMPRODUCT(('All strings'!$B$2:$B$3210=$A2)*(LEN('All strings'!$H$2:$H$3210)=0)) -> 459
A3: Quick | B3: =COUNTIF('All strings'!$B$2:$B$3210,A3) -> 919 | C3: =SUMPRODUCT(('All strings'!$B$2:$B$3210=$A3)*(LEN('All strings'!$E$2:$E$3210)>0)) -> 919 | D3: =SUMPRODUCT(('All strings'!$B$2:$B$3210=$A3)*(LEN('All strings'!$F$2:$F$3210)>0)) -> 919 | E3: =SUMPRODUCT(('All strings'!$B$2:$B$3210=$A3)*(LEN('All strings'!$G$2:$G$3210)>0)) -> 919 | F3: =SUMPRODUCT(('All strings'!$B$2:$B$3210=$A3)*(LEN('All strings'!$H$2:$H$3210)>0)) -> 919 | G3: =SUMPRODUCT(('All strings'!$B$2:$B$3210=$A3)*(LEN('All strings'!$E$2:$E$3210)=0)) -> 0 | H3: =SUMPRODUCT(('All strings'!$B$2:$B$3210=$A3)*(LEN('All strings'!$F$2:$F$3210)=0)) -> 0 | I3: =SUMPRODUCT(('All strings'!$B$2:$B$3210=$A3)*(LEN('All strings'!$G$2:$G$3210)=0)) -> 0 | J3: =SUMPRODUCT(('All strings'!$B$2:$B$3210=$A3)*(LEN('All strings'!$H$2:$H$3210)=0)) -> 0
A4: Trader | B4: =COUNTIF('All strings'!$B$2:$B$3210,A4) -> 58 | C4: =SUMPRODUCT(('All strings'!$B$2:$B$3210=$A4)*(LEN('All strings'!$E$2:$E$3210)>0)) -> 58 | D4: =SUMPRODUCT(('All strings'!$B$2:$B$3210=$A4)*(LEN('All strings'!$F$2:$F$3210)>0)) -> 58 | E4: =SUMPRODUCT(('All strings'!$B$2:$B$3210=$A4)*(LEN('All strings'!$G$2:$G$3210)>0)) -> 58 | F4: =SUMPRODUCT(('All strings'!$B$2:$B$3210=$A4)*(LEN('All strings'!$H$2:$H$3210)>0)) -> 58 | G4: =SUMPRODUCT(('All strings'!$B$2:$B$3210=$A4)*(LEN('All strings'!$E$2:$E$3210)=0)) -> 0 | H4: =SUMPRODUCT(('All strings'!$B$2:$B$3210=$A4)*(LEN('All strings'!$F$2:$F$3210)=0)) -> 0 | I4: =SUMPRODUCT(('All strings'!$B$2:$B$3210=$A4)*(LEN('All strings'!$G$2:$G$3210)=0)) -> 0 | J4: =SUMPRODUCT(('All strings'!$B$2:$B$3210=$A4)*(LEN('All strings'!$H$2:$H$3210)=0)) -> 0
A5: Total | B5: =SUM(B2:B4) -> 3209 | C5: =SUM(C2:C4) -> 3187 | D5: =SUM(D2:D4) -> 2873 | E5: =SUM(E2:E4) -> 2743 | F5: =SUM(F2:F4) -> 2750 | G5: =SUM(G2:G4) -> 22 | H5: =SUM(H2:H4) -> 336 | I5: =SUM(I2:I4) -> 466 | J5: =SUM(J2:J4) -> 459
A7: Content & legal sheet holds a further 1262 auto-translated texts; Kept in English holds 506 phrases.

Sheet All strings
A1: ID | B1: App | C1: Kind | D1: English (source) | E1: Afrikaans | F1: isiZulu | G1: isiXhosa | H1: Sepedi | I1: Flags
A2: T0001 | B2: TrustSquare | C2: App dictionary | D2: AI examples on | E2: KI-voorbeelde aan | F2: Izibonelo ze-AI zivuliwe | G2: Imizekelo ye-AI ivuliwe | H2: Mehlala ya AI e butswe
A3: T0002 | B3: TrustSquare | C3: App dictionary | D3: AI examples off | E3: KI-voorbeelde af | F3: Izibonelo ze-AI zivaliwe | H3: Mehlala ya AI e timilwe | I3: isiXhosa: Blank
A4: T0003 | B4: TrustSquare | C4: App dictionary | D4: AI examples are shown, below the real listings. | E4: KI-voorbeelde word gewys, onder die regte advertensies. | F4: Izibonelo ze-AI ziboniswa ngezansi kwezikhangiso zangempela. | G4: Imizekelo ye-AI iboniswa ngezantsi kweentengiso zokwenyani. | I4: Sepedi: Blank
A5: T0004 | B5: TrustSquare | C5: App dictionary | D5: AI examples are hidden. Only real listings show. | E5: KI-voorbeelde is versteek. Net regte advertensies wys. | I5: isiZulu: Blank; isiXhosa: Blank; Sepedi: Blank
A6: T0005 | B6: TrustSquare | C6: App dictionary | D6: Show AI examples | E6: Wys KI-voorbeelde | I6: isiZulu: Blank; isiXhosa: Blank; Sepedi: Blank
A7: T0006 | B7: TrustSquare | C7: App dictionary | D7: Show or hide the AI example listings | E7: Wys of versteek die KI-voorbeeldadvertensies | I7: isiZulu: Blank; isiXhosa: Blank; Sepedi: Blank
A8: T0007 | B8: TrustSquare | C8: App dictionary | D8: Me | E8: Ek | F8: Mina | G8: Mna | H8: Nna
A9: T0008 | B9: TrustSquare | C9: App dictionary | D9: No | E9: Nee | F9: Cha | G9: Hayi | H9: Aowa
A10: T0009 | B10: TrustSquare | C10: App dictionary | D10: to | E10: tot | F10: ku | G10: ukuya | H10: go
A11: T0010 | B11: TrustSquare | C11: App dictionary | D11: All | E11: Alles | F11: Konke | G11: Zonke | H11: Ka moka
A12: T0011 | B12: TrustSquare | C12: App dictionary | D12: Any | E12: Enige | F12: Noma yini | G12: Nayiphi | H12: Efe goba efe
A13: T0012 | B13: TrustSquare | C13: App dictionary | D13: Art | E13: Kuns | F13: Ubuciko | G13: Ubugcisa | H13: Bokgabo
A14: T0013 | B14: TrustSquare | C14: App dictionary | D14: Fri | E14: Vr | F14: Lwesihlanu | G14: Hla | H14: Hlan
A15: T0014 | B15: TrustSquare | C15: App dictionary | D15: Mon | E15: Ma | F15: Msombuluko | G15: Mvu | H15: Moš
A16: T0015 | B16: TrustSquare | C16: App dictionary | D16: Sat | E16: Sa | F16: Mgqibelo | G16: Mgq | H16: Mok
A17: T0016 | B17: TrustSquare | C17: App dictionary | D17: Sun | E17: So | F17: Sonto | G17: Caw | H17: Son
A18: T0017 | B18: TrustSquare | C18: App dictionary | D18: Thu | E18: Do | F18: Lwesine | G18: Sin | H18: Ne
A19: T0018 | B19: TrustSquare | C19: App dictionary | D19: Tue | E19: Di | F19: Lwesibili | G19: Bin | H19: Bed
... A25: T0024 | B25: TrustSquare | C25: App dictionary | D25: Back | E25: Terug | F25: Emuva | G25: Buyela | H25: Morago
A26: T0025 | B26: TrustSquare | C26: App dictionary | D26: Buzz | E26: Buzz | F26: Buzz | G26: Buzz | H26: Buzz | I26: Afrikaans: Same as English; isiZulu: Same as English; isiXhosa: Same as English; Sepedi: Same as English
A27: T0026 | B27: TrustSquare | C27: App dictionary | D27: Cars | E27: Motors | F27: Izimoto | G27: Iimoto | H27: Dikoloi
A28: T0027 | B28: TrustSquare | C28: App dictionary | D28: Chef | E28: Sjef | F28: Umpheki | G28: Umpheki | H28: Shefo
A29: T0028 | B29: TrustSquare | C29: App dictionary | D29: City | E29: Stad | F29: Idolobha | G29: Isixeko | H29: Toropo
A30: T0029 | B30: TrustSquare | C30: App dictionary | D30: Cook | E30: Kok | F30: Umpheki | G30: Umpheki | H30: Moapei
A31: T0030 | B31: TrustSquare | C31: App dictionary | D31: Cuba | E31: Kuba | F31: iCuba | G31: Cuba | H31: Cuba | I31: isiXhosa: Same as English; Sepedi: Same as English
A32: T0031 | B32: TrustSquare | C32: App dictionary | D32: Edit | E32: Wysig | F32: Hlela | G32: Hlela | H32: Fetola
A33: T0032 | B33: TrustSquare | C33: App dictionary | D33: Farm | E33: Plaas | F33: Ipulazi | G33: Ifama | H33: Polase
A34: T0033 | B34: TrustSquare | C34: App dictionary | D34: Free | E34: Gratis | F34: Mahhala | G34: Simahla | H34: Mahala
A35: T0034 | B35: TrustSquare | C35: App dictionary | D35: Home | E35: Tuis | F35: Ikhaya | G35: Ekhaya | H35: Gae
A36: T0035 | B36: TrustSquare | C36: App dictionary | D36: Iraq | E36: Irak | F36: i-Iraq | G36: Iraq | H36: Iraq | I36: isiXhosa: Same as English; Sepedi: Same as English
A37: T0036 | B37: TrustSquare | C37: App dictionary | D37: Make | E37: Maak | F37: Yenza | G37: Yenza | H37: Dira
A38: T0037 | B38: TrustSquare | C38: App dictionary | D38: Mode | E38: Modus | F38: Imodi | G38: Imo | H38: Mokgwa
A39: T0038 | B39: TrustSquare | C39: App dictionary | D39: More | E39: Meer | F39: Okunye | G39: Ngaphezulu | H39: Tše dingwe
A40: T0039 | B40: TrustSquare | C40: App dictionary | D40: Oman | E40: Oman | F40: i-Oman | G40: Oman | H40: Oman | I40: Afrikaans: Same as English; isiXhosa: Same as English; Sepedi: Same as English
A41: T0040 | B41: TrustSquare | C41: App dictionary | D41: Pool | E41: Swembad | F41: Iphuli | G41: Idama lokuqubha | H41: Bodiba bja go rutha
A42: T0041 | B42: TrustSquare | C42: App dictionary | D42: Save | E42: Stoor | F42: Londoloza | G42: Gcina | H42: Boloka
A43: T0042 | B43: TrustSquare | C43: App dictionary | D43: Sell | E43: Verkoop | F43: Thengisa | G43: Thengisa | H43: Rekiša
A44: T0043 | B44: TrustSquare | C44: App dictionary | D44: Sent | E44: Gestuur | F44: Kuthunyelwe | G44: Ithunyelwe | H44: E rometšwe
A45: T0044 | B45: TrustSquare | C45: App dictionary | D45: Solo | E45: Alleen | F45: Wedwa | G45: Ndedwa | H45: Nnoši
A46: T0045 | B46: TrustSquare | C46: App dictionary | D46: Tags | E46: Etikette | F46: Omaka | G46: Iithegi | H46: Dileibole
A47: T0046 | B47: TrustSquare | C47: App dictionary | D47: Team | E47: Span | F47: Ithimba | G47: Iqela | H47: Sehlopha
A48: T0047 | B48: TrustSquare | C48: App dictionary | D48: Term | E48: Termyn | F48: Isikhathi | G48: Ixesha | H48: Nako ya tumelelano
A49: T0048 | B49: TrustSquare | C49: App dictionary | D49: Tier | E49: Vlak | F49: Izinga | G49: Inqanaba | H49: Legato
A50: T0049 | B50: TrustSquare | C50: App dictionary | D50: bulk | E50: grootmaat | F50: ngobuningi | G50: ngobuninzi | H50: ka bontši
A51: T0050 | B51: TrustSquare | C51: App dictionary | D51: this | E51: hierdie | F51: lokhu | G51: le | H51: se
A52: T0051 | B52: TrustSquare | C52: App dictionary | D52: All → | E52: Alles → | F52: Konke → | G52: Zonke → | H52: Ka moka →
A53: T0052 | B53: TrustSquare | C53: App dictionary | D53: Buyer | E53: Koper | F53: Umthengi | G53: Umthengi | H53: Moreki
A54: T0053 | B54: TrustSquare | C54: App dictionary | D54: Chess | E54: Skaak | F54: I-chess | G54: Itshesi | H54: Chess | I54: Sepedi: Same as English
A55: T0054 | B55: TrustSquare | C55: App dictionary | D55: Chile | E55: Chili | F55: iChile | G55: Chile | H55: Chile | I55: isiXhosa: Same as English; Sepedi: Same as English
A56: T0055 | B56: TrustSquare | C56: App dictionary | D56: China | E56: China | F56: iShayina | G56: iTshayina | H56: China | I56: Afrikaans: Same as English; Sepedi: Same as English
A57: T0056 | B57: TrustSquare | C57: App dictionary | D57: Class | E57: Klas | F57: Isigaba | G57: Udidi | H57: Sehlopha
A58: T0057 | B58: TrustSquare | C58: App dictionary | D58: Clear | E58: Wis | F58: Sula | G58: Cima | H58: Phumola
A59: T0058 | B59: TrustSquare | C59: App dictionary | D59: Egypt | E59: Egipte | F59: iGibhithe | G59: iYiputa | H59: Egipita
A60: T0059 | B60: TrustSquare | C60: App dictionary | D60: Email | E60: E-pos | F60: I-imeyili | G60: I-imeyile | H60: Imeile
A61: T0060 | B61: TrustSquare | C61: App dictionary | D61: Haiko | E61: Haiko | F61: Haiko | G61: Haiko | H61: Haiko | I61: Afrikaans: Same as English; isiZulu: Same as English; isiXhosa: Same as English; Sepedi: Same as English
A62: T0061 | B62: TrustSquare | C62: App dictionary | D62: House | E62: Huis | F62: Indlu | G62: Indlu | H62: Ntlo
A63: T0062 | B63: TrustSquare | C63: App dictionary | D63: India | E63: Indië | F63: iNdiya | G63: iIndiya | H63: India | I63: Sepedi: Same as English
A64: T0063 | B64: TrustSquare | C64: App dictionary | D64: Italy | E64: Italië | F64: i-Italy | G64: iItali | H64: Italy | I64: Sepedi: Same as English
A65: T0064 | B65: TrustSquare | C65: App dictionary | D65: Kenya | E65: Kenia | F65: iKenya | G65: iKenya | H65: Kenya | I65: Sepedi: Same as English
A66: T0065 | B66: TrustSquare | C66: App dictionary | D66: Legal | E66: Regsake | F66: Ezomthetho | G66: Ezomthetho | H66: Tša molao
A67: T0066 | B67: TrustSquare | C67: App dictionary | D67: Level | E67: Vlak | F67: Izinga | G67: Inqanaba | H67: Legato
A68: T0067 | B68: TrustSquare | C68: App dictionary | D68: Libya | E68: Libië | F68: iLibya | G68: Libya | H68: Libya | I68: isiXhosa: Same as English; Sepedi: Same as English
A69: T0068 | B69: TrustSquare | C69: App dictionary | D69: Music | E69: Musiek | F69: Umculo | G69: Umculo | H69: Mmino
A70: T0069 | B70: TrustSquare | C70: App dictionary | D70: Nanny | E70: Kinderoppasser | F70: Umzanyana | G70: Umgcini-bantwana | H70: Mohlokomedi wa bana
A71: T0070 | B71: TrustSquare | C71: App dictionary | D71: Other | E71: Ander | F71: Okunye | G71: Okunye | H71: Tše dingwe
A72: T0071 | B72: TrustSquare | C72: App dictionary | D72: Paver | E72: Plaveier | F72: Obeka amapheva | G72: Umbeki-zitena | H72: Mobei wa diphefi
A73: T0072 | B73: TrustSquare | C73: App dictionary | D73: Plans | E73: Planne | F73: Amapulani | G73: Izicwangciso | H73: Dipeakanyo
A74: T0073 | B74: TrustSquare | C74: App dictionary | D74: Price | E74: Prys | F74: Intengo | G74: Ixabiso | H74: Theko
A75: T0074 | B75: TrustSquare | C75: App dictionary | D75: Reach | E75: Bereik | F75: Ukufinyelela | G75: Ukufikelela | H75: Phihlelelo
A76: T0075 | B76: TrustSquare | C76: App dictionary | D76: Roles | E76: Rolle | F76: Izindima | G76: Iindima | H76: Mediro
A77: T0076 | B77: TrustSquare | C77: App dictionary | D77: Saved | E77: Gestoor | F77: Kulondoloziwe | G77: Kugciniwe | H77: E bolokilwe
A78: T0077 | B78: TrustSquare | C78: App dictionary | D78: Solar | E78: Sonkrag | F78: Ilanga (solar) | G78: Ilanga (solar) | H78: Letšatši
A79: T0078 | B79: TrustSquare | C79: App dictionary | D79: Spain | E79: Spanje | F79: iSpeyini | G79: iSpeyin | H79: Spain | I79: Sepedi: Same as English
A80: T0079 | B80: TrustSquare | C80: App dictionary | D80: Stays | E80: Verblyf | F80: Indawo yokuhlala | G80: Iindawo zokuhlala | H80: Madulo
A81: T0080 | B81: TrustSquare | C81: App dictionary | D81: Study | E81: Studie | F81: Funda | G81: Funda | H81: Ithute
A82: T0081 | B82: TrustSquare | C82: App dictionary | D82: Sudan | E82: Soedan | F82: iSudan | G82: Sudan | H82: Sudan | I82: isiXhosa: Same as English; Sepedi: Same as English
A83: T0082 | B83: TrustSquare | C83: App dictionary | D83: Syria | E83: Sirië | F83: iSyria | G83: iSiriya | H83: Syria | I83: Sepedi: Same as English
A84: T0083 | B84: TrustSquare | C84: App dictionary | D84: Tiler | E84: Teëlêer | F84: Obeka amathayela | G84: Umbeki-zithayile | H84: Mobei wa dithaele
A85: T0084 | B85: TrustSquare | C85: App dictionary | D85: Title | E85: Titel | F85: Isihloko | G85: Isihloko | H85: Thaetlele
A86: T0085 | B86: TrustSquare | C86: App dictionary | D86: Today | E86: Vandag | F86: Namuhla | G86: Namhlanje | H86: Lehono
A87: T0086 | B87: TrustSquare | C87: App dictionary | D87: Trust | E87: Vertroue | F87: Ukwethemba | G87: Ukuthembeka | H87: Tshepo
A88: T0087 | B88: TrustSquare | C88: App dictionary | D88: Yemen | E88: Jemen | F88: iYemen | G88: Yemen | H88: Yemen | I88: isiXhosa: Same as English; Sepedi: Same as English
A89: T0088 | B89: TrustSquare | C89: App dictionary | D89: Active | E89: Aktief | F89: Kuyasebenza | G89: Iyasebenza | H89: E a šoma
A90: T0089 | B90: TrustSquare | C90: App dictionary | D90: Agency | E90: Agentskap | F90: I-ejensi | G90: I-arhente | H90: Etšensi
A91: T0090 | B91: TrustSquare | C91: App dictionary | D91: Ask me | E91: Vra my | F91: Ngibuze | G91: Ndibuze | H91: Mpotšiše
A92: T0091 | B92: TrustSquare | C92: App dictionary | D92: Babies | E92: Babas | F92: Izingane | G92: Iintsana | H92: Masea
A93: T0092 | B93: TrustSquare | C93: App dictionary | D93: Boxing | E93: Boks | F93: Isibhakela | G93: Amanqindi | H93: Ditebele
A94: T0093 | B94: TrustSquare | C94: App dictionary | D94: Brazil | E94: Brasilië | F94: iBrazili | G94: iBrazil | H94: Brazil | I94: Sepedi: Same as English
A95: T0094 | B95: TrustSquare | C95: App dictionary | D95: Browse | E95: Blaai | F95: Bhekabheka | G95: Khangela | H95: Lebelela
A96: T0095 | B96: TrustSquare | C96: App dictionary | D96: Bundle | E96: Bondel | F96: Iphakethe | G96: Iphakheji | H96: Sephuthelwa
A97: T0096 | B97: TrustSquare | C97: App dictionary | D97: Canada | E97: Kanada | F97: iKhanada | G97: iKhanada | H97: Canada | I97: Sepedi: Same as English
A98: T0097 | B98: TrustSquare | C98: App dictionary | D98: Cancel | E98: Kanselleer | F98: Khansela | G98: Rhoxisa | H98: Khansela
A99: T0098 | B99: TrustSquare | C99: App dictionary | D99: Change | E99: Verander | F99: Shintsha | G99: Tshintsha | H99: Fetola
A100: T0099 | B100: TrustSquare | C100: App dictionary | D100: Couple | E100: Paartjie | F100: Umbhangqwana | G100: Isibini | H100: Banyalani
A101: T0100 | B101: TrustSquare | C101: App dictionary | D101: Driver | E101: Bestuurder | F101: Umshayeli | G101: Umqhubi | H101: Mootledi
A102: T0101 | B102: TrustSquare | C102: App dictionary | D102: Duplex | E102: Dupleks | F102: I-duplex | G102: Iduplex | H102: Duplex | I102: Sepedi: Same as English
A103: T0102 | B103: TrustSquare | C103: App dictionary | D103: Either | E103: Enigeen | F103: Noma yikuphi | G103: Nokuba yeyiphi | H103: Efe goba efe
A104: T0103 | B104: TrustSquare | C104: App dictionary | D104: Europe | E104: Europa | F104: iYurophu | G104: iYurophu | H104: Yuropa
A105: T0104 | B105: TrustSquare | C105: App dictionary | D105: Filter | E105: Filter | F105: Hlunga | G105: Hluza | H105: Sefa | I105: Afrikaans: Same as English
...

Sheet Afrikaans review
A1: ID | B1: App | C1: English (source) | D1: Current Afrikaans | E1: Flag | F1: Corrected Afrikaans | G1: Comment
A2: T0001 | B2: TrustSquare | C2: AI examples on | D2: KI-voorbeelde aan
A3: T0002 | B3: TrustSquare | C3: AI examples off | D3: KI-voorbeelde af
A4: T0003 | B4: TrustSquare | C4: AI examples are shown, below the real listings. | D4: KI-voorbeelde word gewys, onder die regte advertensies.
A5: T0004 | B5: TrustSquare | C5: AI examples are hidden. Only real listings show. | D5: KI-voorbeelde is versteek. Net regte advertensies wys.
A6: T0005 | B6: TrustSquare | C6: Show AI examples | D6: Wys KI-voorbeelde
A7: T0006 | B7: TrustSquare | C7: Show or hide the AI example listings | D7: Wys of versteek die KI-voorbeeldadvertensies
A8: T0007 | B8: TrustSquare | C8: Me | D8: Ek
A9: T0008 | B9: TrustSquare | C9: No | D9: Nee
A10: T0009 | B10: TrustSquare | C10: to | D10: tot
A11: T0010 | B11: TrustSquare | C11: All | D11: Alles
A12: T0011 | B12: TrustSquare | C12: Any | D12: Enige
A13: T0012 | B13: TrustSquare | C13: Art | D13: Kuns
... A25: T0024 | B25: TrustSquare | C25: Back | D25: Terug
A26: T0025 | B26: TrustSquare | C26: Buzz | D26: Buzz | E26: Same as English (fine for names/brands)
A27: T0026 | B27: TrustSquare | C27: Cars | D27: Motors
A28: T0027 | B28: TrustSquare | C28: Chef | D28: Sjef
A29: T0028 | B29: TrustSquare | C29: City | D29: Stad
A30: T0029 | B30: TrustSquare | C30: Cook | D30: Kok
A31: T0030 | B31: TrustSquare | C31: Cuba | D31: Kuba
A32: T0031 | B32: TrustSquare | C32: Edit | D32: Wysig
A33: T0032 | B33: TrustSquare | C33: Farm | D33: Plaas
A34: T0033 | B34: TrustSquare | C34: Free | D34: Gratis
A35: T0034 | B35: TrustSquare | C35: Home | D35: Tuis
A36: T0035 | B36: TrustSquare | C36: Iraq | D36: Irak
A37: T0036 | B37: TrustSquare | C37: Make | D37: Maak
A38: T0037 | B38: TrustSquare | C38: Mode | D38: Modus
A39: T0038 | B39: TrustSquare | C39: More | D39: Meer
A40: T0039 | B40: TrustSquare | C40: Oman | D40: Oman | E40: Same as English (fine for names/brands)
A41: T0040 | B41: TrustSquare | C41: Pool | D41: Swembad
A42: T0041 | B42: TrustSquare | C42: Save | D42: Stoor
A43: T0042 | B43: TrustSquare | C43: Sell | D43: Verkoop
A44: T0043 | B44: TrustSquare | C44: Sent | D44: Gestuur
A45: T0044 | B45: TrustSquare | C45: Solo | D45: Alleen
A46: T0045 | B46: TrustSquare | C46: Tags | D46: Etikette
A47: T0046 | B47: TrustSquare | C47: Team | D47: Span
A48: T0047 | B48: TrustSquare | C48: Term | D48: Termyn
A49: T0048 | B49: TrustSquare | C49: Tier | D49: Vlak
A50: T0049 | B50: TrustSquare | C50: bulk | D50: grootmaat
A51: T0050 | B51: TrustSquare | C51: this | D51: hierdie
A52: T0051 | B52: TrustSquare | C52: All → | D52: Alles →
... A55: T0054 | B55: TrustSquare | C55: Chile | D55: Chili
A56: T0055 | B56: TrustSquare | C56: China | D56: China | E56: Same as English (fine for names/brands)
A57: T0056 | B57: TrustSquare | C57: Class | D57: Klas
A58: T0057 | B58: TrustSquare | C58: Clear | D58: Wis
A59: T0058 | B59: TrustSquare | C59: Egypt | D59: Egipte
A60: T0059 | B60: TrustSquare | C60: Email | D60: E-pos
A61: T0060 | B61: TrustSquare | C61: Haiko | D61: Haiko | E61: Same as English (fine for names/brands)
A62: T0061 | B62: TrustSquare | C62: House | D62: Huis
A63: T0062 | B63: TrustSquare | C63: India | D63: Indië
A64: T0063 | B64: TrustSquare | C64: Italy | D64: Italië
A65: T0064 | B65: TrustSquare | C65: Kenya | D65: Kenia
A66: T0065 | B66: TrustSquare | C66: Legal | D66: Regsake
A67: T0066 | B67: TrustSquare | C67: Level | D67: Vlak
A68: T0067 | B68: TrustSquare | C68: Libya | D68: Libië
A69: T0068 | B69: TrustSquare | C69: Music | D69: Musiek
A70: T0069 | B70: TrustSquare | C70: Nanny | D70: Kinderoppasser
A71: T0070 | B71: TrustSquare | C71: Other | D71: Ander
A72: T0071 | B72: TrustSquare | C72: Paver | D72: Plaveier
A73: T0072 | B73: TrustSquare | C73: Plans | D73: Planne
... A104: T0103 | B104: TrustSquare | C104: Europe | D104: Europa
A105: T0104 | B105: TrustSquare | C105: Filter | D105: Filter | E105: Same as English (fine for names/brands)
A106: T0105 | B106: TrustSquare | C106: France | D106: Frankryk
A107: T0106 | B107: TrustSquare | C107: Garden | D107: Tuin
A108: T0107 | B108: TrustSquare | C108: Got it | D108: Reg so
A109: T0108 | B109: TrustSquare | C109: Greece | D109: Griekeland
A110: T0109 | B110: TrustSquare | C110: Intros | D110: Voorstellings
A111: T0110 | B111: TrustSquare | C111: Joined | D111: Aangesluit
A112: T0111 | B112: TrustSquare | C112: Jordan | D112: Jordanië
A113: T0112 | B113: TrustSquare | C113: Manual | D113: Handrat
A114: T0113 | B114: TrustSquare | C114: Matric | D114: Matriek
A115: T0114 | B115: TrustSquare | C115: Mexico | D115: Meksiko
A116: T0115 | B116: TrustSquare | C116: More ▾ | D116: Meer ▾
A117: T0116 | B117: TrustSquare | C117: Next → | D117: Volgende →
... A127: T0126 | B127: TrustSquare | C127: Soccer | D127: Sokker
A128: T0127 | B128: TrustSquare | C128: Square | D128: Square | E128: Same as English (fine for names/brands)
A129: T0128 | B129: TrustSquare | C129: Stamps | D129: Seëls
A130: T0129 | B130: TrustSquare | C130: Suburb | D130: Voorstad
A131: T0130 | B131: TrustSquare | C131: Sweden | D131: Swede
A132: T0131 | B132: TrustSquare | C132: Turkey | D132: Turkye
A133: T0132 | B133: TrustSquare | C133: Tutors | D133: Onderrig
A134: T0133 | B134: TrustSquare | C134: Uganda | D134: Uganda | E134: Same as English (fine for names/brands)
A135: T0134 | B135: TrustSquare | C135: Unlock | D135: Ontsluit
A136: T0135 | B136: TrustSquare | C136: Waiter | D136: Kelner
A137: T0136 | B137: TrustSquare | C137: Wallet | D137: Beursie
A138: T0137 | B138: TrustSquare | C138: Welder | D138: Sweiser
A139: T0138 | B139: TrustSquare | C139: Zambia | D139: Zambië
A140: T0139 | B140: TrustSquare | C140: ← Back | D140: ← Terug
A141: T0140 | B141: TrustSquare | C141: ← Exit | D141: ← Verlaat
A142: T0141 | B142: TrustSquare | C142: 🚗 Cars | D142: 🚗 Motors
A143: T0142 | B143: TrustSquare | C143: / month | D143: / maand
A144: T0143 | B144: TrustSquare | C144: 2 slots | D144: 2 plekke
A145: T0144 | B145: TrustSquare | C145: 7 steps | D145: 7 stappe
A146: T0145 | B146: TrustSquare | C146: Albania | D146: Albanië
... A152: T0151 | B152: TrustSquare | C152: Bolivia | D152: Bolivië
A153: T0152 | B153: TrustSquare | C153: Bukhara | D153: Bukhara | E153: Same as English (fine for names/brands)
A154: T0153 | B154: TrustSquare | C154: Cashier | D154: Kassier
A155: T0154 | B155: TrustSquare | C155: Casuals | D155: Los werkers
A156: T0155 | B156: TrustSquare | C156: Cluster | D156: Groep
A157: T0156 | B157: TrustSquare | C157: Contact | D157: Kontak
...

Sheet isiZulu review
A1: ID | B1: App | C1: English (source) | D1: Current isiZulu | E1: Flag | F1: Corrected isiZulu | G1: Comment
A2: T0001 | B2: TrustSquare | C2: AI examples on | D2: Izibonelo ze-AI zivuliwe
A3: T0002 | B3: TrustSquare | C3: AI examples off | D3: Izibonelo ze-AI zivaliwe
A4: T0003 | B4: TrustSquare | C4: AI examples are shown, below the real listings. | D4: Izibonelo ze-AI ziboniswa ngezansi kwezikhangiso zangempela.
A5: T0004 | B5: TrustSquare | C5: AI examples are hidden. Only real listings show. | E5: Blank — app shows English
A6: T0005 | B6: TrustSquare | C6: Show AI examples | E6: Blank — app shows English
A7: T0006 | B7: TrustSquare | C7: Show or hide the AI example listings | E7: Blank — app shows English
A8: T0007 | B8: TrustSquare | C8: Me | D8: Mina
A9: T0008 | B9: TrustSquare | C9: No | D9: Cha
A10: T0009 | B10: TrustSquare | C10: to | D10: ku
A11: T0010 | B11: TrustSquare | C11: All | D11: Konke
A12: T0011 | B12: TrustSquare | C12: Any | D12: Noma yini
A13: T0012 | B13: TrustSquare | C13: Art | D13: Ubuciko
A14: T0013 | B14: TrustSquare | C14: Fri | D14: Lwesihlanu
A15: T0014 | B15: TrustSquare | C15: Mon | D15: Msombuluko
A16: T0015 | B16: TrustSquare | C16: Sat | D16: Mgqibelo
A17: T0016 | B17: TrustSquare | C17: Sun | D17: Sonto
A18: T0017 | B18: TrustSquare | C18: Thu | D18: Lwesine
A19: T0018 | B19: TrustSquare | C19: Tue | D19: Lwesibili
... A25: T0024 | B25: TrustSquare | C25: Back | D25: Emuva
A26: T0025 | B26: TrustSquare | C26: Buzz | D26: Buzz | E26: Same as English (fine for names/brands)
A27: T0026 | B27: TrustSquare | C27: Cars | D27: Izimoto
A28: T0027 | B28: TrustSquare | C28: Chef | D28: Umpheki
A29: T0028 | B29: TrustSquare | C29: City | D29: Idolobha
A30: T0029 | B30: TrustSquare | C30: Cook | D30: Umpheki
A31: T0030 | B31: TrustSquare | C31: Cuba | D31: iCuba
A32: T0031 | B32: TrustSquare | C32: Edit | D32: Hlela
A33: T0032 | B33: TrustSquare | C33: Farm | D33: Ipulazi
A34: T0033 | B34: TrustSquare | C34: Free | D34: Mahhala
A35: T0034 | B35: TrustSquare | C35: Home | D35: Ikhaya
A36: T0035 | B36: TrustSquare | C36: Iraq | D36: i-Iraq
A37: T0036 | B37: TrustSquare | C37: Make | D37: Yenza
A38: T0037 | B38: TrustSquare | C38: Mode | D38: Imodi
... A60: T0059 | B60: TrustSquare | C60: Email | D60: I-imeyili
A61: T0060 | B61: TrustSquare | C61: Haiko | D61: Haiko | E61: Same as English (fine for names/brands)
A62: T0061 | B62: TrustSquare | C62: House | D62: Indlu
A63: T0062 | B63: TrustSquare | C63: India | D63: iNdiya
A64: T0063 | B64: TrustSquare | C64: Italy | D64: i-Italy
A65: T0064 | B65: TrustSquare | C65: Kenya | D65: iKenya
A66: T0065 | B66: TrustSquare | C66: Legal | D66: Ezomthetho
A67: T0066 | B67: TrustSquare | C67: Level | D67: Izinga
A68: T0067 | B68: TrustSquare | C68: Libya | D68: iLibya
A69: T0068 | B69: TrustSquare | C69: Music | D69: Umculo
A70: T0069 | B70: TrustSquare | C70: Nanny | D70: Umzanyana
A71: T0070 | B71: TrustSquare | C71: Other | D71: Okunye
A72: T0071 | B72: TrustSquare | C72: Paver | D72: Obeka amapheva
A73: T0072 | B73: TrustSquare | C73: Plans | D73: Amapulani
... A152: T0151 | B152: TrustSquare | C152: Bolivia | D152: iBolivia
A153: T0152 | B153: TrustSquare | C153: Bukhara | D153: Bukhara | E153: Same as English (fine for names/brands)
A154: T0153 | B154: TrustSquare | C154: Cashier | D154: Umkhasheli
A155: T0154 | B155: TrustSquare | C155: Casuals | D155: Abasebenza isikhashana
A156: T0155 | B156: TrustSquare | C156: Cluster | D156: Iqoqo lezindlu
A157: T0156 | B157: TrustSquare | C157: Contact | D157: Xhumana
A158: T0157 | B158: TrustSquare | C158: Cricket | D158: Ikhilikithi
A159: T0158 | B159: TrustSquare | C159: Croatia | D159: iCroatia
A160: T0159 | B160: TrustSquare | C160: Damaged | D160: Konakele
A161: T0160 | B161: TrustSquare | C161: Dancing | D161: Ukudansa
A162: T0161 | B162: TrustSquare | C162: Details | D162: Imininingwane
A163: T0162 | B163: TrustSquare | C163: ECT Act | D163: ECT Act | E163: Same as English (fine for names/brands)
A164: T0163 | B164: TrustSquare | C164: Ecuador | D164: i-Ecuador
A165: T0164 | B165: TrustSquare | C165: English | D165: IsiNgisi
A166: T0165 | B166: TrustSquare | C166: Ephesus | D166: Ephesus | E166: Same as English (fine for names/brands)
A167: T0166 | B167: TrustSquare | C167: Estonia | D167: i-Estonia
A168: T0167 | B168: TrustSquare | C168: Flatlet | D168: Ifulethi elincane
A169: T0168 | B169: TrustSquare | C169: For You | D169: Okwakho
A170: T0169 | B170: TrustSquare | C170: Garages | D170: Amagaraji
A171: T0170 | B171: TrustSquare | C171: Georgia | D171: iGeorgia
A172: T0171 | B172: TrustSquare | C172: Germany | D172: iJalimane
A173: T0172 | B173: TrustSquare | C173: Hi! I'm | D173: Sawubona! Ngingu
A174: T0173 | B174: TrustSquare | C174: History | D174: Umlando
A175: T0174 | B175: TrustSquare | C175: Iceland | D175: i-Iceland
A176: T0175 | B176: TrustSquare | C176: Invited | D176: Umenyiwe
A177: T0176 | B177: TrustSquare | C177: Ireland | D177: i-Ayilendi
A178: T0177 | B178: TrustSquare | C178: Lebanon | D178: iLebanon
... A199: T0198 | B199: TrustSquare | C199: Simplex | D199: I-simplex
A200: T0199 | B200: TrustSquare | C200: Starter | D200: Starter | E200: Same as English (fine for names/brands)
A201: T0200 | B201: TrustSquare | C201: Summary | D201: Isifinyezo
A202: T0201 | B202: TrustSquare | C202: This is | D202: Lokhu
A203: T0202 | B203: TrustSquare | C203: Tunisia | D203: iTunisia
A204: T0203 | B204: TrustSquare | C204: Vietnam | D204: iVietnam
A205: T0204 | B205: TrustSquare | C205: Weekend | D205: Impelasonto
A206: T0205 | B206: TrustSquare | C206: device. | D206: idivayisi.
A207: T0206 | B207: TrustSquare | C207: 🏕 Stays | D207: 🏕 Izindawo zokuhlala
A208: T0207 | B208: TrustSquare | C208: 👥 Queue | D208: 👥 Umugqa
A209: T0208 | B209: TrustSquare | C209: 🗺 Tours | D209: 🗺 Ukuvakasha
A210: T0209 | B210: TrustSquare | C210: 🚂 Train | D210: 🚂 Isitimela
A211: T0210 | B211: TrustSquare | C211: 10 slots | D211: izikhala eziyi-10
A212: T0211 | B212: TrustSquare | C212: 30 slots | D212: izikhala ezingama-30
... A218: T0217 | B218: TrustSquare | C218: Borehole | D218: Umgodi wamanzi
A219: T0218 | B219: TrustSquare | C219: Bushveld | D219: Bushveld | E219: Same as English (fine for names/brands)
A220: T0219 | B220: TrustSquare | C220: Cambodia | D220: iCambodia
A221: T0220 | B221: TrustSquare | C221: Carthage | D221: Carthage | E221: Same as English (fine for names/brands)
A222: T0221 | B222: TrustSquare | C222: Category | D222: Isigaba
A223: T0222 | B223: TrustSquare | C223: Colombia | D223: iColombia
A224: T0223 | B224: TrustSquare | C224: Domestic | D224: Ezasekhaya
A225: T0224 | B225: TrustSquare | C225: Duration | D225: Isikhathi esithathwayo
A226: T0225 | B226: TrustSquare | C226: Ethiopia | D226: i-Ethiopia
A227: T0226 | B227: TrustSquare | C227: Featured | D227: Okugqamile
A228: T0227 | B228: TrustSquare | C228: Features | D228: Izici
A229: T0228 | B229: TrustSquare | C229: Firearms | D229: Izibhamu
...

Sheet isiXhosa review
A1: ID | B1: App | C1: English (source) | D1: Current isiXhosa | E1: Flag | F1: Corrected isiXhosa | G1: Comment
A2: T0001 | B2: TrustSquare | C2: AI examples on | D2: Imizekelo ye-AI ivuliwe
A3: T0002 | B3: TrustSquare | C3: AI examples off | E3: Blank — app shows English
A4: T0003 | B4: TrustSquare | C4: AI examples are shown, below the real listings. | D4: Imizekelo ye-AI iboniswa ngezantsi kweentengiso zokwenyani.
A5: T0004 | B5: TrustSquare | C5: AI examples are hidden. Only real listings show. | E5: Blank — app shows English
A6: T0005 | B6: TrustSquare | C6: Show AI examples | E6: Blank — app shows English
A7: T0006 | B7: TrustSquare | C7: Show or hide the AI example listings | E7: Blank — app shows English
A8: T0007 | B8: TrustSquare | C8: Me | D8: Mna
A9: T0008 | B9: TrustSquare | C9: No | D9: Hayi
A10: T0009 | B10: TrustSquare | C10: to | D10: ukuya
A11: T0010 | B11: TrustSquare | C11: All | D11: Zonke
A12: T0011 | B12: TrustSquare | C12: Any | D12: Nayiphi
A13: T0012 | B13: TrustSquare | C13: Art | D13: Ubugcisa
A14: T0013 | B14: TrustSquare | C14: Fri | D14: Hla
A15: T0014 | B15: TrustSquare | C15: Mon | D15: Mvu
A16: T0015 | B16: TrustSquare | C16: Sat | D16: Mgq
A17: T0016 | B17: TrustSquare | C17: Sun | D17: Caw
A18: T0017 | B18: TrustSquare | C18: Thu | D18: Sin
A19: T0018 | B19: TrustSquare | C19: Tue | D19: Bin
... A25: T0024 | B25: TrustSquare | C25: Back | D25: Buyela
A26: T0025 | B26: TrustSquare | C26: Buzz | D26: Buzz | E26: Same as English (fine for names/brands)
A27: T0026 | B27: TrustSquare | C27: Cars | D27: Iimoto
A28: T0027 | B28: TrustSquare | C28: Chef | D28: Umpheki
A29: T0028 | B29: TrustSquare | C29: City | D29: Isixeko
A30: T0029 | B30: TrustSquare | C30: Cook | D30: Umpheki
A31: T0030 | B31: TrustSquare | C31: Cuba | D31: Cuba | E31: Same as English (fine for names/brands)
A32: T0031 | B32: TrustSquare | C32: Edit | D32: Hlela
A33: T0032 | B33: TrustSquare | C33: Farm | D33: Ifama
A34: T0033 | B34: TrustSquare | C34: Free | D34: Simahla
A35: T0034 | B35: TrustSquare | C35: Home | D35: Ekhaya
A36: T0035 | B36: TrustSquare | C36: Iraq | D36: Iraq | E36: Same as English (fine for names/brands)
A37: T0036 | B37: TrustSquare | C37: Make | D37: Yenza
A38: T0037 | B38: TrustSquare | C38: Mode | D38: Imo
A39: T0038 | B39: TrustSquare | C39: More | D39: Ngaphezulu
A40: T0039 | B40: TrustSquare | C40: Oman | D40: Oman | E40: Same as English (fine for names/brands)
A41: T0040 | B41: TrustSquare | C41: Pool | D41: Idama lokuqubha
A42: T0041 | B42: TrustSquare | C42: Save | D42: Gcina
A43: T0042 | B43: TrustSquare | C43: Sell | D43: Thengisa
A44: T0043 | B44: TrustSquare | C44: Sent | D44: Ithunyelwe
A45: T0044 | B45: TrustSquare | C45: Solo | D45: Ndedwa
A46: T0045 | B46: TrustSquare | C46: Tags | D46: Iithegi
A47: T0046 | B47: TrustSquare | C47: Team | D47: Iqela
A48: T0047 | B48: TrustSquare | C48: Term | D48: Ixesha
A49: T0048 | B49: TrustSquare | C49: Tier | D49: Inqanaba
A50: T0049 | B50: TrustSquare | C50: bulk | D50: ngobuninzi
A51: T0050 | B51: TrustSquare | C51: this | D51: le
A52: T0051 | B52: TrustSquare | C52: All → | D52: Zonke →
... A54: T0053 | B54: TrustSquare | C54: Chess | D54: Itshesi
A55: T0054 | B55: TrustSquare | C55: Chile | D55: Chile | E55: Same as English (fine for names/brands)
A56: T0055 | B56: TrustSquare | C56: China | D56: iTshayina
A57: T0056 | B57: TrustSquare | C57: Class | D57: Udidi
A58: T0057 | B58: TrustSquare | C58: Clear | D58: Cima
A59: T0058 | B59: TrustSquare | C59: Egypt | D59: iYiputa
A60: T0059 | B60: TrustSquare | C60: Email | D60: I-imeyile
A61: T0060 | B61: TrustSquare | C61: Haiko | D61: Haiko | E61: Same as English (fine for names/brands)
A62: T0061 | B62: TrustSquare | C62: House | D62: Indlu
A63: T0062 | B63: TrustSquare | C63: India | D63: iIndiya
A64: T0063 | B64: TrustSquare | C64: Italy | D64: iItali
A65: T0064 | B65: TrustSquare | C65: Kenya | D65: iKenya
A66: T0065 | B66: TrustSquare | C66: Legal | D66: Ezomthetho
A67: T0066 | B67: TrustSquare | C67: Level | D67: Inqanaba
A68: T0067 | B68: TrustSquare | C68: Libya | D68: Libya | E68: Same as English (fine for names/brands)
A69: T0068 | B69: TrustSquare | C69: Music | D69: Umculo
A70: T0069 | B70: TrustSquare | C70: Nanny | D70: Umgcini-bantwana
A71: T0070 | B71: TrustSquare | C71: Other | D71: Okunye
A72: T0071 | B72: TrustSquare | C72: Paver | D72: Umbeki-zitena
A73: T0072 | B73: TrustSquare | C73: Plans | D73: Izicwangciso
A74: T0073 | B74: TrustSquare | C74: Price | D74: Ixabiso
A75: T0074 | B75: TrustSquare | C75: Reach | D75: Ukufikelela
A76: T0075 | B76: TrustSquare | C76: Roles | D76: Iindima
A77: T0076 | B77: TrustSquare | C77: Saved | D77: Kugciniwe
A78: T0077 | B78: TrustSquare | C78: Solar | D78: Ilanga (solar)
A79: T0078 | B79: TrustSquare | C79: Spain | D79: iSpeyin
A80: T0079 | B80: TrustSquare | C80: Stays | D80: Iindawo zokuhlala
A81: T0080 | B81: TrustSquare | C81: Study | D81: Funda
A82: T0081 | B82: TrustSquare | C82: Sudan | D82: Sudan | E82: Same as English (fine for names/brands)
A83: T0082 | B83: TrustSquare | C83: Syria | D83: iSiriya
A84: T0083 | B84: TrustSquare | C84: Tiler | D84: Umbeki-zithayile
A85: T0084 | B85: TrustSquare | C85: Title | D85: Isihloko
A86: T0085 | B86: TrustSquare | C86: Today | D86: Namhlanje
A87: T0086 | B87: TrustSquare | C87: Trust | D87: Ukuthembeka
A88: T0087 | B88: TrustSquare | C88: Yemen | D88: Yemen | E88: Same as English (fine for names/brands)
A89: T0088 | B89: TrustSquare | C89: Active | D89: Iyasebenza
A90: T0089 | B90: TrustSquare | C90: Agency | D90: I-arhente
A91: T0090 | B91: TrustSquare | C91: Ask me | D91: Ndibuze
A92: T0091 | B92: TrustSquare | C92: Babies | D92: Iintsana
A93: T0092 | B93: TrustSquare | C93: Boxing | D93: Amanqindi
A94: T0093 | B94: TrustSquare | C94: Brazil | D94: iBrazil
A95: T0094 | B95: TrustSquare | C95: Browse | D95: Khangela
A96: T0095 | B96: TrustSquare | C96: Bundle | D96: Iphakheji
A97: T0096 | B97: TrustSquare | C97: Canada | D97: iKhanada
A98: T0097 | B98: TrustSquare | C98: Cancel | D98: Rhoxisa
A99: T0098 | B99: TrustSquare | C99: Change | D99: Tshintsha
A100: T0099 | B100: TrustSquare | C100: Couple | D100: Isibini
... A117: T0116 | B117: TrustSquare | C117: Next → | D117: Okulandelayo →
A118: T0117 | B118: TrustSquare | C118: Norway | D118: Norway | E118: Same as English (fine for names/brands)
A119: T0118 | B119: TrustSquare | C119: Online | D119: Kwi-intanethi
A120: T0119 | B120: TrustSquare | C120: Open → | D120: Vula →
A121: T0120 | B121: TrustSquare | C121: Photos | D121: Iifoto
A122: T0121 | B122: TrustSquare | C122: Poland | D122: Poland | E122: Same as English (fine for names/brands)
...

Sheet Sepedi review
A1: ID | B1: App | C1: English (source) | D1: Current Sepedi | E1: Flag | F1: Corrected Sepedi | G1: Comment
A2: T0001 | B2: TrustSquare | C2: AI examples on | D2: Mehlala ya AI e butswe
A3: T0002 | B3: TrustSquare | C3: AI examples off | D3: Mehlala ya AI e timilwe
A4: T0003 | B4: TrustSquare | C4: AI examples are shown, below the real listings. | E4: Blank — app shows English
A5: T0004 | B5: TrustSquare | C5: AI examples are hidden. Only real listings show. | E5: Blank — app shows English
A6: T0005 | B6: TrustSquare | C6: Show AI examples | E6: Blank — app shows English
A7: T0006 | B7: TrustSquare | C7: Show or hide the AI example listings | E7: Blank — app shows English
A8: T0007 | B8: TrustSquare | C8: Me | D8: Nna
A9: T0008 | B9: TrustSquare | C9: No | D9: Aowa
A10: T0009 | B10: TrustSquare | C10: to | D10: go
A11: T0010 | B11: TrustSquare | C11: All | D11: Ka moka
A12: T0011 | B12: TrustSquare | C12: Any | D12: Efe goba efe
A13: T0012 | B13: TrustSquare | C13: Art | D13: Bokgabo
A14: T0013 | B14: TrustSquare | C14: Fri | D14: Hlan
A15: T0014 | B15: TrustSquare | C15: Mon | D15: Moš
A16: T0015 | B16: TrustSquare | C16: Sat | D16: Mok
A17: T0016 | B17: TrustSquare | C17: Sun | D17: Son
A18: T0017 | B18: TrustSquare | C18: Thu | D18: Ne
A19: T0018 | B19: TrustSquare | C19: Tue | D19: Bed
... A25: T0024 | B25: TrustSquare | C25: Back | D25: Morago
A26: T0025 | B26: TrustSquare | C26: Buzz | D26: Buzz | E26: Same as English (fine for names/brands)
A27: T0026 | B27: TrustSquare | C27: Cars | D27: Dikoloi
A28: T0027 | B28: TrustSquare | C28: Chef | D28: Shefo
A29: T0028 | B29: TrustSquare | C29: City | D29: Toropo
A30: T0029 | B30: TrustSquare | C30: Cook | D30: Moapei
A31: T0030 | B31: TrustSquare | C31: Cuba | D31: Cuba | E31: Same as English (fine for names/brands)
A32: T0031 | B32: TrustSquare | C32: Edit | D32: Fetola
A33: T0032 | B33: TrustSquare | C33: Farm | D33: Polase
A34: T0033 | B34: TrustSquare | C34: Free | D34: Mahala
A35: T0034 | B35: TrustSquare | C35: Home | D35: Gae
A36: T0035 | B36: TrustSquare | C36: Iraq | D36: Iraq | E36: Same as English (fine for names/brands)
A37: T0036 | B37: TrustSquare | C37: Make | D37: Dira
A38: T0037 | B38: TrustSquare | C38: Mode | D38: Mokgwa
A39: T0038 | B39: TrustSquare | C39: More | D39: Tše dingwe
A40: T0039 | B40: TrustSquare | C40: Oman | D40: Oman | E40: Same as English (fine for names/brands)
A41: T0040 | B41: TrustSquare | C41: Pool | D41: Bodiba bja go rutha
A42: T0041 | B42: TrustSquare | C42: Save | D42: Boloka
A43: T0042 | B43: TrustSquare | C43: Sell | D43: Rekiša
A44: T0043 | B44: TrustSquare | C44: Sent | D44: E rometšwe
A45: T0044 | B45: TrustSquare | C45: Solo | D45: Nnoši
A46: T0045 | B46: TrustSquare | C46: Tags | D46: Dileibole
A47: T0046 | B47: TrustSquare | C47: Team | D47: Sehlopha
A48: T0047 | B48: TrustSquare | C48: Term | D48: Nako ya tumelelano
A49: T0048 | B49: TrustSquare | C49: Tier | D49: Legato
A50: T0049 | B50: TrustSquare | C50: bulk | D50: ka bontši
A51: T0050 | B51: TrustSquare | C51: this | D51: se
A52: T0051 | B52: TrustSquare | C52: All → | D52: Ka moka →
A53: T0052 | B53: TrustSquare | C53: Buyer | D53: Moreki
A54: T0053 | B54: TrustSquare | C54: Chess | D54: Chess | E54: Same as English (fine for names/brands)
A55: T0054 | B55: TrustSquare | C55: Chile | D55: Chile | E55: Same as English (fine for names/brands)
A56: T0055 | B56: TrustSquare | C56: China | D56: China | E56: Same as English (fine for names/brands)
A57: T0056 | B57: TrustSquare | C57: Class | D57: Sehlopha
A58: T0057 | B58: TrustSquare | C58: Clear | D58: Phumola
A59: T0058 | B59: TrustSquare | C59: Egypt | D59: Egipita
A60: T0059 | B60: TrustSquare | C60: Email | D60: Imeile
A61: T0060 | B61: TrustSquare | C61: Haiko | D61: Haiko | E61: Same as English (fine for names/brands)
A62: T0061 | B62: TrustSquare | C62: House | D62: Ntlo
A63: T0062 | B63: TrustSquare | C63: India | D63: India | E63: Same as English (fine for names/brands)
A64: T0063 | B64: TrustSquare | C64: Italy | D64: Italy | E64: Same as English (fine for names/brands)
A65: T0064 | B65: TrustSquare | C65: Kenya | D65: Kenya | E65: Same as English (fine for names/brands)
A66: T0065 | B66: TrustSquare | C66: Legal | D66: Tša molao
A67: T0066 | B67: TrustSquare | C67: Level | D67: Legato
A68: T0067 | B68: TrustSquare | C68: Libya | D68: Libya | E68: Same as English (fine for names/brands)
A69: T0068 | B69: TrustSquare | C69: Music | D69: Mmino
A70: T0069 | B70: TrustSquare | C70: Nanny | D70: Mohlokomedi wa bana
A71: T0070 | B71: TrustSquare | C71: Other | D71: Tše dingwe
A72: T0071 | B72: TrustSquare | C72: Paver | D72: Mobei wa diphefi
A73: T0072 | B73: TrustSquare | C73: Plans | D73: Dipeakanyo
A74: T0073 | B74: TrustSquare | C74: Price | D74: Theko
A75: T0074 | B75: TrustSquare | C75: Reach | D75: Phihlelelo
A76: T0075 | B76: TrustSquare | C76: Roles | D76: Mediro
A77: T0076 | B77: TrustSquare | C77: Saved | D77: E bolokilwe
A78: T0077 | B78: TrustSquare | C78: Solar | D78: Letšatši
A79: T0078 | B79: TrustSquare | C79: Spain | D79: Spain | E79: Same as English (fine for names/brands)
A80: T0079 | B80: TrustSquare | C80: Stays | D80: Madulo
A81: T0080 | B81: TrustSquare | C81: Study | D81: Ithute
A82: T0081 | B82: TrustSquare | C82: Sudan | D82: Sudan | E82: Same as English (fine for names/brands)
A83: T0082 | B83: TrustSquare | C83: Syria | D83: Syria | E83: Same as English (fine for names/brands)
A84: T0083 | B84: TrustSquare | C84: Tiler | D84: Mobei wa dithaele
A85: T0084 | B85: TrustSquare | C85: Title | D85: Thaetlele
A86: T0085 | B86: TrustSquare | C86: Today | D86: Lehono
A87: T0086 | B87: TrustSquare | C87: Trust | D87: Tshepo
A88: T0087 | B88: TrustSquare | C88: Yemen | D88: Yemen | E88: Same as English (fine for names/brands)
A89: T0088 | B89: TrustSquare | C89: Active | D89: E a šoma
A90: T0089 | B90: TrustSquare | C90: Agency | D90: Etšensi
A91: T0090 | B91: TrustSquare | C91: Ask me | D91: Mpotšiše
A92: T0091 | B92: TrustSquare | C92: Babies | D92: Masea
A93: T0092 | B93: TrustSquare | C93: Boxing | D93: Ditebele
A94: T0093 | B94: TrustSquare | C94: Brazil | D94: Brazil | E94: Same as English (fine for names/brands)
A95: T0094 | B95: TrustSquare | C95: Browse | D95: Lebelela
A96: T0095 | B96: TrustSquare | C96: Bundle | D96: Sephuthelwa
A97: T0096 | B97: TrustSquare | C97: Canada | D97: Canada | E97: Same as English (fine for names/brands)
A98: T0097 | B98: TrustSquare | C98: Cancel | D98: Khansela
A99: T0098 | B99: TrustSquare | C99: Change | D99: Fetola
A100: T0099 | B100: TrustSquare | C100: Couple | D100: Banyalani
A101: T0100 | B101: TrustSquare | C101: Driver | D101: Mootledi
A102: T0101 | B102: TrustSquare | C102: Duplex | D102: Duplex | E102: Same as English (fine for names/brands)
A103: T0102 | B103: TrustSquare | C103: Either | D103: Efe goba efe
A104: T0103 | B104: TrustSquare | C104: Europe | D104: Yuropa
A105: T0104 | B105: TrustSquare | C105: Filter | D105: Sefa
...

Sheet Content & legal
A1: ID | B1: App | C1: Kind | D1: English (source) | E1: Afrikaans | F1: isiZulu | G1: isiXhosa | H1: Sepedi
A2: C0001 | B2: TrustSquare | C2: Content / legal / places | D2: Taj Mahal | F2: I-Taj Mahal
A3: C0002 | B3: TrustSquare | C3: Content / legal / places | D3: Machu Picchu | F3: I-Machu Picchu
A4: C0003 | B4: TrustSquare | C4: Content / legal / places | D4: Petra | F4: I-Petra
A5: C0004 | B5: TrustSquare | C5: Content / legal / places | D5: Angkor Wat | F5: I-Angkor Wat
A6: C0005 | B6: TrustSquare | C6: Content / legal / places | D6: Stonehenge | F6: I-Stonehenge
A7: C0006 | B7: TrustSquare | C7: Content / legal / places | D7: Mont-Saint-Michel | F7: I-Mont-Saint-Michel
A8: C0007 | B8: TrustSquare | C8: Content / legal / places | D8: Alhambra | F8: I-Alhambra
A9: C0008 | B9: TrustSquare | C9: Content / legal / places | D9: Chichen Itza | F9: I-Chichen Itza
A10: C0009 | B10: TrustSquare | C10: Content / legal / places | D10: Cappadocia (Göreme) | E10: Cappadocië (Göreme) | F10: I-Cappadocia (Göreme)
A11: C0010 | B11: TrustSquare | C11: Content / legal / places | D11: Jiuzhaigou Valley | E11: Jiuzhaigou-vallei | F11: I-Jiuzhaigou Valley
A12: C0011 | B12: TrustSquare | C12: Content / legal / places | D12: Timbuktu | E12: Timboektoe | F12: I-Timbuktu
A13: C0012 | B13: TrustSquare | C13: Content / legal / places | D13: Hagia Sophia, Istanbul | F13: I-Hagia Sophia, Istanbul
A14: C0013 | B14: TrustSquare | C14: Content / legal / places | D14: From A$540per night | E14: Van A$540per night
A15: C0014 | B15: TrustSquare | C15: Content / legal / places | D15: From £350per night | E15: Van £350per night
A16: C0015 | B16: TrustSquare | C16: Content / legal / places | D16: From $420per night | E16: Van $420per night
A17: C0016 | B17: TrustSquare | C17: Content / legal / places | D17: From €180per night | E17: Van €180per night
A18: C0017 | B18: TrustSquare | C18: Content / legal / places | D18: From KSh60,000per night | E18: Van KSh60,000per night
A19: C0018 | B19: TrustSquare | C19: Content / legal / places | D19: £95per person | E19: £95 per persoon
A20: C0019 | B20: TrustSquare | C20: Content / legal / places | D20: $180per person | E20: $180 per persoon
A21: C0020 | B21: TrustSquare | C21: Content / legal / places | D21: €1,450per person | E21: €1,450 per persoon
A22: C0021 | B22: TrustSquare | C22: Content / legal / places | D22: From KSh18,000per night | E22: Vanaf KSh18,000 per nag
A23: C0022 | B23: TrustSquare | C23: Content / legal / places | D23: R1,850per person | E23: R1,850 per persoon
A24: C0023 | B24: TrustSquare | C24: Content / legal / places | D24: A$5,900per person | E24: A$5,900 per persoon
A25: C0024 | B25: TrustSquare | C25: Content / legal / places | D25: £4,450per person | E25: £4,450 per persoon
... A45: C0044 | B45: TrustSquare | C45: Content / legal / places | D45: your city · narrow your search | E45: jou stad · vernou jou soektog
A46: C0045 | B46: TrustSquare | C46: Content / legal / places | D46: Sarek National Park | E46: Sarek Nasionale Park | F46: Isipala Sezimbali Se-Sarek | G46: iSarek National Park | H46: Phaka ya Bosetšhaba ya Sarek
A47: C0046 | B47: TrustSquare | C47: Content / legal / places | D47: Killarney National Park | E47: Killarney Nasionale Park | F47: Isipala Sezimbali SeKillarney | G47: iKillarney National Park | H47: Phaka ya Bosetšhaba ya Killarney
A48: C0047 | B48: TrustSquare | C48: Content / legal / places | D48: Doñana National Park | E48: Doñana Nasionale Park | F48: Isipala Sezimbali Se-Doñana | G48: iDoñana National Park | H48: Phaka ya Bosetšhaba ya Doñana
A49: C0048 | B49: TrustSquare | C49: Content / legal / places | D49: Gran Paradiso National Park | E49: Gran Paradiso Nasionale Park | F49: Isipala Sezimbali Se-Gran Paradiso | G49: iGran Paradiso National Park | H49: Phaka ya Bosetšhaba ya Gran Paradiso
A50: C0049 | B50: TrustSquare | C50: Content / legal / places | D50: Berchtesgaden National Park | E50: Berchtesgaden Nasionale Park | F50: Isipala Sezimbali SeeBerchtesgaden | G50: iBerchtesgaden National Park | H50: Phaka ya Bosetšhaba ya Berchtesgaden
A51: C0050 | B51: TrustSquare | C51: Content / legal / places | D51: Royal Chitwan National Park | E51: Royal Chitwan Nasionale Park | F51: Isipala Sezimbali SeRoyal Chitwan | G51: iRoyal Chitwan National Park | H51: Phaka ya Bosetšhaba ya Royal Chitwan
A52: C0051 | B52: TrustSquare | C52: Content / legal / places | D52: Zion National Park | E52: Zion Nasionale Park | F52: Isipala Sezimbali Se-Zion | G52: iZion National Park | H52: Phaka ya Bosetšhaba ya Zion
A53: C0052 | B53: TrustSquare | C53: Content / legal / places | D53: Glacier National Park (U.S.) | E53: Glacier Nasionale Park (U.S.) | F53: Isipala Sezimbali Se-Glacier | G53: iGlacier National Park (U.S.) | H53: Phaka ya Bosetšhaba ya Glacier (U.S.)
A54: C0053 | B54: TrustSquare | C54: Content / legal / places | D54: Jasper National Park | E54: Jasper Nasionale Park | F54: Isipala Sezimbali Se-Jasper | G54: iJasper National Park | H54: Phaka ya Bosetšhaba ya Jasper
A55: C0054 | B55: TrustSquare | C55: Content / legal / places | D55: Manuel Antonio National Park | E55: Manuel Antonio Nasionale Park | F55: Isipala Sezimbali SeManuel Antonio | G55: iManuel Antonio National Park | H55: Phaka ya Bosetšhaba ya Manuel Antonio
A56: C0055 | B56: TrustSquare | C56: Content / legal / places | D56: Louvre Museum | E56: Louvre-museum | G56: Imyuziyam yaseLouvre
A57: C0056 | B57: TrustSquare | C57: Content / legal / places | D57: Hermitage Museum | E57: Hermitage-museum | G57: Imyuziyam yaseHermitage
A58: C0057 | B58: TrustSquare | C58: Content / legal / places | D58: Pergamon Museum | E58: Pergamon-museum | F58: I-Pergamon Museum | G58: Imyuziyam yasePergamon
A59: C0058 | B59: TrustSquare | C59: Content / legal / places | D59: Historic Centre of Porto | E59: Historiese sentrum van Porto | F59: Indawo Yesikhathi Esasele YePorto | G59: Iziko Elidala lePorto | H59: Bogare bja Histori bja Porto
A60: C0059 | B60: TrustSquare | C60: Content / legal / places | D60: Historic Monuments of Ancient Kyoto | E60: Historiese monumente van antieke Kyoto | F60: Amamoniyumenti Esasele AeKyoto | G60: Izimonument Zamandulo zase-Kyoto Yamandulo | H60: Difika tša Histori tša Kyoto ya Bogologolo
A61: C0060 | B61: TrustSquare | C61: Content / legal / places | D61: All categories · New York | E61: Alle kategorieë · New York | F61: Zonke izigaba · New York
A62: C0061 | B62: TrustSquare | C62: Content / legal / places | D62: 29 listings found | E62: 29 lyste gevind | F62: 29 izikhangiso ezitholiwe
A63: C0062 | B63: TrustSquare | C63: Content / legal / places | D63: New York · narrow your search | E63: New York · vernou jou soektog | F63: New York · cisha okukhethiwe
A64: C0063 | B64: TrustSquare | C64: Content / legal / places | D64: AI EXAMPLE GENERATED ADVERT — not a real listing; an AI-made example of the benchmark for this category | E64: AI EXAMPLE GENERATED ADVERT — nie 'n regte advertensie nie; 'n AI-gemaakte voorbeeld van die maatstaf vir hierdie kategorie | F64: {AI EXAMPLE GENERATED ADVERT — not a real listing; an AI-made example of the benchmark for this category}
A65: C0064 | B65: TrustSquare | C65: Content / legal / places | D65: 0 · New · 40 · Established · 70 · Trusted · 90 · Highly Trusted | E65: 0 · Nuut · 40 · Gevestigd · 70 · Betroubaar · 90 · Hoogs Betroubaar | F65: 0 · {New} · 40 · {Established} · 70 · {Trusted} · 90 · {Highly Trusted}
A66: C0065 | B66: TrustSquare | C66: Content / legal / places | D66: Sunrise balloon flight over the Magaliesberg with sparkling-wine landing breakfast. Showcase advert: AI imagery; free for a real seller to claim and replace with their own product. | E66: Sunrise-ballonvlucht oor die Magaliesberg met sprankelwynlandingsontbyt. Showcase-advertensie: AI-beelde; gratis vir 'n regte verkoper om te eis en met hul eie produk te vervang. | F66: {Sunrise balloon flight over the Magaliesberg with sparkling-wine landing breakfast. Showcase advert: AI imagery; free for a real seller to claim and replace with their own product.}
A67: C0066 | B67: TrustSquare | C67: Content / legal / places | D67: Kunsthistorisches Museum | F67: Iziko Zekhonkwane Zekunst | G67: iKunsthistorisches Museum | H67: Musiamo wa Kunsthistorisches
A68: C0067 | B68: TrustSquare | C68: Content / legal / places | D68: Topkapı Palace Museum | E68: Topkapı-paleismuseum | F68: Iziko Lepalesi LeTopkapı | G68: iTopkapı Palace Museum | H68: Musiamo wa Mošate wa Topkapı
A69: C0068 | B69: TrustSquare | C69: Content / legal / places | D69: Victoria and Albert Museum | E69: Victoria en Albert-museum | F69: Iziko LeVictoria noAlbert | G69: iVictoria and Albert Museum | H69: Victoria le Albert Museum
A70: C0069 | B70: TrustSquare | C70: Content / legal / places | D70: Last checked 2026-08-21 | E70: Laas gekontroleer 2026-08-21 | F70: Kuphela kulandelwa ngo-2026-08-21
A71: C0070 | B71: TrustSquare | C71: Content / legal / places | D71: Leg 1 | E71: Been 1 | F71: Izingxenye 1
A72: C0071 | B72: TrustSquare | C72: Content / legal / places | D72: Pretoria — trip start | E72: Pretoria — reis begin | F72: Pretoria — umjako uqala
A73: C0072 | B73: TrustSquare | C73: Content / legal / places | D73: ≈ 1 h 10 to the dam | E73: ≈ 1 h 10 na die dam | F73: ≈ 1 h 10 kuya kudam
A74: C0073 | B74: TrustSquare | C74: Content / legal / places | D74: Leg 2 | E74: Been 2 | F74: Izingxenye 2
A75: C0074 | B75: TrustSquare | C75: Content / legal / places | D75: ≈ 45 min on | E75: ≈ 45 min aan | F75: ≈ 45 min kuhamba
A76: C0075 | B76: TrustSquare | C76: Content / legal / places | D76: Leg 3 | E76: Been 3 | F76: Izingxenye 3
A77: C0076 | B77: TrustSquare | C77: Content / legal / places | D77: ≈ 1 h 15 on | E77: ≈ 1 h 15 aan | F77: ≈ 1 h 15 kuhamba
A78: C0077 | B78: TrustSquare | C78: Content / legal / places | D78: Leg 4 | E78: Been 4 | F78: Izingxenye 4
A79: C0078 | B79: TrustSquare | C79: Content / legal / places | D79: Gates open at sunrise | E79: Poorte oop by sonopkoms | F79: Amageyiti avuleka ekuseni
A80: C0079 | B80: TrustSquare | C80: Content / legal / places | D80: Butrint | F80: i-Butrint
A81: C0080 | B81: TrustSquare | C81: Content / legal / places | D81: Delphi | F81: i-Delphi
A82: C0081 | B82: TrustSquare | C82: Content / legal / places | D82: Herculaneum | F82: i-Herculaneum
A83: C0082 | B83: TrustSquare | C83: Content / legal / places | D83: Chan Chan | F83: i-Chan Chan
A84: C0083 | B84: TrustSquare | C84: Content / legal / places | D84: Nazca Lines | E84: Nazca-lyne | F84: i-Nazca Lines
A85: C0084 | B85: TrustSquare | C85: Content / legal / places | D85: Cahokia | F85: i-Cahokia
A86: C0085 | B86: TrustSquare | C86: Content / legal / places | D86: Knossos | F86: i-Knossos
A87: C0086 | B87: TrustSquare | C87: Content / legal / places | D87: Mycenae | F87: i-Mycenae
A88: C0087 | B88: TrustSquare | C88: Content / legal / places | D88: Palmyra | F88: i-Palmyra
A89: C0088 | B89: TrustSquare | C89: Content / legal / places | D89: Hattusa | F89: i-Hattusa
A90: C0089 | B90: TrustSquare | C90: Content / legal / places | D90: Monte Albán | F90: i-Monte Albán
A91: C0090 | B91: TrustSquare | C91: Content / legal / places | D91: Palenque | F91: i-Palenque
A92: C0091 | B92: TrustSquare | C92: Content / legal / places | D92: Copán | F92: i-Copán
A93: C0092 | B93: TrustSquare | C93: Content / legal / places | D93: Honduras | F93: i-Honduras
A94: C0093 | B94: TrustSquare | C94: Content / legal / places | D94: Anuradhapura | F94: i-Anuradhapura
A95: C0094 | B95: TrustSquare | C95: Content / legal / places | D95: Polonnaruwa | F95: i-Polonnaruwa
A96: C0095 | B96: TrustSquare | C96: Content / legal / places | D96: Volubilis | F96: i-Volubilis
A97: C0096 | B97: TrustSquare | C97: Content / legal / places | D97: Te Papa Tongarewa | F97: i-Te Papa Tongarewa | G97: iTe Papa Tongarewa
A98: C0097 | B98: TrustSquare | C98: Content / legal / places | D98: Yakushima | F98: i-Yakushima
A99: C0098 | B99: TrustSquare | C99: Content / legal / places | D99: Tiwanaku | F99: i-Tiwanaku
A100: C0099 | B100: TrustSquare | C100: Content / legal / places | D100: Self-drive · ~170 km each way · 2–3 days · Big-5 reserve, MALARIA-FREE | E100: Self-ry · ~170 km eenrigtingverkeer · 2–3 dae · Big-5-reserwe, MALARIA-VRY | F100: Ikhudi lakho · ~170 km ikhethelo ngalinye · izinsuku 2–3 · Irezebi le-Big-5, KUKHULA NGESONKA
A101: C0100 | B101: TrustSquare | C101: Content / legal / places | D101: Two SA adults, own car, one night out, Aug 2026 prices. Conservation and toll figures verified; accommodation is the advert's own rate. | E101: Twee SA-volwassenes, eie motor, een nag uit, Aug 2026-pryse. Bewaring en toltariewe geverifieer; akkommodasie is die advertensie se eie tarief. | F101: Izintombazane ezimbili zase-SA, imodeli yakho, ubusuku obunye, intengo ka-Aug 2026. Conservation and toll figures verified; accommodation is the advert's own rate.
A102: C0101 | B102: TrustSquare | C102: Content / legal / places | D102: Pilanesberg gate — SA adult | E102: Pilanesberg-poort — SA-volwassene | F102: Pilanesberg gate — umuntu omkhulu wase-SA
A103: C0102 | B103: TrustSquare | C103: Content / legal / places | D103: R168 per person per day | E103: R168 per persoon per dag | F103: R168 ngomuntu ngosuku
A104: C0103 | B104: TrustSquare | C104: Content / legal / places | D104: Pilanesberg gate — vehicle | E104: Pilanesberg-poort — voertuig | F104: Pilanesberg gate — imoto
A105: C0104 | B105: TrustSquare | C105: Content / legal / places | D105: R168 per sedan / LDV / SUV per day | E105: R168 per sedan / LDV / SUV per dag | F105: R168 nge-sedan / LDV / SUV ngosuku
A106: C0105 | B106: TrustSquare | C106: Content / legal / places | D106: ≈ R39 each way | E106: ≈ R39 eenrigtingverkeer | F106: ≈ R39 ikhethelo ngalinye
A107: C0106 | B107: TrustSquare | C107: Content / legal / places | D107: Union Buildings lawns, fuel and padkos before you go. Voortrekker Monument is a short detour south. | E107: Union Buildings-grasveld, brandstof en padkos voordat jy gaan. Voortrekker Monument is 'n kort omweg suid. | F107: Union Buildings lawns, fuel kanye padkos ngaphambi kokuthi uhambe. Voortrekker Monument ikunlwandle okufushane eningizimu.
A108: C0107 | B108: TrustSquare | C108: Content / legal / places | D108: Mausoleum of the First Qin Emperor (Terracotta Army) | E108: Mausoleum van die eerste Qin-keiser (Terracottaleër) | F108: Inzalo yoMnumzane Wokuqala we-Qin (Terracotta Army) | G108: Ingcwaba loMlawuli wokuqala waseQin (Terracotta Army) | H108: Lebitla la Moemphera wa Pele wa Qin (Madira a Terracotta)
A109: C0108 | B109: TrustSquare | C109: Content / legal / places | D109: Dam-wall viewpoint and the curio market. Maropeng and the Sterkfontein caves (UNESCO Cradle of Humankind) sit south of here if you want the heritage day. | E109: Dam-muuruitkykpunt en die kunstemarkta. Maropeng en die Sterkfontein-grotte (UNESCO Wieg van die Mensdom) sit hier suid as jy die erfenisdag wil hê. | F109: I-dam-wall viewpoint kanye nemarket yamacurio. Maropeng kanye neSterkfontein caves (UNESCO Cradle of Humankind) zihlala eningizimu lapha uma ufuna heritage day.
A110: C0109 | B110: TrustSquare | C110: Content / legal / places | D110: Scenic crossing with picnic spots. Last easy fuel and shops before the reserve. | E110: Skone oorsteek met pikniekplekke. Laaste maklike brandstof en winkels voor die reserwe. | F110: Ukuvuka okumnandi ngezikhundla zokupiknika. Amafueli nokutengisa okwamakhulu phambi kwe-reserve.
A111: C0110 | B111: TrustSquare | C111: Content / legal / places | D111: Big-5 reserve, self-drive game viewing on 200+ km of maintained gravel and tar. A sedan is fine — no 4x4 needed. | E111: Big-5-reserwe, self-ry wildbeskouing op 200+ km van onderhoudde gruis en teer. 'n Sedan is goed — geen 4x4 nodig. | F111: I-Big-5 reserve, zibonele izilwane ngezigwili zakho kukhona 200+ km yokugranulwa nokuthalathalala. I-sedan ilungile — ayikho i-4x4 edingekayo.
A112: C0111 | B112: TrustSquare | C112: Content / legal / places | D112: SA ID must be shown for the resident rate. SADC R385, international R748. Tariff effective 1 Dec 2025. | E112: SA-ID moet vir die inwonerstarief getoon word. SADC R385, internasionaal R748. Tarief van krag 1 Des 2025. | F112: SA ID kufanele ikhuphe izindlela zoku-resident. SADC R385, international R748. Imali ephumelelayo ngo-1 Dec 2025.
A113: C0112 | B113: TrustSquare | C113: Content / legal / places | D113: Doornpoort R19.50 + Brits R19.50, Class 1, from 1 Mar 2026. Gauteng e-tolls are dead — no tag needed. | E113: Doornpoort R19.50 + Brits R19.50, Klas 1, vanaf 1 Mrt 2026. Gauteng e-tolle is dood — geen etiket nodig. | F113: Doornpoort R19.50 + Brits R19.50, Isigaba 1, kusuka 1 Mar 2026. I-Gauteng e-tolls isile — i-tag ayidingeki.
A114: C0113 | B114: TrustSquare | C114: Content / legal / places | D114: ≈ 340 km round trip | E114: ≈ 340 km heen-en-terug | F114: ≈ 340 km indlela iphindwe kabili
A115: C0114 | B115: TrustSquare | C115: Content / legal / places | D115: Attendant-served. Most take cards, a minority are cash-only — carry some cash. | E115: Bediende word jou. Meeste neem kaarte, sommige net kontant — neem 'n bietjie kontant saam. | F115: Isebenzi elisikhethile. Iningi lithathe amakhadi, abambalwa abayisipho kuphela — thwala imali.
A116: C0115 | B116: TrustSquare | C116: Content / legal / places | D116: From R2,450 / night (Thatch & Bushveld, 15 min from Manyane Gate) | E116: Van R2,450 / nag (Thatch & Bushveld, 15 min vanaf Manyane Gate) | F116: Kusukela ku-R2,450 / ubusuku (Thatch & Bushveld, 15 min kusuka ku-Manyane Gate)
A117: C0116 | B117: TrustSquare | C117: Content / legal / places | D117: This advert's own rate. Ask for an introduction below. | E117: Hierdie advertensie se eie tarief. Vra vir 'n bekendstelling hieronder. | F117: Intengo yeshumeka. Cela isingeniso ngezansi.
A118: C0117 | B118: TrustSquare | C118: Content / legal / places | D118: Tips | E118: Fooi | F118: Amathiphu
A119: C0118 | B119: TrustSquare | C119: Content / legal / places | D119: Petrol attendant R5–R10 · car guard R5–R10 · restaurant 10–15% | E119: Petrol bedienaar R5–R10 · motor wag R5–R10 · restaurant 10–15% | F119: Umuntu othengisa iflanga R5–R10 · umlindi wemoto R5–R10 · indawo yokudla 10–15%
...

Sheet Kept in English
A1: English (leave as is)
A2: 1 Tuppence ($2) deducted only on seller acceptance
A3: 1. Definitions & Interpretation
A4: 1. Tuppence is non-refundable platform currency.
A5: 1.1 Definitions
A6: 1.2 Interpretation
A7: 10. Disputes, Enforcement & Liability
A8: 10.1 User Disputes
A9: 10.2 Platform Enforcement
A10: 10.3 Pre-Dispute Negotiation (60 Days)
A11: 10.4 Binding Arbitration
A12: 10.5 Consumer Protection Act Override
... A507: ⚠️ These were read from your photos — nothing was looked up in a vehicle database. On less common models the AI can be confidently wrong, so please check every figure against your own papers before confirming.
